Workbook

Sheet Gráficos

Sheet 1. Ramos Totales
A1: Sector Asegurador Hondureño
A2: Situación de Primas y Siniestros por Ramo
A3: Al 31 de diciembre de 2025
A4: (Valores en millones de Lempiras y Porcentajes)
A6: 1. Ramos Totales
A8: Rubro | B8: PRIMAS | F8: SINIESTROS | J8: Siniestros/Primas | N8: Participación de mercado
B9: 45657 | C9: 46022 | D9: Relativa | E9: Absoluta | F9: =B9 -> 45657 | G9: =C9 -> 46022 | H9: Relativa | I9: Absoluta | J9: =B9 -> 45657 | K9: =C9 -> 46022 | L9: Relativa | M9: Absoluta | N9: =B9 -> 45657 | O9: =C9 -> 46022 | P9: Relativa | Q9: Absoluta
A10: Vida | B10: ='Primas Diciembre 2024'!D51/1000 -> 6507.7859 | C10: ='Primas Diciembre 2025'!B51/1000 -> 6900.9688 | D10: =IFERROR(E10/B10,0%) -> 0.060417307 | E10: =IFERROR(C10-B10,0) -> 393.1829 | F10: ='Siniestros Diciembre 2024'!E51/1000 -> 1797.332 | G10: ='Siniestros Diciembre 2025'!B51/1000 -> 2010.424 | H10: =IFERROR(I10/F10,0%) -> 0.1185602 | I10: =IFERROR(G10-F10,0) -> 213.09203 | J10: =IFERROR((F10/B10),0%) -> 0.27618179 | K10: =IFERROR(G10/C10,0%) -> 0.2913249 | L10: =IFERROR(M10/J10,0%) -> 0.054830195 | M10: =K10-J10 -> 0.015143102 | N10: =B10/$B$21 -> 0.35288353 | O10: =C10/$C$21 -> 0.3419413 | P10: =IFERROR(Q10/N10,0%) -> -0.031008044 | Q10: =IFERROR(O10-N10,0) -> -0.010942228
A11: Vida Individual | B11: ='Primas Diciembre 2024'!D55/1000 -> 904.40902 | C11: ='Primas Diciembre 2025'!B55/1000 -> 957.52387 | D11: =IFERROR(E11/B11,0%) -> 0.058728791 | E11: =IFERROR(C11-B11,0) -> 53.114848 | F11: ='Siniestros Diciembre 2024'!E55/1000 -> 196.62319 | G11: ='Siniestros Diciembre 2025'!B55/1000 -> 272.35245 | H11: =IFERROR(I11/F11,0%) -> 0.38514916 | I11: =IFERROR(G11-F11,0) -> 75.729258 | J11: =IFERROR((F11/B11),0%) -> 0.21740517 | K11: =IFERROR(G11/C11,0%) -> 0.28443411 | L11: =IFERROR(M11/J11,0%) -> 0.30831349 | M11: =K11-J11 -> 0.067028946 | N11: =B11/$B$21 -> 0.049041417 | O11: =C11/$C$21 -> 0.047445071 | P11: =IFERROR(Q11/N11,0%) -> -0.032550983 | Q11: =IFERROR(O11-N11,0) -> -0.0015963463
A12: Vida Colectivo | B12: ='Primas Diciembre 2024'!D54/1000 -> 5589.6173 | C12: ='Primas Diciembre 2025'!B54/1000 -> 5929.7598 | D12: =IFERROR(E12/B12,0%) -> 0.060852565 | E12: =IFERROR(C12-B12,0) -> 340.14255 | F12: ='Siniestros Diciembre 2024'!E54/1000 -> 1590.688 | G12: ='Siniestros Diciembre 2025'!B54/1000 -> 1729.9776 | H12: =IFERROR(I12/F12,0%) -> 0.087565582 | I12: =IFERROR(G12-F12,0) -> 139.28952 | J12: =IFERROR((F12/B12),0%) -> 0.28457906 | K12: =IFERROR(G12/C12,0%) -> 0.29174497 | L12: =IFERROR(M12/J12,0%) -> 0.025180706 | M12: =K12-J12 -> 0.0071659017 | N12: =B12/$B$21 -> 0.303096 | O12: =C12/$C$21 -> 0.29381813 | P12: =IFERROR(Q12/N12,0%) -> -0.030610313 | Q12: =IFERROR(O12-N12,0) -> -0.0092778632
A13: Accidentes y Enfermedades | B13: ='Primas Diciembre 2024'!D12/1000 -> 3667.9374 | C13: ='Primas Diciembre 2025'!B12/1000 -> 4050.0066 | D13: =IFERROR(E13/B13,0%) -> 0.10416457 | E13: =IFERROR(C13-B13,0) -> 382.06912 | F13: ='Siniestros Diciembre 2024'!E12/1000 -> 2523.8946 | G13: ='Siniestros Diciembre 2025'!B12/1000 -> 2764.2953 | H13: =IFERROR(I13/F13,0%) -> 0.095249906 | I13: =IFERROR(G13-F13,0) -> 240.40072 | J13: =IFERROR((F13/B13),0%) -> 0.68809641 | K13: =IFERROR(G13/C13,0%) -> 0.68254094 | L13: =IFERROR(M13/J13,0%) -> -0.0080736723 | M13: =K13-J13 -> -0.0055554649 | N13: =B13/$B$21 -> 0.19889325 | O13: =C13/$C$21 -> 0.20067682 | P13: =IFERROR(Q13/N13,0%) -> 0.0089674863 | Q13: =IFERROR(O13-N13,0) -> 0.0017835725
A14: Accidentes Personales | B14: ='Primas Diciembre 2024'!D14/1000 -> 413.14882 | C14: ='Primas Diciembre 2025'!B14/1000 -> 510.89209 | D14: =IFERROR(E14/B14,0%) -> 0.23658127 | E14: =IFERROR(C14-B14,0) -> 97.743271 | F14: ='Siniestros Diciembre 2024'!E14/1000 -> 76.625171 | G14: ='Siniestros Diciembre 2025'!B14/1000 -> 92.908461 | H14: =IFERROR(I14/F14,0%) -> 0.21250576 | I14: =IFERROR(G14-F14,0) -> 16.28329 | J14: =IFERROR((F14/B14),0%) -> 0.18546627 | K14: =IFERROR(G14/C14,0%) -> 0.18185535 | L14: =IFERROR(M14/J14,0%) -> -0.019469413 | M14: =K14-J14 -> -0.0036109195 | N14: =B14/$B$21 -> 0.022402921 | O14: =C14/$C$21 -> 0.025314577 | P14: =IFERROR(Q14/N14,0%) -> 0.1299677 | Q14: =IFERROR(O14-N14,0) -> 0.002911656
A15: Salud y Hospitalización | B15: ='Primas Diciembre 2024'!D15/1000 -> 3246.0557 | C15: ='Primas Diciembre 2025'!B15/1000 -> 3528.053 | D15: =IFERROR(E15/B15,0%) -> 0.086873818 | E15: =IFERROR(C15-B15,0) -> 281.99725 | F15: ='Siniestros Diciembre 2024'!E15/1000 -> 2443.8482 | G15: ='Siniestros Diciembre 2025'!B15/1000 -> 2666.7692 | H15: =IFERROR(I15/F15,0%) -> 0.091217207 | I15: =IFERROR(G15-F15,0) -> 222.92101 | J15: =IFERROR((F15/B15),0%) -> 0.75286699 | K15: =IFERROR(G15/C15,0%) -> 0.75587562 | L15: =IFERROR(M15/J15,0%) -> 0.0039962221 | M15: =K15-J15 -> 0.0030086237 | N15: =B15/$B$21 -> 0.17601679 | O15: =C15/$C$21 -> 0.17481415 | P15: =IFERROR(Q15/N15,0%) -> -0.0068325183 | Q15: =IFERROR(O15-N15,0) -> -0.0012026379
A16: Seguros Generales | B16: ='Primas Diciembre 2024'!D57/1000 -> 6413.4995 | C16: ='Primas Diciembre 2025'!B57/1000 -> 7125.184 | D16: =IFERROR(E16/B16,0%) -> 0.11096665 | E16: =IFERROR(C16-B16,0) -> 711.68453 | F16: ='Siniestros Diciembre 2024'!E57/1000 -> 2688.53 | G16: ='Siniestros Diciembre 2025'!B57/1000 -> 3568.6455 | H16: =IFERROR(I16/F16,0%) -> 0.32735937 | I16: =IFERROR(G16-F16,0) -> 880.11549 | J16: =IFERROR((F16/B16),0%) -> 0.4191986 | K16: =IFERROR(G16/C16,0%) -> 0.50084959 | L16: =IFERROR(M16/J16,0%) -> 0.19477878 | M16: =K16-J16 -> 0.081650991 | N16: =B16/$B$21 -> 0.34777086 | O16: =C16/$C$21 -> 0.35305111 | P16: =IFERROR(Q16/N16,0%) -> 0.015183113 | Q16: =IFERROR(O16-N16,0) -> 0.0052802445
A17: Incendio y Líneas Aliadas | B17: ='Primas Diciembre 2024'!D58/1000 -> 3597.3025 | C17: ='Primas Diciembre 2025'!B58/1000 -> 3994.6503 | D17: =IFERROR(E17/B17,0%) -> 0.11045717 | E17: =IFERROR(C17-B17,0) -> 397.34786 | F17: ='Siniestros Diciembre 2024'!E58/1000 -> 1028.7882 | G17: ='Siniestros Diciembre 2025'!B58/1000 -> 1697.7849 | H17: =IFERROR(I17/F17,0%) -> 0.65027641 | I17: =IFERROR(G17-F17,0) -> 668.99669 | J17: =IFERROR((F17/B17),0%) -> 0.28598879 | K17: =IFERROR(G17/C17,0%) -> 0.42501464 | L17: =IFERROR(M17/J17,0%) -> 0.48612342 | M17: =K17-J17 -> 0.13902585 | N17: =B17/$B$21 -> 0.19506308 | O17: =C17/$C$21 -> 0.19793394 | P17: =IFERROR(Q17/N17,0%) -> 0.014717566 | Q17: =IFERROR(O17-N17,0) -> 0.0028708537
A18: Vehículos Automotores | B18: ='Primas Diciembre 2024'!D59/1000 -> 2816.197 | C18: ='Primas Diciembre 2025'!B59/1000 -> 3130.5337 | D18: =IFERROR(E18/B18,0%) -> 0.11161743 | E18: =IFERROR(C18-B18,0) -> 314.33667 | F18: ='Siniestros Diciembre 2024'!E59/1000 -> 1659.7411 | G18: ='Siniestros Diciembre 2025'!B59/1000 -> 1870.8606 | H18: =IFERROR(I18/F18,0%) -> 0.12720026 | I18: =IFERROR(G18-F18,0) -> 211.1195 | J18: =IFERROR((F18/B18),0%) -> 0.58935547 | K18: =IFERROR(G18/C18,0%) -> 0.59761715 | L18: =IFERROR(M18/J18,0%) -> 0.014018162 | M18: =K18-J18 -> 0.0082616802 | N18: =B18/$B$21 -> 0.15270778 | O18: =C18/$C$21 -> 0.15511717 | P18: =IFERROR(Q18/N18,0%) -> 0.015777786 | Q18: =IFERROR(O18-N18,0) -> 0.0024093908
A19: Otros Seguros Generales | B19: ='Primas Diciembre 2024'!D22/1000 -> 1619.8638 | C19: ='Primas Diciembre 2025'!B22/1000 -> 1811.7784 | D19: =IFERROR(E19/B19,0%) -> 0.1184758 | E19: =IFERROR(C19-B19,0) -> 191.91465 | F19: ='Siniestros Diciembre 2024'!E22/1000 -> 557.16199 | G19: ='Siniestros Diciembre 2025'!B22/1000 -> 422.17715 | H19: =IFERROR(I19/F19,0%) -> -0.24227216 | I19: =IFERROR(G19-F19,0) -> -134.98484 | J19: =IFERROR((F19/B19),0%) -> 0.34395608 | K19: =IFERROR(G19/C19,0%) -> 0.23301809 | L19: =IFERROR(M19/J19,0%) -> -0.32253533 | M19: =K19-J19 -> -0.11093799 | N19: =B19/$B$21 -> 0.087836824 | O19: =C19/$C$21 -> 0.089773174 | P19: =IFERROR(Q19/N19,0%) -> 0.022044853 | Q19: =IFERROR(O19-N19,0) -> 0.0019363498
A20: Fianzas | B20: ='Primas Diciembre 2024'!D17/1000 -> 232.65236 | C20: ='Primas Diciembre 2025'!B17/1000 -> 293.7975 | D20: =IFERROR(E20/B20,0%) -> 0.26281764 | E20: =IFERROR(C20-B20,0) -> 61.145145 | F20: ='Siniestros Diciembre 2024'!E17/1000 -> 10.491704 | G20: ='Siniestros Diciembre 2025'!B17/1000 -> 41.792077 | H20: =IFERROR(I20/F20,0%) -> 2.9833449 | I20: =IFERROR(G20-F20,0) -> 31.300373 | J20: =IFERROR((F20/B20),0%) -> 0.045096058 | K20: =IFERROR(G20/C20,0%) -> 0.1422479 | L20: =IFERROR(M20/J20,0%) -> 2.1543311 | M20: =K20-J20 -> 0.097151839 | N20: =B20/$B$21 -> 0.012615533 | O20: =C20/$C$21 -> 0.014557594 | P20: =IFERROR(Q20/N20,0%) -> 0.15394207 | Q20: =IFERROR(O20-N20,0) -> 0.0019420611
A21: Totales | B21: ='Primas Diciembre 2024'!D61/1000 -> 18441.739 | C21: ='Primas Diciembre 2025'!B61/1000 -> 20181.735 | D21: =C21/B21-1 -> 0.094350991 | E21: =C21-B21 -> 1739.9963 | F21: ='Siniestros Diciembre 2024'!E61/1000 -> 7577.4097 | G21: ='Siniestros Diciembre 2025'!B61/1000 -> 8807.9031 | H21: =G21/F21-1 -> 0.16238971 | I21: =+G21-F21 -> 1230.4934 | J21: =IFERROR((F21/B21),0%) -> 0.41088369 | K21: =IFERROR(G21/C21,0%) -> 0.43642942 | L21: =IFERROR(M21/J21,0%) -> 0.062172668 | M21: =K21-J21 -> 0.025545735 | N21: =B21/$B$21 -> 1 | O21: =C21/$C$21 -> 1 | P21: =IFERROR(Q21/N21,0%) -> 0 | Q21: =IFERROR(O21-N21,0) -> 0
A22: En millones de USD | B22: =B21/B27 -> 742.73825 | C22: =C21/C27 -> 776.23253 | D22: =C22/B22-1 -> 0.04509567 | E22: =C22-B22 -> 33.494279 | F22: =F21/B27 -> 305.17903 | G22: =G21/C27 -> 338.77071 | H22: =G22/F22-1 -> 0.11007206 | I22: =+G22-F22 -> 33.591683
A24: Inflación Interanual Diciembre 2025 | D24: 0.0498 | F24: Inflación Acumulada Diciembre 2025 | J24: 0.0498
A25: Crecimiento Real | D25: =D21-D24 -> 0.044550991
A27: Tasa de Cambio (compra, promedio cierre mensual) | B27: 24.829392 | C27: 25.9996
A29: 1. Ramos Totales (USD)
A31: Rubro | B31: PRIMAS | F31: SINIESTROS
B32: 45657 | C32: 46022 | D32: Relativa | E32: Absoluta | F32: =B32 -> 45657 | G32: =C32 -> 46022 | H32: Relativa | I32: Absoluta
A33: Vida | B33: =B10/$B$27 -> 262.1001 | C33: =C10/$C$27 -> 265.42596 | D33: =IFERROR(E33/B33,0%) -> 0.012689297 | E33: =IFERROR(C33-B33,0) -> 3.325866 | F33: =F10/$B$27 -> 72.387275 | G33: =G10/$C$27 -> 77.325191 | H33: =IFERROR(I33/F33,0%) -> 0.068215249 | I33: =IFERROR(G33-F33,0) -> 4.937916
A34: Vida Individual | B34: =B11/$B$27 -> 36.424937 | C34: =C11/$C$27 -> 36.828408 | D34: =IFERROR(E34/B34,0%) -> 0.011076778 | E34: =IFERROR(C34-B34,0) -> 0.40347095 | F34: =F11/$B$27 -> 7.9189694 | G34: =G11/$C$27 -> 10.475255 | H34: =IFERROR(I34/F34,0%) -> 0.32280539 | I34: =IFERROR(G34-F34,0) -> 2.556286
A35: Vida Colectivo | B35: =B12/$B$27 -> 225.12099 | C35: =C12/$C$27 -> 228.07119 | D35: =IFERROR(E35/B35,0%) -> 0.013104965 | E35: =IFERROR(C35-B35,0) -> 2.9502026 | F35: =F12/$B$27 -> 64.064721 | G35: =G12/$C$27 -> 66.538623 | H35: =IFERROR(I35/F35,0%) -> 0.038615663 | I35: =IFERROR(G35-F35,0) -> 2.4739017
A36: Accidentes y Enfermedades | B36: =B13/$B$27 -> 147.72563 | C36: =C13/$C$27 -> 155.77188 | D36: =IFERROR(E36/B36,0%) -> 0.054467551 | E36: =IFERROR(C36-B36,0) -> 8.0462531 | F36: =F13/$B$27 -> 101.64947 | G36: =G13/$C$27 -> 106.32069 | H36: =IFERROR(I36/F36,0%) -> 0.045954126 | I36: =IFERROR(G36-F36,0) -> 4.6712126
A37: Accidentes Personales | B37: =B14/$B$27 -> 16.639506 | C37: =C14/$C$27 -> 19.649998 | D37: =IFERROR(E37/B37,0%) -> 0.18092435 | E37: =IFERROR(C37-B37,0) -> 3.0104918 | F37: =F14/$B$27 -> 3.0860672 | G37: =G14/$C$27 -> 3.5734573 | H37: =IFERROR(I37/F37,0%) -> 0.15793244 | I37: =IFERROR(G37-F37,0) -> 0.48739013
A38: Salud y Hospitalización | B38: =B15/$B$27 -> 130.7344 | C38: =C15/$C$27 -> 135.69643 | D38: =IFERROR(E38/B38,0%) -> 0.037955035 | E38: =IFERROR(C38-B38,0) -> 4.9620288 | F38: =F15/$B$27 -> 98.425617 | G38: =G15/$C$27 -> 102.56962 | H38: =IFERROR(I38/F38,0%) -> 0.042102933 | I38: =IFERROR(G38-F38,0) -> 4.1440072
A39: Seguros Generales | B39: =B16/$B$27 -> 258.30272 | C39: =C16/$C$27 -> 274.04976 | D39: =IFERROR(E39/B39,0%) -> 0.060963476 | E39: =IFERROR(C39-B39,0) -> 15.747032 | F39: =F16/$B$27 -> 108.28014 | G39: =G16/$C$27 -> 137.25771 | H39: =IFERROR(I39/F39,0%) -> 0.26761664 | I39: =IFERROR(G39-F39,0) -> 28.977568
A40: Incendio y Líneas Aliadas | B40: =B17/$B$27 -> 144.88081 | C40: =C17/$C$27 -> 153.64276 | D40: =IFERROR(E40/B40,0%) -> 0.060476934 | E40: =IFERROR(C40-B40,0) -> 8.7619474 | F40: =F17/$B$27 -> 41.434289 | G40: =G17/$C$27 -> 65.300423 | H40: =IFERROR(I40/F40,0%) -> 0.57599961 | I40: =IFERROR(G40-F40,0) -> 23.866134
A41: Vehículos Automotores | B41: =B18/$B$27 -> 113.42191 | C41: =C18/$C$27 -> 120.40699 | D41: =IFERROR(E41/B41,0%) -> 0.061584966 | E41: =IFERROR(C41-B41,0) -> 6.9850845 | F41: =F18/$B$27 -> 66.845823 | G41: =G18/$C$27 -> 71.957285 | H41: =IFERROR(I41/F41,0%) -> 0.076466436 | I41: =IFERROR(G41-F41,0) -> 5.1114619
A42: Otros Seguros Generales | B42: =B19/$B$27 -> 65.239769 | C42: =C19/$C$27 -> 69.684858 | D42: =IFERROR(E42/B42,0%) -> 0.06813465 | E42: =IFERROR(C42-B42,0) -> 4.4450888 | F42: =F19/$B$27 -> 22.439615 | G42: =G19/$C$27 -> 16.237833 | H42: =IFERROR(I42/F42,0%) -> -0.27637651 | I42: =IFERROR(G42-F42,0) -> -6.2017826
A43: Fianzas | B43: =B20/$B$27 -> 9.3700386 | C43: =C20/$C$27 -> 11.300078 | D43: =IFERROR(E43/B43,0%) -> 0.20597986 | E43: =IFERROR(C43-B43,0) -> 1.9300392 | F43: =F20/$B$27 -> 0.4225518 | G43: =G20/$C$27 -> 1.6074123 | H43: =IFERROR(I43/F43,0%) -> 2.8040597 | I43: =IFERROR(G43-F43,0) -> 1.1848605
A44: Totales | B44: =B21/B27 -> 742.73825 | C44: =C21/C27 -> 776.23253 | D44: =C44/B44-1 -> 0.04509567 | E44: =C44-B44 -> 33.494279 | F44: =F21/B27 -> 305.17903 | G44: =G21/C27 -> 338.77071 | H44: =G44/F44-1 -> 0.11007206 | I44: =+G44-F44 -> 33.591683

Sheet 2. Vida
A1: Sector Asegurador Hondureño
A2: Situación de Primas y Siniestros por Ramo
A3: ='1. Ramos Totales'!A3 -> Al 31 de diciembre de 2025
A4: (Valores en millones de Lempiras y Porcentajes)
A6: 2. Vida
A8: No. | B8: Compañía | C8: Primas | G8: Siniestros | K8: Siniestros/Primas | O8: Participación de mercado
C9: ='1. Ramos Totales'!$B$9 -> 45657 | D9: ='1. Ramos Totales'!$C$9 -> 46022 | E9: Relativa | F9: Absoluta | G9: ='1. Ramos Totales'!$B$9 -> 45657 | H9: ='1. Ramos Totales'!$C$9 -> 46022 | I9: Relativa | J9: Absoluta | K9: ='1. Ramos Totales'!$B$9 -> 45657 | L9: ='1. Ramos Totales'!$C$9 -> 46022 | M9: Relativa | N9: Absoluta | O9: ='1. Ramos Totales'!$B$9 -> 45657 | P9: ='1. Ramos Totales'!$C$9 -> 46022 | Q9: Relativa | R9: Absoluta
A10: 1 | B10: ='Primas Diciembre 2024'!$I11 -> MAPFRE SEGUROS | C10: ='Primas Diciembre 2024'!I51/1000 -> 1431.9608 | D10: ='Primas Diciembre 2025'!E51/1000 -> 1465.588 | E10: =IFERROR(F10/C10,0%) -> 0.02348336 | F10: =IFERROR(D10-C10,0) -> 33.62725 | G10: ='Siniestros Diciembre 2024'!K51/1000 -> 323.77839 | H10: ='Siniestros Diciembre 2025'!H51/1000 -> 338.41864 | I10: =IFERROR(J10/G10,0%) -> 0.045216877 | J10: =IFERROR(H10-G10,0) -> 14.640248 | K10: =IFERROR((G10/C10),0%) -> 0.22610842 | L10: =IFERROR(H10/D10,0%) -> 0.2309098 | M10: =IFERROR(N10/K10,0%) -> 0.021234852 | N10: =L10-K10 -> 0.0048013788 | O10: =C10/$C$22 -> 0.22003809 | P10: =D10/$D$22 -> 0.21237424 | Q10: =IFERROR(R10/O10,0%) -> -0.034829635 | R10: =IFERROR(P10-O10,0) -> -0.0076638463
A11: 2 | B11: ='Primas Diciembre 2024'!$J11 -> FICOHSA SEGUROS | C11: ='Primas Diciembre 2024'!J51/1000 -> 1124.4967 | D11: ='Primas Diciembre 2025'!F51/1000 -> 1300.2513 | E11: =IFERROR(F11/C11,0%) -> 0.15629627 | F11: =IFERROR(D11-C11,0) -> 175.75463 | G11: ='Siniestros Diciembre 2024'!M51/1000 -> 332.94247 | H11: ='Siniestros Diciembre 2025'!J51/1000 -> 311.91989 | I11: =IFERROR(J11/G11,0%) -> -0.063141778 | J11: =IFERROR(H11-G11,0) -> -21.02258 | K11: =IFERROR((G11/C11),0%) -> 0.29608133 | L11: =IFERROR(H11/D11,0%) -> 0.239892 | M11: =IFERROR(N11/K11,0%) -> -0.18977666 | N11: =L11-K11 -> -0.056189326 | O11: =C11/$C$22 -> 0.17279251 | P11: =D11/$D$22 -> 0.18841576 | Q11: =IFERROR(R11/O11,0%) -> 0.090416251 | R11: =IFERROR(P11-O11,0) -> 0.015623251
A12: 3 | B12: ='Primas Diciembre 2024'!$L11 -> SEGUROS ATLÁNTIDA | C12: ='Primas Diciembre 2024'!L51/1000 -> 774.12862 | D12: ='Primas Diciembre 2025'!H51/1000 -> 770.53317 | E12: =IFERROR(F12/C12,0%) -> -0.0046445179 | F12: =IFERROR(D12-C12,0) -> -3.5954543 | G12: ='Siniestros Diciembre 2024'!Q51/1000 -> 240.98385 | H12: ='Siniestros Diciembre 2025'!N51/1000 -> 285.83678 | I12: =IFERROR(J12/G12,0%) -> 0.18612422 | J12: =IFERROR(H12-G12,0) -> 44.852931 | K12: =IFERROR((G12/C12),0%) -> 0.31129691 | L12: =IFERROR(H12/D12,0%) -> 0.37095973 | M12: =IFERROR(N12/K12,0%) -> 0.1916589 | N12: =L12-K12 -> 0.059662824 | O12: =C12/$C$22 -> 0.11895422 | P12: =D12/$D$22 -> 0.1116558 | Q12: =IFERROR(R12/O12,0%) -> -0.061354926 | R12: =IFERROR(P12-O12,0) -> -0.0072984276
A13: 4 | B13: ='Primas Diciembre 2024'!$G11 -> SEGUROS DAVIVIENDA | C13: ='Primas Diciembre 2024'!G51/1000 -> 727.74247 | D13: ='Primas Diciembre 2025'!C51/1000 -> 739.87358 | E13: =IFERROR(F13/C13,0%) -> 0.016669505 | F13: =IFERROR(D13-C13,0) -> 12.131107 | G13: ='Siniestros Diciembre 2024'!G51/1000 -> 152.22861 | H13: ='Siniestros Diciembre 2025'!D51/1000 -> 240.64329 | I13: =IFERROR(J13/G13,0%) -> 0.58080195 | J13: =IFERROR(H13-G13,0) -> 88.414676 | K13: =IFERROR((G13/C13),0%) -> 0.20917924 | L13: =IFERROR(H13/D13,0%) -> 0.3252492 | M13: =IFERROR(N13/K13,0%) -> 0.55488282 | N13: =L13-K13 -> 0.11606996 | O13: =C13/$C$22 -> 0.11182643 | P13: =D13/$D$22 -> 0.107213 | Q13: =IFERROR(R13/O13,0%) -> -0.04125527 | R13: =IFERROR(P13-O13,0) -> -0.0046134296
A14: 5 | B14: ='Primas Diciembre 2024'!$H11 -> PALIC | C14: ='Primas Diciembre 2024'!H51/1000 -> 708.21103 | D14: ='Primas Diciembre 2025'!D51/1000 -> 736.63882 | E14: =IFERROR(F14/C14,0%) -> 0.040140288 | F14: =IFERROR(D14-C14,0) -> 28.427795 | G14: ='Siniestros Diciembre 2024'!I51/1000 -> 109.1135 | H14: ='Siniestros Diciembre 2025'!F51/1000 -> 129.06297 | I14: =IFERROR(J14/G14,0%) -> 0.18283227 | J14: =IFERROR(H14-G14,0) -> 19.94947 | K14: =IFERROR((G14/C14),0%) -> 0.1540692 | L14: =IFERROR(H14/D14,0%) -> 0.17520523 | M14: =IFERROR(N14/K14,0%) -> 0.13718532 | N14: =L14-K14 -> 0.021136033 | O14: =C14/$C$22 -> 0.10882519 | P14: =D14/$D$22 -> 0.10674426 | Q14: =IFERROR(R14/O14,0%) -> -0.019121736 | R14: =IFERROR(P14-O14,0) -> -0.0020809265
A15: 6 | B15: ='Primas Diciembre 2024'!$M11 -> CREFISA | C15: ='Primas Diciembre 2024'!M51/1000 -> 368.06353 | D15: ='Primas Diciembre 2025'!I51/1000 -> 408.60058 | E15: =IFERROR(F15/C15,0%) -> 0.11013601 | F15: =IFERROR(D15-C15,0) -> 40.537049 | G15: ='Siniestros Diciembre 2024'!S51/1000 -> 115.52164 | H15: ='Siniestros Diciembre 2025'!P51/1000 -> 146.72312 | I15: =IFERROR(J15/G15,0%) -> 0.27009209 | J15: =IFERROR(H15-G15,0) -> 31.201481 | K15: =IFERROR((G15/C15),0%) -> 0.31386331 | L15: =IFERROR(H15/D15,0%) -> 0.35908691 | M15: =IFERROR(N15/K15,0%) -> 0.14408692 | N15: =L15-K15 -> 0.045223599 | O15: =C15/$C$22 -> 0.056557412 | P15: =D15/$D$22 -> 0.059209162 | Q15: =IFERROR(R15/O15,0%) -> 0.046885979 | R15: =IFERROR(P15-O15,0) -> 0.0026517496
A16: 7 | B16: ='Primas Diciembre 2024'!$N11 -> SEGUROS EQUIDAD | C16: ='Primas Diciembre 2024'!N51/1000 -> 492.61278 | D16: ='Primas Diciembre 2025'!J51/1000 -> 401.65467 | E16: =IFERROR(F16/C16,0%) -> -0.18464424 | F16: =IFERROR(D16-C16,0) -> -90.958115 | G16: ='Siniestros Diciembre 2024'!U51/1000 -> 243.98002 | H16: ='Siniestros Diciembre 2025'!R51/1000 -> 228.24947 | I16: =IFERROR(J16/G16,0%) -> -0.064474767 | J16: =IFERROR(H16-G16,0) -> -15.730555 | K16: =IFERROR((G16/C16),0%) -> 0.49527749 | L16: =IFERROR(H16/D16,0%) -> 0.56827291 | M16: =IFERROR(N16/K16,0%) -> 0.14738288 | N16: =L16-K16 -> 0.072995422 | O16: =C16/$C$22 -> 0.075695911 | P16: =D16/$D$22 -> 0.058202649 | Q16: =IFERROR(R16/O16,0%) -> -0.23109916 | R16: =IFERROR(P16-O16,0) -> -0.017493262
A17: 8 | B17: ='Primas Diciembre 2024'!$O11 -> SEGUROS DEL PAÍS | C17: ='Primas Diciembre 2024'!O51/1000 -> 293.76795 | D17: ='Primas Diciembre 2025'!K51/1000 -> 321.79939 | E17: =IFERROR(F17/C17,0%) -> 0.095420336 | F17: =IFERROR(D17-C17,0) -> 28.031437 | G17: ='Siniestros Diciembre 2024'!W51/1000 -> 58.031663 | H17: ='Siniestros Diciembre 2025'!T51/1000 -> 79.050757 | I17: =IFERROR(J17/G17,0%) -> 0.36220043 | J17: =IFERROR(H17-G17,0) -> 21.019093 | K17: =IFERROR((G17/C17),0%) -> 0.19754252 | L17: =IFERROR(H17/D17,0%) -> 0.24565229 | M17: =IFERROR(N17/K17,0%) -> 0.2435413 | N17: =L17-K17 -> 0.048109764 | O17: =C17/$C$22 -> 0.045140998 | P17: =D17/$D$22 -> 0.046631045 | Q17: =IFERROR(R17/O17,0%) -> 0.03300873 | R17: =IFERROR(P17-O17,0) -> 0.001490047
A18: 9 | B18: ='Primas Diciembre 2024'!$Q11 -> ASEGURADORA RURAL | C18: ='Primas Diciembre 2024'!Q51/1000 -> 285.62994 | D18: ='Primas Diciembre 2025'!M51/1000 -> 316.46013 | E18: =IFERROR(F18/C18,0%) -> 0.10793753 | F18: =IFERROR(D18-C18,0) -> 30.830191 | G18: ='Siniestros Diciembre 2024'!AA51/1000 -> 133.92161 | H18: ='Siniestros Diciembre 2025'!X51/1000 -> 128.56251 | I18: =IFERROR(J18/G18,0%) -> -0.040016657 | J18: =IFERROR(H18-G18,0) -> -5.3590951 | K18: =IFERROR((G18/C18),0%) -> 0.46886404 | L18: =IFERROR(H18/D18,0%) -> 0.40625185 | M18: =IFERROR(N18/K18,0%) -> -0.13354019 | N18: =L18-K18 -> -0.062612194 | O18: =C18/$C$22 -> 0.043890494 | P18: =D18/$D$22 -> 0.045857348 | Q18: =IFERROR(R18/O18,0%) -> 0.04481276 | R18: =IFERROR(P18-O18,0) -> 0.0019668542
A19: 10 | B19: ='Primas Diciembre 2024'!$P11 -> SEGUROS LAFISE | C19: ='Primas Diciembre 2024'!P51/1000 -> 200.55151 | D19: ='Primas Diciembre 2025'!L51/1000 -> 192.84464 | E19: =IFERROR(F19/C19,0%) -> -0.038428378 | F19: =IFERROR(D19-C19,0) -> -7.7068692 | G19: ='Siniestros Diciembre 2024'!Y51/1000 -> 53.214254 | H19: ='Siniestros Diciembre 2025'!V51/1000 -> 68.584484 | I19: =IFERROR(J19/G19,0%) -> 0.2888367 | J19: =IFERROR(H19-G19,0) -> 15.37023 | K19: =IFERROR((G19/C19),0%) -> 0.26533959 | L19: =IFERROR(H19/D19,0%) -> 0.35564631 | M19: =IFERROR(N19/K19,0%) -> 0.34034394 | N19: =L19-K19 -> 0.090306721 | O19: =C19/$C$22 -> 0.030817164 | P19: =D19/$D$22 -> 0.027944575 | Q19: =IFERROR(R19/O19,0%) -> -0.09321395 | R19: =IFERROR(P19-O19,0) -> -0.0028725896
A20: 11 | B20: ='Primas Diciembre 2024'!$R11 -> ASSA CIA. DE SEGUROS | C20: ='Primas Diciembre 2024'!R51/1000 -> 18.600111 | D20: ='Primas Diciembre 2025'!N51/1000 -> 157.07301 | E20: =IFERROR(F20/C20,0%) -> 7.4447352 | F20: =IFERROR(D20-C20,0) -> 138.4729 | G20: ='Siniestros Diciembre 2024'!AC51/1000 -> 7.8655091 | H20: ='Siniestros Diciembre 2025'!Z51/1000 -> 25.169193 | I20: =IFERROR(J20/G20,0%) -> 2.1999445 | J20: =IFERROR(H20-G20,0) -> 17.303684 | K20: =IFERROR((G20/C20),0%) -> 0.42287431 | L20: =IFERROR(H20/D20,0%) -> 0.16023881 | M20: =IFERROR(N20/K20,0%) -> -0.62107225 | N20: =L20-K20 -> -0.2626355 | O20: =C20/$C$22 -> 0.002858132 | P20: =D20/$D$22 -> 0.022761009 | Q20: =IFERROR(R20/O20,0%) -> 6.9635962 | R20: =IFERROR(P20-O20,0) -> 0.019902877
A21: 12 | B21: ='Primas Diciembre 2024'!$K11 -> SEGUROS CONTINENTAL | C21: ='Primas Diciembre 2024'!K51/1000 -> 82.02052 | D21: ='Primas Diciembre 2025'!G51/1000 -> 89.6515 | E21: =IFERROR(F21/C21,0%) -> 0.093037451 | F21: =IFERROR(D21-C21,0) -> 7.6309801 | G21: ='Siniestros Diciembre 2024'!O51/1000 -> 25.750475 | H21: ='Siniestros Diciembre 2025'!L51/1000 -> 28.202925 | I21: =IFERROR(J21/G21,0%) -> 0.095239011 | J21: =IFERROR(H21-G21,0) -> 2.4524498 | K21: =IFERROR((G21/C21),0%) -> 0.31395162 | L21: =IFERROR(H21/D21,0%) -> 0.31458397 | M21: =IFERROR(N21/K21,0%) -> 0.0020141671 | N21: =L21-K21 -> 0.00063235102 | O21: =C21/$C$22 -> 0.012603445 | P21: =D21/$D$22 -> 0.012991147 | Q21: =IFERROR(R21/O21,0%) -> 0.03076161 | R21: =IFERROR(P21-O21,0) -> 0.00038770225
A22: Total general | C22: =SUM(C10:C21) -> 6507.7859 | D22: =SUM(D10:D21) -> 6900.9688 | E22: =IFERROR(F22/C22,0%) -> 0.060417307 | F22: =D22-C22 -> 393.1829 | G22: =SUM(G10:G21) -> 1797.332 | H22: =SUM(H10:H21) -> 2010.424 | I22: =IFERROR(J22/G22,0%) -> 0.1185602 | J22: =H22-G22 -> 213.09203 | K22: =IFERROR((G22/C22),0%) -> 0.27618179 | L22: =IFERROR(H22/D22,0%) -> 0.2913249 | M22: =IFERROR(N22/K22,0%) -> 0.054830195 | N22: =L22-K22 -> 0.015143102
A24: ='1. Ramos Totales'!A$24 -> Inflación Interanual Diciembre 2025 | E24: ='1. Ramos Totales'!$D$24 -> 0.0498 | G24: ='1. Ramos Totales'!$F$24 -> Inflación Acumulada Diciembre 2025 | J24: ='1. Ramos Totales'!$J$24 -> 0.0498
A25: Crecimiento Real | E25: =E22-E24 -> 0.010617307

Sheet 2.1 Vida Individual
A1: Sector Asegurador Hondureño
A2: Situación de Primas y Siniestros por Ramo
A3: ='1. Ramos Totales'!A3 -> Al 31 de diciembre de 2025
A4: (Valores en millones de Lempiras y Porcentajes)
A6: 2. 1 Vida Individual
A8: No. | B8: Compañía | C8: Primas | G8: Siniestros | K8: Siniestros/Primas | O8: Participación de mercado
C9: ='1. Ramos Totales'!$B$9 -> 45657 | D9: ='1. Ramos Totales'!$C$9 -> 46022 | E9: Relativa | F9: Absoluta | G9: ='1. Ramos Totales'!$B$9 -> 45657 | H9: ='1. Ramos Totales'!$C$9 -> 46022 | I9: Relativa | J9: Absoluta | K9: ='1. Ramos Totales'!$B$9 -> 45657 | L9: ='1. Ramos Totales'!$C$9 -> 46022 | M9: Relativa | N9: Absoluta | O9: ='1. Ramos Totales'!$B$9 -> 45657 | P9: ='1. Ramos Totales'!$C$9 -> 46022 | Q9: Relativa | R9: Absoluta
A10: 1 | B10: ='Primas Diciembre 2024'!$H11 -> PALIC | C10: ='Primas Diciembre 2024'!H55/1000 -> 338.91513 | D10: ='Primas Diciembre 2025'!D55/1000 -> 379.40606 | E10: =IFERROR(F10/C10,0%) -> 0.11947219 | F10: =IFERROR(D10-C10,0) -> 40.490934 | G10: ='Siniestros Diciembre 2024'!I55/1000 -> 71.618304 | H10: ='Siniestros Diciembre 2025'!F55/1000 -> 85.010821 | I10: =IFERROR(J10/G10,0%) -> 0.18699852 | J10: =IFERROR(H10-G10,0) -> 13.392517 | K10: =IFERROR((G10/C10),0%) -> 0.21131634 | L10: =IFERROR(H10/D10,0%) -> 0.22406289 | M10: =IFERROR(N10/K10,0%) -> 0.060319789 | N10: =L10-K10 -> 0.012746557 | O10: =C10/$C$22 -> 0.37473657 | P10: =D10/$D$22 -> 0.39623667 | Q10: =IFERROR(R10/O10,0%) -> 0.057373902 | R10: =IFERROR(P10-O10,0) -> 0.021500099
A11: 2 | B11: ='Primas Diciembre 2024'!$G11 -> SEGUROS DAVIVIENDA | C11: ='Primas Diciembre 2024'!G55/1000 -> 312.35542 | D11: ='Primas Diciembre 2025'!C55/1000 -> 311.5464 | E11: =IFERROR(F11/C11,0%) -> -0.0025900772 | F11: =IFERROR(D11-C11,0) -> -0.80902465 | G11: ='Siniestros Diciembre 2024'!G55/1000 -> 69.06604 | H11: ='Siniestros Diciembre 2025'!D55/1000 -> 116.46894 | I11: =IFERROR(J11/G11,0%) -> 0.68634171 | J11: =IFERROR(H11-G11,0) -> 47.402904 | K11: =IFERROR((G11/C11),0%) -> 0.22111363 | L11: =IFERROR(H11/D11,0%) -> 0.37384141 | M11: =IFERROR(N11/K11,0%) -> 0.69072081 | N11: =L11-K11 -> 0.15272778 | O11: =C11/$C$22 -> 0.34536965 | P11: =D11/$D$22 -> 0.32536672 | Q11: =IFERROR(R11/O11,0%) -> -0.057917446 | R11: =IFERROR(P11-O11,0) -> -0.020002928
A12: 3 | B12: ='Primas Diciembre 2024'!$J11 -> FICOHSA SEGUROS | C12: ='Primas Diciembre 2024'!J55/1000 -> 92.220254 | D12: ='Primas Diciembre 2025'!F55/1000 -> 97.773838 | E12: =IFERROR(F12/C12,0%) -> 0.060220875 | F12: =IFERROR(D12-C12,0) -> 5.5535844 | G12: ='Siniestros Diciembre 2024'!M55/1000 -> 24.117753 | H12: ='Siniestros Diciembre 2025'!J55/1000 -> 23.054899 | I12: =IFERROR(J12/G12,0%) -> -0.044069375 | J12: =IFERROR(H12-G12,0) -> -1.0628543 | K12: =IFERROR((G12/C12),0%) -> 0.26152339 | L12: =IFERROR(H12/D12,0%) -> 0.23579824 | M12: =IFERROR(N12/K12,0%) -> -0.098366531 | N12: =L12-K12 -> -0.025725149 | O12: =C12/$C$22 -> 0.10196742 | P12: =D12/$D$22 -> 0.10211112 | Q12: =IFERROR(R12/O12,0%) -> 0.0014093172 | R12: =IFERROR(P12-O12,0) -> 0.00014370443
A13: 4 | B13: ='Primas Diciembre 2024'!$K11 -> SEGUROS CONTINENTAL | C13: ='Primas Diciembre 2024'!K55/1000 -> 58.814421 | D13: ='Primas Diciembre 2025'!G55/1000 -> 67.27082 | E13: =IFERROR(F13/C13,0%) -> 0.14378106 | F13: =IFERROR(D13-C13,0) -> 8.4563996 | G13: ='Siniestros Diciembre 2024'!O55/1000 -> 8.396654 | H13: ='Siniestros Diciembre 2025'!L55/1000 -> 19.961438 | I13: =IFERROR(J13/G13,0%) -> 1.3773086 | J13: =IFERROR(H13-G13,0) -> 11.564784 | K13: =IFERROR((G13/C13),0%) -> 0.14276522 | L13: =IFERROR(H13/D13,0%) -> 0.29673249 | M13: =IFERROR(N13/K13,0%) -> 1.0784647 | N13: =L13-K13 -> 0.15396726 | O13: =C13/$C$22 -> 0.065030776 | P13: =D13/$D$22 -> 0.07025498 | Q13: =IFERROR(R13/O13,0%) -> 0.080334329 | R13: =IFERROR(P13-O13,0) -> 0.0052242038
A14: 5 | B14: ='Primas Diciembre 2024'!$I11 -> MAPFRE SEGUROS | C14: ='Primas Diciembre 2024'!I55/1000 -> 43.653249 | D14: ='Primas Diciembre 2025'!E55/1000 -> 41.58141 | E14: =IFERROR(F14/C14,0%) -> -0.047461291 | F14: =IFERROR(D14-C14,0) -> -2.0718396 | G14: ='Siniestros Diciembre 2024'!K55/1000 -> 10.273022 | H14: ='Siniestros Diciembre 2025'!H55/1000 -> 16.26929 | I14: =IFERROR(J14/G14,0%) -> 0.58369073 | J14: =IFERROR(H14-G14,0) -> 5.9962679 | K14: =IFERROR((G14/C14),0%) -> 0.23533236 | L14: =IFERROR(H14/D14,0%) -> 0.39126356 | M14: =IFERROR(N14/K14,0%) -> 0.66259987 | N14: =L14-K14 -> 0.15593119 | O14: =C14/$C$22 -> 0.048267154 | P14: =D14/$D$22 -> 0.043425977 | Q14: =IFERROR(R14/O14,0%) -> -0.10029961 | R14: =IFERROR(P14-O14,0) -> -0.0048411765
A15: 6 | B15: ='Primas Diciembre 2024'!$O11 -> SEGUROS DEL PAÍS | C15: ='Primas Diciembre 2024'!O55/1000 -> 19.450308 | D15: ='Primas Diciembre 2025'!K55/1000 -> 20.063308 | E15: =IFERROR(F15/C15,0%) -> 0.031516242 | F15: =IFERROR(D15-C15,0) -> 0.61300059 | G15: ='Siniestros Diciembre 2024'!W55/1000 -> 5.7660791 | H15: ='Siniestros Diciembre 2025'!T55/1000 -> 6.4556599 | I15: =IFERROR(J15/G15,0%) -> 0.11959267 | J15: =IFERROR(H15-G15,0) -> 0.68958079 | K15: =IFERROR((G15/C15),0%) -> 0.29645182 | L15: =IFERROR(H15/D15,0%) -> 0.32176448 | M15: =IFERROR(N15/K15,0%) -> 0.0853854 | N15: =L15-K15 -> 0.025312658 | O15: =C15/$C$22 -> 0.021506096 | P15: =D15/$D$22 -> 0.020953324 | Q15: =IFERROR(R15/O15,0%) -> -0.025703041 | R15: =IFERROR(P15-O15,0) -> -0.00055277207
A16: 7 | B16: ='Primas Diciembre 2024'!$L11 -> SEGUROS ATLÁNTIDA | C16: ='Primas Diciembre 2024'!L55/1000 -> 16.370249 | D16: ='Primas Diciembre 2025'!H55/1000 -> 17.343844 | E16: =IFERROR(F16/C16,0%) -> 0.05947344 | F16: =IFERROR(D16-C16,0) -> 0.97359505 | G16: ='Siniestros Diciembre 2024'!Q55/1000 -> 6.78534 | H16: ='Siniestros Diciembre 2025'!N55/1000 -> 2.6063985 | I16: =IFERROR(J16/G16,0%) -> -0.61587798 | J16: =IFERROR(H16-G16,0) -> -4.1789415 | K16: =IFERROR((G16/C16),0%) -> 0.41449216 | L16: =IFERROR(H16/D16,0%) -> 0.15027801 | M16: =IFERROR(N16/K16,0%) -> -0.63744063 | N16: =L16-K16 -> -0.26421414 | O16: =C16/$C$22 -> 0.018100493 | P16: =D16/$D$22 -> 0.018113224 | Q16: =IFERROR(R16/O16,0%) -> 0.00070334339 | R16: =IFERROR(P16-O16,0) -> 1.2730862e-05
A17: 8 | B17: ='Primas Diciembre 2024'!$P11 -> SEGUROS LAFISE | C17: ='Primas Diciembre 2024'!P55/1000 -> 17.873668 | D17: ='Primas Diciembre 2025'!L55/1000 -> 17.279997 | E17: =IFERROR(F17/C17,0%) -> -0.033214831 | F17: =IFERROR(D17-C17,0) -> -0.59367086 | G17: ='Siniestros Diciembre 2024'!Y55/1000 -> 0.6 | H17: ='Siniestros Diciembre 2025'!V55/1000 -> 2.525 | I17: =IFERROR(J17/G17,0%) -> 3.2083333 | J17: =IFERROR(H17-G17,0) -> 1.925 | K17: =IFERROR((G17/C17),0%) -> 0.033568935 | L17: =IFERROR(H17/D17,0%) -> 0.14612271 | M17: =IFERROR(N17/K17,0%) -> 3.3529147 | N17: =L17-K17 -> 0.11255377 | O17: =C17/$C$22 -> 0.019762815 | P17: =D17/$D$22 -> 0.018046545 | Q17: =IFERROR(R17/O17,0%) -> -0.086843413 | R17: =IFERROR(P17-O17,0) -> -0.0017162703
A18: 9 | B18: ='Primas Diciembre 2024'!$M11 -> CREFISA | C18: ='Primas Diciembre 2024'!M55/1000 -> 3.1895241 | D18: ='Primas Diciembre 2025'!I55/1000 -> 3.0334318 | E18: =IFERROR(F18/C18,0%) -> -0.048939029 | F18: =IFERROR(D18-C18,0) -> -0.15609221 | G18: ='Siniestros Diciembre 2024'!S55/1000 -> 0 | H18: ='Siniestros Diciembre 2025'!P55/1000 -> 0 | I18: =IFERROR(J18/G18,0%) -> 0 | J18: =IFERROR(H18-G18,0) -> 0 | K18: =IFERROR((G18/C18),0%) -> 0 | L18: =IFERROR(H18/D18,0%) -> 0 | M18: =IFERROR(N18/K18,0%) -> 0 | N18: =L18-K18 -> 0 | O18: =C18/$C$22 -> 0.0035266389 | P18: =D18/$D$22 -> 0.0031679961 | Q18: =IFERROR(R18/O18,0%) -> -0.10169537 | R18: =IFERROR(P18-O18,0) -> -0.00035864286
A19: 10 | B19: ='Primas Diciembre 2024'!$Q11 -> ASEGURADORA RURAL | C19: ='Primas Diciembre 2024'!Q55/1000 -> 1.566793 | D19: ='Primas Diciembre 2025'!M55/1000 -> 2.2247548 | E19: =IFERROR(F19/C19,0%) -> 0.41994176 | F19: =IFERROR(D19-C19,0) -> 0.6579618 | G19: ='Siniestros Diciembre 2024'!AA55/1000 -> 0 | H19: ='Siniestros Diciembre 2025'!X55/1000 -> 0 | I19: =IFERROR(J19/G19,0%) -> 0 | J19: =IFERROR(H19-G19,0) -> 0 | K19: =IFERROR((G19/C19),0%) -> 0 | L19: =IFERROR(H19/D19,0%) -> 0 | M19: =IFERROR(N19/K19,0%) -> 0 | N19: =L19-K19 -> 0 | O19: =C19/$C$22 -> 0.0017323942 | P19: =D19/$D$22 -> 0.0023234458 | Q19: =IFERROR(R19/O19,0%) -> 0.34117611 | R19: =IFERROR(P19-O19,0) -> 0.00059105153
A20: 11 | B20: ='Primas Diciembre 2024'!$N11 -> SEGUROS EQUIDAD | C20: ='Primas Diciembre 2024'!N55/1000 -> 0 | D20: ='Primas Diciembre 2025'!J55/1000 -> 0 | E20: =IFERROR(F20/C20,0%) -> 0 | F20: =IFERROR(D20-C20,0) -> 0 | G20: ='Siniestros Diciembre 2024'!U55/1000 -> 0 | H20: ='Siniestros Diciembre 2025'!H80/1000 -> 0 | I20: =IFERROR(J20/G20,0%) -> 0 | J20: =IFERROR(H20-G20,0) -> 0 | K20: =IFERROR((G20/C20),0%) -> 0 | L20: =IFERROR(H20/D20,0%) -> 0 | M20: =IFERROR(N20/K20,0%) -> 0 | N20: =L20-K20 -> 0 | O20: =C20/$C$22 -> 0 | P20: =D20/$D$22 -> 0 | Q20: =IFERROR(R20/O20,0%) -> 0 | R20: =IFERROR(P20-O20,0) -> 0
A21: 12 | B21: ='Primas Diciembre 2024'!$R11 -> ASSA CIA. DE SEGUROS | C21: ='Primas Diciembre 2024'!R55/1000 -> 0 | D21: ='Primas Diciembre 2025'!N55/1000 -> 0 | E21: =IFERROR(F21/C21,0%) -> 0 | F21: =IFERROR(D21-C21,0) -> 0 | G21: ='Siniestros Diciembre 2024'!AC55/1000 -> 0 | H21: ='Siniestros Diciembre 2025'!Z55/1000 -> 0 | I21: =IFERROR(J21/G21,0%) -> 0 | J21: =IFERROR(H21-G21,0) -> 0 | K21: =IFERROR((G21/C21),0%) -> 0 | L21: =IFERROR(H21/D21,0%) -> 0 | M21: =IFERROR(N21/K21,0%) -> 0 | N21: =L21-K21 -> 0 | O21: =C21/$C$22 -> 0 | P21: =D21/$D$22 -> 0 | Q21: =IFERROR(R21/O21,0%) -> 0 | R21: =IFERROR(P21-O21,0) -> 0
A22: Total general | C22: =SUM(C10:C21) -> 904.40902 | D22: =SUM(D10:D21) -> 957.52387 | E22: =IFERROR(F22/C22,0%) -> 0.058728791 | F22: =D22-C22 -> 53.114848 | G22: =SUM(G10:G21) -> 196.62319 | H22: =SUM(H10:H21) -> 272.35245 | I22: =IFERROR(J22/G22,0%) -> 0.38514916 | J22: =H22-G22 -> 75.729258 | K22: =IFERROR((G22/C22),0%) -> 0.21740517 | L22: =IFERROR(H22/D22,0%) -> 0.28443411 | M22: =IFERROR(N22/K22,0%) -> 0.30831349 | N22: =L22-K22 -> 0.067028946
A24: ='1. Ramos Totales'!A$24 -> Inflación Interanual Diciembre 2025 | E24: ='1. Ramos Totales'!$D$24 -> 0.0498 | G24: ='1. Ramos Totales'!$F$24 -> Inflación Acumulada Diciembre 2025 | J24: ='1. Ramos Totales'!$J$24 -> 0.0498
A25: Crecimiento Real | E25: =E22-E24 -> 0.0089287906

Sheet 2.2 Vida Colectivo
A1: Sector Asegurador Hondureño
A2: Situación de Primas y Siniestros por Ramo
A3: ='1. Ramos Totales'!A3 -> Al 31 de diciembre de 2025
A4: (Valores en millones de Lempiras y Porcentajes)
A6: 2.2 Vida Colectivo
A8: No. | B8: Compañía | C8: Primas | G8: Siniestros | K8: Siniestros/Primas | O8: Participación de mercado
C9: ='1. Ramos Totales'!$B$9 -> 45657 | D9: ='1. Ramos Totales'!$C$9 -> 46022 | E9: Relativa | F9: Absoluta | G9: ='1. Ramos Totales'!$B$9 -> 45657 | H9: ='1. Ramos Totales'!$C$9 -> 46022 | I9: Relativa | J9: Absoluta | K9: ='1. Ramos Totales'!$B$9 -> 45657 | L9: ='1. Ramos Totales'!$C$9 -> 46022 | M9: Relativa | N9: Absoluta | O9: ='1. Ramos Totales'!$B$9 -> 45657 | P9: ='1. Ramos Totales'!$C$9 -> 46022 | Q9: Relativa | R9: Absoluta
A10: 1 | B10: ='Primas Diciembre 2024'!$I11 -> MAPFRE SEGUROS | C10: =+'Primas Diciembre 2024'!I54/1000 -> 1388.3075 | D10: ='Primas Diciembre 2025'!E54/1000 -> 1424.0066 | E10: =IFERROR(F10/C10,0%) -> 0.025714108 | F10: =IFERROR(D10-C10,0) -> 35.699089 | G10: ='Siniestros Diciembre 2024'!K54/1000 -> 313.50537 | H10: ='Siniestros Diciembre 2025'!H54/1000 -> 322.14935 | I10: =IFERROR(J10/G10,0%) -> 0.027572031 | J10: =IFERROR(H10-G10,0) -> 8.6439797 | K10: =IFERROR((G10/C10),0%) -> 0.22581839 | L10: =IFERROR(H10/D10,0%) -> 0.22622742 | M10: =IFERROR(N10/K10,0%) -> 0.0018113463 | N10: =L10-K10 -> 0.0004090353 | O10: =C10/$C$22 -> 0.24837256 | P10: =D10/$D$22 -> 0.24014575 | Q10: =IFERROR(R10/O10,0%) -> -0.033122847 | R10: =IFERROR(P10-O10,0) -> -0.0082268062
A11: 2 | B11: ='Primas Diciembre 2024'!$J11 -> FICOHSA SEGUROS | C11: =+'Primas Diciembre 2024'!J54/1000 -> 1032.2764 | D11: ='Primas Diciembre 2025'!F54/1000 -> 1202.4775 | E11: =IFERROR(F11/C11,0%) -> 0.16487933 | F11: =IFERROR(D11-C11,0) -> 170.20105 | G11: ='Siniestros Diciembre 2024'!M54/1000 -> 308.82472 | H11: ='Siniestros Diciembre 2025'!J54/1000 -> 288.86499 | I11: =IFERROR(J11/G11,0%) -> -0.064631243 | J11: =IFERROR(H11-G11,0) -> -19.959725 | K11: =IFERROR((G11/C11),0%) -> 0.29916863 | L11: =IFERROR(H11/D11,0%) -> 0.24022487 | M11: =IFERROR(N11/K11,0%) -> -0.19702519 | N11: =L11-K11 -> -0.058943756 | O11: =C11/$C$22 -> 0.18467748 | P11: =D11/$D$22 -> 0.20278688 | Q11: =IFERROR(R11/O11,0%) -> 0.098059589 | R11: =IFERROR(P11-O11,0) -> 0.018109398
A12: 3 | B12: ='Primas Diciembre 2024'!$L11 -> SEGUROS ATLÁNTIDA | C12: =+'Primas Diciembre 2024'!L54/1000 -> 757.75837 | D12: ='Primas Diciembre 2025'!H54/1000 -> 753.18932 | E12: =IFERROR(F12/C12,0%) -> -0.0060296916 | F12: =IFERROR(D12-C12,0) -> -4.5690493 | G12: ='Siniestros Diciembre 2024'!Q54/1000 -> 234.19851 | H12: ='Siniestros Diciembre 2025'!N54/1000 -> 283.23038 | I12: =IFERROR(J12/G12,0%) -> 0.20936031 | J12: =IFERROR(H12-G12,0) -> 49.031872 | K12: =IFERROR((G12/C12),0%) -> 0.30906753 | L12: =IFERROR(H12/D12,0%) -> 0.37604142 | M12: =IFERROR(N12/K12,0%) -> 0.21669662 | N12: =L12-K12 -> 0.066973888 | O12: =C12/$C$22 -> 0.13556534 | P12: =D12/$D$22 -> 0.12701852 | Q12: =IFERROR(R12/O12,0%) -> -0.06304576 | R12: =IFERROR(P12-O12,0) -> -0.00854682
A13: 4 | B13: ='Primas Diciembre 2024'!$G11 -> SEGUROS DAVIVIENDA | C13: =+'Primas Diciembre 2024'!G54/1000 -> 415.38705 | D13: ='Primas Diciembre 2025'!C54/1000 -> 428.32718 | E13: =IFERROR(F13/C13,0%) -> 0.031151986 | F13: =IFERROR(D13-C13,0) -> 12.940131 | G13: ='Siniestros Diciembre 2024'!G54/1000 -> 83.162574 | H13: ='Siniestros Diciembre 2025'!D54/1000 -> 124.17435 | I13: =IFERROR(J13/G13,0%) -> 0.49315178 | J13: =IFERROR(H13-G13,0) -> 41.011772 | K13: =IFERROR((G13/C13),0%) -> 0.20020502 | L13: =IFERROR(H13/D13,0%) -> 0.28990536 | M13: =IFERROR(N13/K13,0%) -> 0.44804239 | N13: =L13-K13 -> 0.089700336 | O13: =C13/$C$22 -> 0.074314042 | P13: =D13/$D$22 -> 0.072233479 | Q13: =IFERROR(R13/O13,0%) -> -0.027996896 | R13: =IFERROR(P13-O13,0) -> -0.0020805625
A14: 5 | B14: ='Primas Diciembre 2024'!$M11 -> CREFISA | C14: =+'Primas Diciembre 2024'!M54/1000 -> 364.87401 | D14: ='Primas Diciembre 2025'!I54/1000 -> 405.56715 | E14: =IFERROR(F14/C14,0%) -> 0.11152656 | F14: =IFERROR(D14-C14,0) -> 40.693141 | G14: ='Siniestros Diciembre 2024'!S54/1000 -> 115.52164 | H14: ='Siniestros Diciembre 2025'!P54/1000 -> 146.72312 | I14: =IFERROR(J14/G14,0%) -> 0.27009209 | J14: =IFERROR(H14-G14,0) -> 31.201481 | K14: =IFERROR((G14/C14),0%) -> 0.31660692 | L14: =IFERROR(H14/D14,0%) -> 0.36177269 | M14: =IFERROR(N14/K14,0%) -> 0.14265565 | N14: =L14-K14 -> 0.045165765 | O14: =C14/$C$22 -> 0.0652771 | P14: =D14/$D$22 -> 0.068395207 | Q14: =IFERROR(R14/O14,0%) -> 0.047767232 | R14: =IFERROR(P14-O14,0) -> 0.0031181064
A15: 6 | B15: ='Primas Diciembre 2024'!$N11 -> SEGUROS EQUIDAD | C15: =+'Primas Diciembre 2024'!N54/1000 -> 478.85315 | D15: ='Primas Diciembre 2025'!J54/1000 -> 387.96953 | E15: =IFERROR(F15/C15,0%) -> -0.18979435 | F15: =IFERROR(D15-C15,0) -> -90.883621 | G15: ='Siniestros Diciembre 2024'!U54/1000 -> 233.95977 | H15: ='Siniestros Diciembre 2025'!R54/1000 -> 220.15547 | I15: =IFERROR(J15/G15,0%) -> -0.0590029 | J15: =IFERROR(H15-G15,0) -> -13.804305 | K15: =IFERROR((G15/C15),0%) -> 0.48858355 | L15: =IFERROR(H15/D15,0%) -> 0.56745556 | M15: =IFERROR(N15/K15,0%) -> 0.16142994 | N15: =L15-K15 -> 0.078872012 | O15: =C15/$C$22 -> 0.085668325 | P15: =D15/$D$22 -> 0.065427528 | Q15: =IFERROR(R15/O15,0%) -> -0.23626932 | R15: =IFERROR(P15-O15,0) -> -0.020240797
A16: 7 | B16: ='Primas Diciembre 2024'!$H11 -> PALIC | C16: =+'Primas Diciembre 2024'!H54/1000 -> 369.29589 | D16: ='Primas Diciembre 2025'!D54/1000 -> 357.23276 | E16: =IFERROR(F16/C16,0%) -> -0.03266524 | F16: =IFERROR(D16-C16,0) -> -12.063139 | G16: ='Siniestros Diciembre 2024'!I54/1000 -> 37.4952 | H16: ='Siniestros Diciembre 2025'!F54/1000 -> 44.052152 | I16: =IFERROR(J16/G16,0%) -> 0.17487446 | J16: =IFERROR(H16-G16,0) -> 6.5569528 | K16: =IFERROR((G16/C16),0%) -> 0.10153159 | L16: =IFERROR(H16/D16,0%) -> 0.12331499 | M16: =IFERROR(N16/K16,0%) -> 0.21454796 | N16: =L16-K16 -> 0.021783396 | O16: =C16/$C$22 -> 0.06606819 | P16: =D16/$D$22 -> 0.060244052 | Q16: =IFERROR(R16/O16,0%) -> -0.088153442 | R16: =IFERROR(P16-O16,0) -> -0.0058241384
A17: 8 | B17: ='Primas Diciembre 2024'!$Q11 -> ASEGURADORA RURAL | C17: =+'Primas Diciembre 2024'!Q54/1000 -> 284.06315 | D17: ='Primas Diciembre 2025'!M54/1000 -> 314.23537 | E17: =IFERROR(F17/C17,0%) -> 0.10621663 | F17: =IFERROR(D17-C17,0) -> 30.172229 | G17: ='Siniestros Diciembre 2024'!AA54/1000 -> 133.92161 | H17: ='Siniestros Diciembre 2025'!X54/1000 -> 128.56251 | I17: =IFERROR(J17/G17,0%) -> -0.040016657 | J17: =IFERROR(H17-G17,0) -> -5.3590951 | K17: =IFERROR((G17/C17),0%) -> 0.47145013 | L17: =IFERROR(H17/D17,0%) -> 0.40912807 | M17: =IFERROR(N17/K17,0%) -> -0.13219227 | N17: =L17-K17 -> -0.062322062 | O17: =C17/$C$22 -> 0.050819785 | P17: =D17/$D$22 -> 0.052992935 | Q17: =IFERROR(R17/O17,0%) -> 0.042761891 | R17: =IFERROR(P17-O17,0) -> 0.0021731501
A18: 9 | B18: ='Primas Diciembre 2024'!$O11 -> SEGUROS DEL PAÍS | C18: =+'Primas Diciembre 2024'!O54/1000 -> 274.31765 | D18: ='Primas Diciembre 2025'!K54/1000 -> 301.73608 | E18: =IFERROR(F18/C18,0%) -> 0.099951413 | F18: =IFERROR(D18-C18,0) -> 27.418436 | G18: ='Siniestros Diciembre 2024'!W54/1000 -> 52.265584 | H18: ='Siniestros Diciembre 2025'!T54/1000 -> 72.595097 | I18: =IFERROR(J18/G18,0%) -> 0.38896557 | J18: =IFERROR(H18-G18,0) -> 20.329513 | K18: =IFERROR((G18/C18),0%) -> 0.19052943 | L18: =IFERROR(H18/D18,0%) -> 0.24059137 | M18: =IFERROR(N18/K18,0%) -> 0.26275175 | N18: =L18-K18 -> 0.05006194 | O18: =C18/$C$22 -> 0.049076284 | P18: =D18/$D$22 -> 0.050885043 | Q18: =IFERROR(R18/O18,0%) -> 0.036856062 | R18: =IFERROR(P18-O18,0) -> 0.0018087586
A19: 10 | B19: ='Primas Diciembre 2024'!$P11 -> SEGUROS LAFISE | C19: =+'Primas Diciembre 2024'!P54/1000 -> 182.67784 | D19: ='Primas Diciembre 2025'!L54/1000 -> 175.56464 | E19: =IFERROR(F19/C19,0%) -> -0.038938485 | F19: =IFERROR(D19-C19,0) -> -7.1131984 | G19: ='Siniestros Diciembre 2024'!Y54/1000 -> 52.614254 | H19: ='Siniestros Diciembre 2025'!V54/1000 -> 66.059484 | I19: =IFERROR(J19/G19,0%) -> 0.25554348 | J19: =IFERROR(H19-G19,0) -> 13.44523 | K19: =IFERROR((G19/C19),0%) -> 0.28801662 | L19: =IFERROR(H19/D19,0%) -> 0.37626873 | M19: =IFERROR(N19/K19,0%) -> 0.30641323 | N19: =L19-K19 -> 0.088252103 | O19: =C19/$C$22 -> 0.032681637 | P19: =D19/$D$22 -> 0.029607378 | Q19: =IFERROR(R19/O19,0%) -> -0.094066842 | R19: =IFERROR(P19-O19,0) -> -0.0030742583
A20: 11 | B20: ='Primas Diciembre 2024'!$R11 -> ASSA CIA. DE SEGUROS | C20: =+'Primas Diciembre 2024'!R54/1000 -> 18.600111 | D20: ='Primas Diciembre 2025'!N54/1000 -> 157.07301 | E20: =IFERROR(F20/C20,0%) -> 7.4447352 | F20: =IFERROR(D20-C20,0) -> 138.4729 | G20: ='Siniestros Diciembre 2024'!AC54/1000 -> 7.8655091 | H20: ='Siniestros Diciembre 2025'!Z54/1000 -> 25.169193 | I20: =IFERROR(J20/G20,0%) -> 2.1999445 | J20: =IFERROR(H20-G20,0) -> 17.303684 | K20: =IFERROR((G20/C20),0%) -> 0.42287431 | L20: =IFERROR(H20/D20,0%) -> 0.16023881 | M20: =IFERROR(N20/K20,0%) -> -0.62107225 | N20: =L20-K20 -> -0.2626355 | O20: =C20/$C$22 -> 0.003327618 | P20: =D20/$D$22 -> 0.026488934 | Q20: =IFERROR(R20/O20,0%) -> 6.9603288 | R20: =IFERROR(P20-O20,0) -> 0.023161316
A21: 12 | B21: ='Primas Diciembre 2024'!$K11 -> SEGUROS CONTINENTAL | C21: =+'Primas Diciembre 2024'!K54/1000 -> 23.206099 | D21: ='Primas Diciembre 2025'!G54/1000 -> 22.38068 | E21: =IFERROR(F21/C21,0%) -> -0.035569075 | F21: =IFERROR(D21-C21,0) -> -0.82541949 | G21: ='Siniestros Diciembre 2024'!O54/1000 -> 17.353321 | H21: ='Siniestros Diciembre 2025'!L54/1000 -> 8.2414875 | I21: =IFERROR(J21/G21,0%) -> -0.52507723 | J21: =IFERROR(H21-G21,0) -> -9.1118339 | K21: =IFERROR((G21/C21),0%) -> 0.7477914 | L21: =IFERROR(H21/D21,0%) -> 0.36824116 | M21: =IFERROR(N21/K21,0%) -> -0.50756165 | N21: =L21-K21 -> -0.37955024 | O21: =C21/$C$22 -> 0.0041516437 | P21: =D21/$D$22 -> 0.0037742979 | Q21: =IFERROR(R21/O21,0%) -> -0.090890708 | R21: =IFERROR(P21-O21,0) -> -0.00037734583
A22: Total general | C22: =SUM(C10:C21) -> 5589.6173 | D22: =SUM(D10:D21) -> 5929.7598 | E22: =IFERROR(F22/C22,0%) -> 0.060852565 | F22: =D22-C22 -> 340.14255 | G22: =SUM(G10:G21) -> 1590.688 | H22: =SUM(H10:H21) -> 1729.9776 | I22: =IFERROR(J22/G22,0%) -> 0.087565582 | J22: =H22-G22 -> 139.28952 | K22: =IFERROR((G22/C22),0%) -> 0.28457906 | L22: =IFERROR(H22/D22,0%) -> 0.29174497 | M22: =IFERROR(N22/K22,0%) -> 0.025180706 | N22: =L22-K22 -> 0.0071659017
A24: ='1. Ramos Totales'!A$24 -> Inflación Interanual Diciembre 2025 | E24: ='1. Ramos Totales'!$D$24 -> 0.0498 | G24: ='1. Ramos Totales'!$F$24 -> Inflación Acumulada Diciembre 2025 | J24: ='1. Ramos Totales'!$J$24 -> 0.0498
A25: Crecimiento Real | E25: =E22-E24 -> 0.011052565

Sheet 3. Accidentes y Enfermedades
A1: Sector Asegurador Hondureño
A2: Situación de Primas y Siniestros por Ramo
A3: ='1. Ramos Totales'!A3 -> Al 31 de diciembre de 2025
A4: (Valores en millones de Lempiras y Porcentajes)
A6: 3. Accidentes y Enfermedades
A8: No. | B8: Compañía | C8: Primas | G8: Siniestros | K8: Siniestros/Primas | O8: Participación de mercado
C9: ='1. Ramos Totales'!$B$9 -> 45657 | D9: ='1. Ramos Totales'!$C$9 -> 46022 | E9: Relativa | F9: Absoluta | G9: ='1. Ramos Totales'!$B$9 -> 45657 | H9: ='1. Ramos Totales'!$C$9 -> 46022 | I9: Relativa | J9: Absoluta | K9: ='1. Ramos Totales'!$B$9 -> 45657 | L9: ='1. Ramos Totales'!$C$9 -> 46022 | M9: Relativa | N9: Absoluta | O9: ='1. Ramos Totales'!$B$9 -> 45657 | P9: ='1. Ramos Totales'!$C$9 -> 46022 | Q9: Relativa | R9: Absoluta
A10: 1 | B10: ='Primas Diciembre 2024'!J11 -> FICOHSA SEGUROS | C10: =('Primas Diciembre 2024'!J12)/1000 -> 914.25207 | D10: =('Primas Diciembre 2025'!F12)/1000 -> 1042.9622 | E10: =IFERROR(F10/C10,0%) -> 0.14078191 | F10: =IFERROR(D10-C10,0) -> 128.71016 | G10: =('Siniestros Diciembre 2024'!M12)/1000 -> 657.16551 | H10: =('Siniestros Diciembre 2025'!J12)/1000 -> 756.24702 | I10: =IFERROR(J10/G10,0%) -> 0.15077101 | J10: =IFERROR(H10-G10,0) -> 99.081506 | K10: =IFERROR((G10/C10),0%) -> 0.71880123 | L10: =IFERROR(H10/D10,0%) -> 0.72509531 | M10: =IFERROR(N10/K10,0%) -> 0.0087563568 | N10: =IFERROR(L10-K10,0) -> 0.00629408 | O10: =C10/$C$22 -> 0.24925509 | P10: =D10/$D$22 -> 0.25752112 | Q10: =IFERROR(R10/O10,0%) -> 0.033162942 | R10: =IFERROR(P10-O10,0) -> 0.008266032
A11: 2 | B11: ='Primas Diciembre 2024'!H11 -> PALIC | C11: =('Primas Diciembre 2024'!H12)/1000 -> 673.59016 | D11: =('Primas Diciembre 2025'!D12)/1000 -> 713.44266 | E11: =IFERROR(F11/C11,0%) -> 0.05916431 | F11: =IFERROR(D11-C11,0) -> 39.852497 | G11: =('Siniestros Diciembre 2024'!I12)/1000 -> 429.7557 | H11: =('Siniestros Diciembre 2025'!F12)/1000 -> 454.57002 | I11: =IFERROR(J11/G11,0%) -> 0.057740529 | J11: =IFERROR(H11-G11,0) -> 24.814322 | K11: =IFERROR((G11/C11),0%) -> 0.63800769 | L11: =IFERROR(H11/D11,0%) -> 0.63715005 | M11: =IFERROR(N11/K11,0%) -> -0.0013442491 | N11: =IFERROR(L11-K11,0) -> -0.00085764124 | O11: =C11/$C$22 -> 0.18364276 | P11: =D11/$D$22 -> 0.1761584 | Q11: =IFERROR(R11/O11,0%) -> -0.040755029 | R11: =IFERROR(P11-O11,0) -> -0.007484366
A12: 3 | B12: ='Primas Diciembre 2024'!I11 -> MAPFRE SEGUROS | C12: =('Primas Diciembre 2024'!I12)/1000 -> 624.003 | D12: =('Primas Diciembre 2025'!E12)/1000 -> 633.09547 | E12: =IFERROR(F12/C12,0%) -> 0.014571204 | F12: =IFERROR(D12-C12,0) -> 9.0924752 | G12: =('Siniestros Diciembre 2024'!K12)/1000 -> 385.53207 | H12: =('Siniestros Diciembre 2025'!H12)/1000 -> 355.23353 | I12: =IFERROR(J12/G12,0%) -> -0.078588904 | J12: =IFERROR(H12-G12,0) -> -30.298543 | K12: =IFERROR((G12/C12),0%) -> 0.61783689 | L12: =IFERROR(H12/D12,0%) -> 0.56110578 | M12: =IFERROR(N12/K12,0%) -> -0.09182215 | N12: =IFERROR(L12-K12,0) -> -0.056731112 | O12: =C12/$C$22 -> 0.17012367 | P12: =D12/$D$22 -> 0.15631962 | Q12: =IFERROR(R12/O12,0%) -> -0.081141314 | R12: =IFERROR(P12-O12,0) -> -0.013804059
A13: 4 | B13: ='Primas Diciembre 2024'!M11 -> CREFISA | C13: =('Primas Diciembre 2024'!M12)/1000 -> 529.58263 | D13: =('Primas Diciembre 2025'!I12)/1000 -> 568.72902 | E13: =IFERROR(F13/C13,0%) -> 0.073919318 | F13: =IFERROR(D13-C13,0) -> 39.146387 | G13: =('Siniestros Diciembre 2024'!S12)/1000 -> 347.09725 | H13: =('Siniestros Diciembre 2025'!P12)/1000 -> 368.88942 | I13: =IFERROR(J13/G13,0%) -> 0.062784054 | J13: =IFERROR(H13-G13,0) -> 21.792172 | K13: =IFERROR((G13/C13),0%) -> 0.6554166 | L13: =IFERROR(H13/D13,0%) -> 0.64862071 | M13: =IFERROR(N13/K13,0%) -> -0.010368809 | N13: =IFERROR(L13-K13,0) -> -0.0067958893 | O13: =C13/$C$22 -> 0.14438159 | P13: =D13/$D$22 -> 0.14042669 | Q13: =IFERROR(R13/O13,0%) -> -0.027391977 | R13: =IFERROR(P13-O13,0) -> -0.0039548971
A14: 5 | B14: ='Primas Diciembre 2024'!L11 -> SEGUROS ATLÁNTIDA | C14: =('Primas Diciembre 2024'!L12)/1000 -> 397.55087 | D14: =('Primas Diciembre 2025'!H12)/1000 -> 463.16415 | E14: =IFERROR(F14/C14,0%) -> 0.16504372 | F14: =IFERROR(D14-C14,0) -> 65.613274 | G14: =('Siniestros Diciembre 2024'!Q12)/1000 -> 355.48088 | H14: =('Siniestros Diciembre 2025'!N12)/1000 -> 384.35203 | I14: =IFERROR(J14/G14,0%) -> 0.081217167 | J14: =IFERROR(H14-G14,0) -> 28.87115 | K14: =IFERROR((G14/C14),0%) -> 0.89417708 | L14: =IFERROR(H14/D14,0%) -> 0.82983976 | M14: =IFERROR(N14/K14,0%) -> -0.071951421 | N14: =IFERROR(L14-K14,0) -> -0.064337312 | O14: =C14/$C$22 -> 0.1083854 | P14: =D14/$D$22 -> 0.11436133 | Q14: =IFERROR(R14/O14,0%) -> 0.055135938 | R14: =IFERROR(P14-O14,0) -> 0.0059759308
A15: 6 | B15: ='Primas Diciembre 2024'!O11 -> SEGUROS DEL PAÍS | C15: =('Primas Diciembre 2024'!O12)/1000 -> 146.23899 | D15: =('Primas Diciembre 2025'!K12)/1000 -> 150.60871 | E15: =IFERROR(F15/C15,0%) -> 0.029880665 | F15: =IFERROR(D15-C15,0) -> 4.3697184 | G15: =('Siniestros Diciembre 2024'!W12)/1000 -> 80.950222 | H15: =('Siniestros Diciembre 2025'!T12)/1000 -> 80.919353 | I15: =IFERROR(J15/G15,0%) -> -0.00038132854 | J15: =IFERROR(H15-G15,0) -> -0.03086863 | K15: =IFERROR((G15/C15),0%) -> 0.55354746 | L15: =IFERROR(H15/D15,0%) -> 0.53728203 | M15: =IFERROR(N15/K15,0%) -> -0.029383981 | N15: =IFERROR(L15-K15,0) -> -0.016265428 | O15: =C15/$C$22 -> 0.039869544 | P15: =D15/$D$22 -> 0.037187276 | Q15: =IFERROR(R15/O15,0%) -> -0.067276116 | R15: =IFERROR(P15-O15,0) -> -0.002682268
A16: 7 | B16: ='Primas Diciembre 2024'!R11 -> ASSA CIA. DE SEGUROS | C16: =('Primas Diciembre 2024'!R12)/1000 -> 89.863386 | D16: =('Primas Diciembre 2025'!N12)/1000 -> 125.78472 | E16: =IFERROR(F16/C16,0%) -> 0.39973268 | F16: =IFERROR(D16-C16,0) -> 35.921332 | G16: =('Siniestros Diciembre 2024'!AC12)/1000 -> 51.687813 | H16: =('Siniestros Diciembre 2025'!Z12)/1000 -> 79.363936 | I16: =IFERROR(J16/G16,0%) -> 0.53544776 | J16: =IFERROR(H16-G16,0) -> 27.676124 | K16: =IFERROR((G16/C16),0%) -> 0.57518212 | L16: =IFERROR(H16/D16,0%) -> 0.63095055 | M16: =IFERROR(N16/K16,0%) -> 0.096957855 | N16: =IFERROR(L16-K16,0) -> 0.055768424 | O16: =C16/$C$22 -> 0.024499705 | P16: =D16/$D$22 -> 0.031057905 | Q16: =IFERROR(R16/O16,0%) -> 0.26768484 | R16: =IFERROR(P16-O16,0) -> 0.0065581996
A17: 8 | B17: ='Primas Diciembre 2024'!G11 -> SEGUROS DAVIVIENDA | C17: =('Primas Diciembre 2024'!G12)/1000 -> 90.366199 | D17: =('Primas Diciembre 2025'!C12)/1000 -> 112.31359 | E17: =IFERROR(F17/C17,0%) -> 0.24287165 | F17: =IFERROR(D17-C17,0) -> 21.947388 | G17: =('Siniestros Diciembre 2024'!G12)/1000 -> 62.357868 | H17: =('Siniestros Diciembre 2025'!D12)/1000 -> 88.201256 | I17: =IFERROR(J17/G17,0%) -> 0.41443668 | J17: =IFERROR(H17-G17,0) -> 25.843388 | K17: =IFERROR((G17/C17),0%) -> 0.69005744 | L17: =IFERROR(H17/D17,0%) -> 0.78531242 | M17: =IFERROR(N17/K17,0%) -> 0.13803921 | N17: =IFERROR(L17-K17,0) -> 0.095254986 | O17: =C17/$C$22 -> 0.024636789 | P17: =D17/$D$22 -> 0.027731705 | Q17: =IFERROR(R17/O17,0%) -> 0.12562175 | R17: =IFERROR(P17-O17,0) -> 0.0030949165
A18: 9 | B18: ='Primas Diciembre 2024'!Q11 -> ASEGURADORA RURAL | C18: =('Primas Diciembre 2024'!Q12)/1000 -> 49.346352 | D18: =('Primas Diciembre 2025'!M12)/1000 -> 89.300424 | E18: =IFERROR(F18/C18,0%) -> 0.80966619 | F18: =IFERROR(D18-C18,0) -> 39.954073 | G18: =('Siniestros Diciembre 2024'!AA12)/1000 -> 56.99302 | H18: =('Siniestros Diciembre 2025'!X12)/1000 -> 67.768249 | I18: =IFERROR(J18/G18,0%) -> 0.18906224 | J18: =IFERROR(H18-G18,0) -> 10.775228 | K18: =IFERROR((G18/C18),0%) -> 1.1549592 | L18: =IFERROR(H18/D18,0%) -> 0.75887936 | M18: =IFERROR(N18/K18,0%) -> -0.34293836 | N18: =IFERROR(L18-K18,0) -> -0.39607979 | O18: =C18/$C$22 -> 0.013453433 | P18: =D18/$D$22 -> 0.022049452 | Q18: =IFERROR(R18/O18,0%) -> 0.63894608 | R18: =IFERROR(P18-O18,0) -> 0.0085960185
A19: 10 | B19: ='Primas Diciembre 2024'!K11 -> SEGUROS CONTINENTAL | C19: =('Primas Diciembre 2024'!K12)/1000 -> 72.925601 | D19: =('Primas Diciembre 2025'!G12)/1000 -> 74.618928 | E19: =IFERROR(F19/C19,0%) -> 0.02321993 | F19: =IFERROR(D19-C19,0) -> 1.6933273 | G19: =('Siniestros Diciembre 2024'!O12)/1000 -> 38.34444 | H19: =('Siniestros Diciembre 2025'!L12)/1000 -> 74.883833 | I19: =IFERROR(J19/G19,0%) -> 0.95292544 | J19: =IFERROR(H19-G19,0) -> 36.539393 | K19: =IFERROR((G19/C19),0%) -> 0.52580219 | L19: =IFERROR(H19/D19,0%) -> 1.0035501 | M19: =IFERROR(N19/K19,0%) -> 0.9086077 | N19: =IFERROR(L19-K19,0) -> 0.47774792 | O19: =C19/$C$22 -> 0.01988191 | P19: =D19/$D$22 -> 0.018424397 | Q19: =IFERROR(R19/O19,0%) -> -0.073308491 | R19: =IFERROR(P19-O19,0) -> -0.0014575128
A20: 11 | B20: ='Primas Diciembre 2024'!N11 -> SEGUROS EQUIDAD | C20: =('Primas Diciembre 2024'!N12)/1000 -> 75.339583 | D20: =('Primas Diciembre 2025'!J12)/1000 -> 69.227719 | E20: =IFERROR(F20/C20,0%) -> -0.081124215 | F20: =IFERROR(D20-C20,0) -> -6.1118646 | G20: =('Siniestros Diciembre 2024'!U12)/1000 -> 56.215273 | H20: =('Siniestros Diciembre 2025'!R12)/1000 -> 49.006646 | I20: =IFERROR(J20/G20,0%) -> -0.12823253 | J20: =IFERROR(H20-G20,0) -> -7.208627 | K20: =IFERROR((G20/C20),0%) -> 0.74615854 | L20: =IFERROR(H20/D20,0%) -> 0.70790497 | M20: =IFERROR(N20/K20,0%) -> -0.051267342 | N20: =IFERROR(L20-K20,0) -> -0.038253565 | O20: =C20/$C$22 -> 0.02054004 | P20: =D20/$D$22 -> 0.017093236 | Q20: =IFERROR(R20/O20,0%) -> -0.16780903 | R20: =IFERROR(P20-O20,0) -> -0.0034468042
A21: 12 | B21: ='Primas Diciembre 2024'!P11 -> SEGUROS LAFISE | C21: =('Primas Diciembre 2024'!P12)/1000 -> 4.8785932 | D21: =('Primas Diciembre 2025'!L12)/1000 -> 6.7589499 | E21: =IFERROR(F21/C21,0%) -> 0.38543012 | F21: =IFERROR(D21-C21,0) -> 1.8803567 | G21: =('Siniestros Diciembre 2024'!Y12)/1000 -> 2.3145313 | H21: =('Siniestros Diciembre 2025'!V12)/1000 -> 4.8600086 | I21: =IFERROR(J21/G21,0%) -> 1.0997809 | J21: =IFERROR(H21-G21,0) -> 2.5454773 | K21: =IFERROR((G21/C21),0%) -> 0.47442597 | L21: =IFERROR(H21/D21,0%) -> 0.71904788 | M21: =IFERROR(N21/K21,0%) -> 0.5156166 | N21: =IFERROR(L21-K21,0) -> 0.24462191 | O21: =C21/$C$22 -> 0.0013300645 | P21: =D21/$D$22 -> 0.0016688738 | Q21: =IFERROR(R21/O21,0%) -> 0.25473155 | R21: =IFERROR(P21-O21,0) -> 0.00033880938
A22: Total general | C22: =SUM(C10:C21) -> 3667.9374 | D22: =SUM(D10:D21) -> 4050.0066 | E22: =D22/C22-1 -> 0.10416457 | F22: =D22-C22 -> 382.06912 | G22: =SUM(G10:G21) -> 2523.8946 | H22: =SUM(H10:H21) -> 2764.2953 | I22: =H22/G22-1 -> 0.095249906 | J22: =H22-G22 -> 240.40072 | K22: =IFERROR((G22/C22),0%) -> 0.68809641 | L22: =IFERROR(H22/D22,0%) -> 0.68254094 | M22: =IFERROR(N22/K22,0%) -> -0.0080736723 | N22: =L22-K22 -> -0.0055554649
A24: ='1. Ramos Totales'!A$24 -> Inflación Interanual Diciembre 2025 | E24: ='1. Ramos Totales'!$D$24 -> 0.0498 | G24: ='1. Ramos Totales'!$F$24 -> Inflación Acumulada Diciembre 2025 | J24: ='1. Ramos Totales'!$J$24 -> 0.0498
A25: Crecimiento Real | E25: =E22-E24 -> 0.054364569

Sheet 3.1 Salud y Hospitalización
A1: Sector Asegurador Hondureño
A2: Situación de Primas y Siniestros por Ramo
A3: ='1. Ramos Totales'!A3 -> Al 31 de diciembre de 2025
A4: (Valores en millones de Lempiras y Porcentajes)
A6: 3.1 Salud y Hospitalización
A8: No. | B8: Compañía | C8: Primas | G8: Siniestros | K8: Siniestros/Primas | O8: Participación de mercado
C9: ='1. Ramos Totales'!$B$9 -> 45657 | D9: ='1. Ramos Totales'!$C$9 -> 46022 | E9: Relativa | F9: Absoluta | G9: ='1. Ramos Totales'!$B$9 -> 45657 | H9: ='1. Ramos Totales'!$C$9 -> 46022 | I9: Relativa | J9: Absoluta | K9: ='1. Ramos Totales'!$B$9 -> 45657 | L9: ='1. Ramos Totales'!$C$9 -> 46022 | M9: Relativa | N9: Absoluta | O9: ='1. Ramos Totales'!$B$9 -> 45657 | P9: ='1. Ramos Totales'!$C$9 -> 46022 | Q9: Relativa | R9: Absoluta
A10: 1 | B10: ='Primas Diciembre 2024'!J11 -> FICOHSA SEGUROS | C10: =('Primas Diciembre 2024'!J15)/1000 -> 869.41191 | D10: =('Primas Diciembre 2025'!F15)/1000 -> 954.91969 | E10: =IFERROR(F10/C10,0%) -> 0.098351293 | F10: =IFERROR(D10-C10,0) -> 85.507785 | G10: =('Siniestros Diciembre 2024'!M15)/1000 -> 643.68816 | H10: =('Siniestros Diciembre 2025'!J15)/1000 -> 727.01661 | I10: =IFERROR(J10/G10,0%) -> 0.12945469 | J10: =IFERROR(H10-G10,0) -> 83.32845 | K10: =IFERROR((G10/C10),0%) -> 0.74037191 | L10: =IFERROR(H10/D10,0%) -> 0.76133796 | M10: =IFERROR(N10/K10,0%) -> 0.028318258 | N10: =IFERROR(L10-K10,0) -> 0.020966043 | O10: =C10/$C$22 -> 0.26783641 | P10: =D10/$D$22 -> 0.27066478 | Q10: =IFERROR(R10/O10,0%) -> 0.010560081 | R10: =IFERROR(P10-O10,0) -> 0.0028283741
A11: 2 | B11: ='Primas Diciembre 2024'!H11 -> PALIC | C11: =('Primas Diciembre 2024'!H15)/1000 -> 667.89291 | D11: =('Primas Diciembre 2025'!D15)/1000 -> 707.39371 | E11: =IFERROR(F11/C11,0%) -> 0.059142415 | F11: =IFERROR(D11-C11,0) -> 39.5008 | G11: =('Siniestros Diciembre 2024'!I15)/1000 -> 429.7557 | H11: =('Siniestros Diciembre 2025'!F15)/1000 -> 454.57002 | I11: =IFERROR(J11/G11,0%) -> 0.057740529 | J11: =IFERROR(H11-G11,0) -> 24.814322 | K11: =IFERROR((G11/C11),0%) -> 0.64345001 | L11: =IFERROR(H11/D11,0%) -> 0.64259834 | M11: =IFERROR(N11/K11,0%) -> -0.0013236046 | N11: =IFERROR(L11-K11,0) -> -0.00085167338 | O11: =C11/$C$22 -> 0.20575522 | P11: =D11/$D$22 -> 0.20050541 | Q11: =IFERROR(R11/O11,0%) -> -0.025514832 | R11: =IFERROR(P11-O11,0) -> -0.0052498099
A12: 3 | B12: ='Primas Diciembre 2024'!M11 -> CREFISA | C12: =('Primas Diciembre 2024'!M15)/1000 -> 477.07633 | D12: =('Primas Diciembre 2025'!I15)/1000 -> 513.55569 | E12: =IFERROR(F12/C12,0%) -> 0.076464416 | F12: =IFERROR(D12-C12,0) -> 36.479363 | G12: =('Siniestros Diciembre 2024'!S15)/1000 -> 336.48771 | H12: =('Siniestros Diciembre 2025'!P15)/1000 -> 359.60654 | I12: =IFERROR(J12/G12,0%) -> 0.068706332 | J12: =IFERROR(H12-G12,0) -> 23.118836 | K12: =IFERROR((G12/C12),0%) -> 0.7053121 | L12: =IFERROR(H12/D12,0%) -> 0.70022891 | M12: =IFERROR(N12/K12,0%) -> -0.007207005 | N12: =IFERROR(L12-K12,0) -> -0.0050831879 | O12: =C12/$C$22 -> 0.14697109 | P12: =D12/$D$22 -> 0.14556349 | Q12: =IFERROR(R12/O12,0%) -> -0.0095773783 | R12: =IFERROR(P12-O12,0) -> -0.0014075977
A13: 4 | B13: ='Primas Diciembre 2024'!L11 -> SEGUROS ATLÁNTIDA | C13: =('Primas Diciembre 2024'!L15)/1000 -> 382.18166 | D13: =('Primas Diciembre 2025'!H15)/1000 -> 446.33783 | E13: =IFERROR(F13/C13,0%) -> 0.16786826 | F13: =IFERROR(D13-C13,0) -> 64.15617 | G13: =('Siniestros Diciembre 2024'!Q15)/1000 -> 351.03241 | H13: =('Siniestros Diciembre 2025'!N15)/1000 -> 379.1183 | I13: =IFERROR(J13/G13,0%) -> 0.080009405 | J13: =IFERROR(H13-G13,0) -> 28.085894 | K13: =IFERROR((G13/C13),0%) -> 0.91849622 | L13: =IFERROR(H13/D13,0%) -> 0.84939765 | M13: =IFERROR(N13/K13,0%) -> -0.075230109 | N13: =IFERROR(L13-K13,0) -> -0.069098571 | O13: =C13/$C$22 -> 0.11773725 | P13: =D13/$D$22 -> 0.12651109 | Q13: =IFERROR(R13/O13,0%) -> 0.074520558 | R13: =IFERROR(P13-O13,0) -> 0.0087738453
A14: 5 | B14: ='Primas Diciembre 2024'!I11 -> MAPFRE SEGUROS | C14: =('Primas Diciembre 2024'!I15)/1000 -> 441.92555 | D14: =('Primas Diciembre 2025'!E15)/1000 -> 413.58126 | E14: =IFERROR(F14/C14,0%) -> -0.064138162 | F14: =IFERROR(D14-C14,0) -> -28.344293 | G14: =('Siniestros Diciembre 2024'!K15)/1000 -> 361.42817 | H14: =('Siniestros Diciembre 2025'!H15)/1000 -> 332.01762 | I14: =IFERROR(J14/G14,0%) -> -0.081373154 | J14: =IFERROR(H14-G14,0) -> -29.41055 | K14: =IFERROR((G14/C14),0%) -> 0.81784856 | L14: =IFERROR(H14/D14,0%) -> 0.80278692 | M14: =IFERROR(N14/K14,0%) -> -0.018416171 | N14: =IFERROR(L14-K14,0) -> -0.015061639 | O14: =C14/$C$22 -> 0.13614232 | P14: =D14/$D$22 -> 0.11722649 | Q14: =IFERROR(R14/O14,0%) -> -0.13894159 | R14: =IFERROR(P14-O14,0) -> -0.018915831
A15: 6 | B15: ='Primas Diciembre 2024'!R11 -> ASSA CIA. DE SEGUROS | C15: =('Primas Diciembre 2024'!N15)/1000 -> 71.898293 | D15: =('Primas Diciembre 2025'!N15)/1000 -> 100.52402 | E15: =IFERROR(F15/C15,0%) -> 0.3981419 | F15: =IFERROR(D15-C15,0) -> 28.625723 | G15: =('Siniestros Diciembre 2024'!U15)/1000 -> 55.066515 | H15: =('Siniestros Diciembre 2025'!Z15)/1000 -> 75.186177 | I15: =IFERROR(J15/G15,0%) -> 0.36537018 | J15: =IFERROR(H15-G15,0) -> 20.119663 | K15: =IFERROR((G15/C15),0%) -> 0.7658946 | L15: =IFERROR(H15/D15,0%) -> 0.74794244 | M15: =IFERROR(N15/K15,0%) -> -0.023439476 | N15: =IFERROR(L15-K15,0) -> -0.017952168 | O15: =C15/$C$22 -> 0.022149433 | P15: =D15/$D$22 -> 0.028492774 | Q15: =IFERROR(R15/O15,0%) -> 0.28638842 | R15: =IFERROR(P15-O15,0) -> 0.0063433412
A16: 7 | B16: ='Primas Diciembre 2024'!O11 -> SEGUROS DEL PAÍS | C16: =('Primas Diciembre 2024'!O15)/1000 -> 101.66852 | D16: =('Primas Diciembre 2025'!K15)/1000 -> 98.201007 | E16: =IFERROR(F16/C16,0%) -> -0.034106027 | F16: =IFERROR(D16-C16,0) -> -3.4675092 | G16: =('Siniestros Diciembre 2024'!W15)/1000 -> 73.147582 | H16: =('Siniestros Diciembre 2025'!T15)/1000 -> 73.684767 | I16: =IFERROR(J16/G16,0%) -> 0.0073438426 | J16: =IFERROR(H16-G16,0) -> 0.53718433 | K16: =IFERROR((G16/C16),0%) -> 0.71947133 | L16: =IFERROR(H16/D16,0%) -> 0.75034635 | M16: =IFERROR(N16/K16,0%) -> 0.042913478 | N16: =IFERROR(L16-K16,0) -> 0.030875017 | O16: =C16/$C$22 -> 0.031320632 | P16: =D16/$D$22 -> 0.027834335 | Q16: =IFERROR(R16/O16,0%) -> -0.11130993 | R16: =IFERROR(P16-O16,0) -> -0.0034862973
A17: 8 | B17: ='Primas Diciembre 2024'!Q11 -> ASEGURADORA RURAL | C17: =('Primas Diciembre 2024'!R15)/1000 -> 66.066166 | D17: =('Primas Diciembre 2025'!M15)/1000 -> 89.300424 | E17: =IFERROR(F17/C17,0%) -> 0.35168164 | F17: =IFERROR(D17-C17,0) -> 23.234258 | G17: =('Siniestros Diciembre 2024'!AC15)/1000 -> 46.623295 | H17: =('Siniestros Diciembre 2025'!X15)/1000 -> 67.768249 | I17: =IFERROR(J17/G17,0%) -> 0.45352765 | J17: =IFERROR(H17-G17,0) -> 21.144954 | K17: =IFERROR((G17/C17),0%) -> 0.70570608 | L17: =IFERROR(H17/D17,0%) -> 0.75887936 | M17: =IFERROR(N17/K17,0%) -> 0.075347631 | N17: =IFERROR(L17-K17,0) -> 0.053173281 | O17: =C17/$C$22 -> 0.020352752 | P17: =D17/$D$22 -> 0.025311532 | Q17: =IFERROR(R17/O17,0%) -> 0.24364174 | R17: =IFERROR(P17-O17,0) -> 0.0049587798
A18: 9 | B18: ='Primas Diciembre 2024'!G11 -> SEGUROS DAVIVIENDA | C18: =('Primas Diciembre 2024'!G15)/1000 -> 63.828602 | D18: =('Primas Diciembre 2025'!C15)/1000 -> 83.423914 | E18: =IFERROR(F18/C18,0%) -> 0.30699893 | F18: =IFERROR(D18-C18,0) -> 19.595312 | G18: =('Siniestros Diciembre 2024'!G15)/1000 -> 55.535784 | H18: =('Siniestros Diciembre 2025'!D15)/1000 -> 80.517117 | I18: =IFERROR(J18/G18,0%) -> 0.44982409 | J18: =IFERROR(H18-G18,0) -> 24.981333 | K18: =IFERROR((G18/C18),0%) -> 0.87007677 | L18: =IFERROR(H18/D18,0%) -> 0.9651563 | M18: =IFERROR(N18/K18,0%) -> 0.10927718 | N18: =IFERROR(L18-K18,0) -> 0.095079537 | O18: =C18/$C$22 -> 0.019663434 | P18: =D18/$D$22 -> 0.023645879 | Q18: =IFERROR(R18/O18,0%) -> 0.20253051 | R18: =IFERROR(P18-O18,0) -> 0.0039824454
A19: 10 | B19: ='Primas Diciembre 2024'!N11 -> SEGUROS EQUIDAD | C19: =('Primas Diciembre 2024'!K15)/1000 -> 54.759427 | D19: =('Primas Diciembre 2025'!J15)/1000 -> 65.567324 | E19: =IFERROR(F19/C19,0%) -> 0.19737053 | F19: =IFERROR(D19-C19,0) -> 10.807897 | G19: =('Siniestros Diciembre 2024'!O15)/1000 -> 34.089857 | H19: =('Siniestros Diciembre 2025'!R15)/1000 -> 47.5609 | I19: =IFERROR(J19/G19,0%) -> 0.39516281 | J19: =IFERROR(H19-G19,0) -> 13.471043 | K19: =IFERROR((G19/C19),0%) -> 0.6225386 | L19: =IFERROR(H19/D19,0%) -> 0.72537504 | M19: =IFERROR(N19/K19,0%) -> 0.16518887 | N19: =IFERROR(L19-K19,0) -> 0.10283644 | O19: =C19/$C$22 -> 0.016869528 | P19: =D19/$D$22 -> 0.018584563 | Q19: =IFERROR(R19/O19,0%) -> 0.10166471 | R19: =IFERROR(P19-O19,0) -> 0.0017150356
A20: 11 | B20: ='Primas Diciembre 2024'!K11 -> SEGUROS CONTINENTAL | C20: =('Primas Diciembre 2024'!Q15)/1000 -> 49.346352 | D20: =('Primas Diciembre 2025'!G15)/1000 -> 55.248097 | E20: =IFERROR(F20/C20,0%) -> 0.11959842 | F20: =IFERROR(D20-C20,0) -> 5.9017455 | G20: =('Siniestros Diciembre 2024'!AA15)/1000 -> 56.99302 | H20: =('Siniestros Diciembre 2025'!L15)/1000 -> 69.722899 | I20: =IFERROR(J20/G20,0%) -> 0.22335855 | J20: =IFERROR(H20-G20,0) -> 12.729879 | K20: =IFERROR((G20/C20),0%) -> 1.1549592 | L20: =IFERROR(H20/D20,0%) -> 1.2619964 | M20: =IFERROR(N20/K20,0%) -> 0.092676209 | N20: =IFERROR(L20-K20,0) -> 0.10703724 | O20: =C20/$C$22 -> 0.015201942 | P20: =D20/$D$22 -> 0.015659656 | Q20: =IFERROR(R20/O20,0%) -> 0.030108922 | R20: =IFERROR(P20-O20,0) -> 0.0004577141
A21: 12 | B21: ='Primas Diciembre 2024'!P11 -> SEGUROS LAFISE | C21: =('Primas Diciembre 2024'!P15)/1000 -> 0 | D21: =('Primas Diciembre 2025'!L15)/1000 -> 0 | E21: =IFERROR(F21/C21,0%) -> 0 | F21: =IFERROR(D21-C21,0) -> 0 | G21: =('Siniestros Diciembre 2024'!Y15)/1000 -> 0 | H21: =('Siniestros Diciembre 2025'!V15)/1000 -> 0 | I21: =IFERROR(J21/G21,0%) -> 0 | J21: =IFERROR(H21-G21,0) -> 0 | K21: =IFERROR((G21/C21),0%) -> 0 | L21: =IFERROR(H21/D21,0%) -> 0 | M21: =IFERROR(N21/K21,0%) -> 0 | N21: =IFERROR(L21-K21,0) -> 0 | O21: =C21/$C$22 -> 0 | P21: =D21/$D$22 -> 0 | Q21: =IFERROR(R21/O21,0%) -> 0 | R21: =IFERROR(P21-O21,0) -> 0
A22: Total general | C22: =SUM(C10:C21) -> 3246.0557 | D22: =SUM(D10:D21) -> 3528.053 | E22: =D22/C22-1 -> 0.086873818 | F22: =D22-C22 -> 281.99725 | G22: =SUM(G10:G21) -> 2443.8482 | H22: =SUM(H10:H21) -> 2666.7692 | I22: =H22/G22-1 -> 0.091217207 | J22: =H22-G22 -> 222.92101 | K22: =IFERROR((G22/C22),0%) -> 0.75286699 | L22: =IFERROR(H22/D22,0%) -> 0.75587562 | M22: =IFERROR(N22/K22,0%) -> 0.0039962221 | N22: =L22-K22 -> 0.0030086237
A24: ='1. Ramos Totales'!A$24 -> Inflación Interanual Diciembre 2025 | E24: ='1. Ramos Totales'!$D$24 -> 0.0498 | G24: ='1. Ramos Totales'!$F$24 -> Inflación Acumulada Diciembre 2025 | J24: ='1. Ramos Totales'!$J$24 -> 0.0498
A25: Crecimiento Real | E25: =E22-E24 -> 0.037073818

Sheet 3.2 Accidentes Personales
A1: Sector Asegurador Hondureño
A2: Situación de Primas y Siniestros por Ramo
A3: ='1. Ramos Totales'!A3 -> Al 31 de diciembre de 2025
A4: (Valores en millones de Lempiras y Porcentajes)
A6: 3. Accidentes Personales
A8: No. | B8: Compañía | C8: Primas | G8: Siniestros | K8: Siniestros/Primas | O8: Participación de mercado
C9: ='1. Ramos Totales'!$B$9 -> 45657 | D9: ='1. Ramos Totales'!$C$9 -> 46022 | E9: Relativa | F9: Absoluta | G9: ='1. Ramos Totales'!$B$9 -> 45657 | H9: ='1. Ramos Totales'!$C$9 -> 46022 | I9: Relativa | J9: Absoluta | K9: ='1. Ramos Totales'!$B$9 -> 45657 | L9: ='1. Ramos Totales'!$C$9 -> 46022 | M9: Relativa | N9: Absoluta | O9: ='1. Ramos Totales'!$B$9 -> 45657 | P9: ='1. Ramos Totales'!$C$9 -> 46022 | Q9: Relativa | R9: Absoluta
A10: 1 | B10: ='Primas Diciembre 2024'!I11 -> MAPFRE SEGUROS | C10: =('Primas Diciembre 2024'!I14)/1000 -> 182.07745 | D10: =('Primas Diciembre 2025'!E14)/1000 -> 219.51421 | E10: =IFERROR(F10/C10,0%) -> 0.20560903 | F10: =IFERROR(D10-C10,0) -> 37.436768 | G10: =('Siniestros Diciembre 2024'!K14)/1000 -> 24.103901 | H10: =('Siniestros Diciembre 2025'!H14)/1000 -> 23.215908 | I10: =IFERROR(J10/G10,0%) -> -0.036840217 | J10: =IFERROR(H10-G10,0) -> -0.88799295 | K10: =IFERROR((G10/C10),0%) -> 0.13238268 | L10: =IFERROR(H10/D10,0%) -> 0.10576039 | M10: =IFERROR(N10/K10,0%) -> -0.20110106 | N10: =IFERROR(L10-K10,0) -> -0.026622298 | O10: =C10/$C$22 -> 0.44070668 | P10: =D10/$D$22 -> 0.42966845 | Q10: =IFERROR(R10/O10,0%) -> -0.025046663 | R10: =IFERROR(P10-O10,0) -> -0.011038232
A11: 2 | B11: ='Primas Diciembre 2024'!J11 -> FICOHSA SEGUROS | C11: =('Primas Diciembre 2024'!J14)/1000 -> 39.01621 | D11: =('Primas Diciembre 2025'!F14)/1000 -> 81.356294 | E11: =IFERROR(F11/C11,0%) -> 1.0851922 | F11: =IFERROR(D11-C11,0) -> 42.340085 | G11: =('Siniestros Diciembre 2024'!M14)/1000 -> 10.056148 | H11: =('Siniestros Diciembre 2025'!J14)/1000 -> 25.093981 | I11: =IFERROR(J11/G11,0%) -> 1.495387 | J11: =IFERROR(H11-G11,0) -> 15.037833 | K11: =IFERROR((G11/C11),0%) -> 0.25774282 | L11: =IFERROR(H11/D11,0%) -> 0.30844548 | M11: =IFERROR(N11/K11,0%) -> 0.196718 | N11: =IFERROR(L11-K11,0) -> 0.050702652 | O11: =C11/$C$22 -> 0.094436212 | P11: =D11/$D$22 -> 0.1592436 | Q11: =IFERROR(R11/O11,0%) -> 0.68625566 | R11: =IFERROR(P11-O11,0) -> 0.064807385
A12: 3 | B12: ='Primas Diciembre 2024'!M11 -> CREFISA | C12: =('Primas Diciembre 2024'!M14)/1000 -> 52.506298 | D12: =('Primas Diciembre 2025'!I14)/1000 -> 55.173322 | E12: =IFERROR(F12/C12,0%) -> 0.050794356 | F12: =IFERROR(D12-C12,0) -> 2.6670236 | G12: =('Siniestros Diciembre 2024'!S14)/1000 -> 10.609538 | H12: =('Siniestros Diciembre 2025'!P14)/1000 -> 9.2828738 | I12: =IFERROR(J12/G12,0%) -> -0.12504445 | J12: =IFERROR(H12-G12,0) -> -1.3266638 | K12: =IFERROR((G12/C12),0%) -> 0.20206219 | L12: =IFERROR(H12/D12,0%) -> 0.16824932 | M12: =IFERROR(N12/K12,0%) -> -0.16733894 | N12: =IFERROR(L12-K12,0) -> -0.033812872 | O12: =C12/$C$22 -> 0.1270881 | P12: =D12/$D$22 -> 0.10799408 | Q12: =IFERROR(R12/O12,0%) -> -0.15024238 | R12: =IFERROR(P12-O12,0) -> -0.019094018
A13: 4 | B13: ='Primas Diciembre 2024'!O11 -> SEGUROS DEL PAÍS | C13: =('Primas Diciembre 2024'!O14)/1000 -> 44.570475 | D13: =('Primas Diciembre 2025'!K14)/1000 -> 52.407703 | E13: =IFERROR(F13/C13,0%) -> 0.17583899 | F13: =IFERROR(D13-C13,0) -> 7.8372276 | G13: =('Siniestros Diciembre 2024'!W14)/1000 -> 7.8026392 | H13: =('Siniestros Diciembre 2025'!T14)/1000 -> 7.2345863 | I13: =IFERROR(J13/G13,0%) -> -0.072802669 | J13: =IFERROR(H13-G13,0) -> -0.56805296 | K13: =IFERROR((G13/C13),0%) -> 0.17506296 | L13: =IFERROR(H13/D13,0%) -> 0.13804433 | M13: =IFERROR(N13/K13,0%) -> -0.21145894 | N13: =IFERROR(L13-K13,0) -> -0.037018627 | O13: =C13/$C$22 -> 0.10787995 | P13: =D13/$D$22 -> 0.10258077 | Q13: =IFERROR(R13/O13,0%) -> -0.049121132 | R13: =IFERROR(P13-O13,0) -> -0.0052991854
A14: 5 | B14: ='Primas Diciembre 2024'!R11 -> ASSA CIA. DE SEGUROS | C14: =('Primas Diciembre 2024'!R14)/1000 -> 23.79722 | D14: =('Primas Diciembre 2025'!N14)/1000 -> 25.260702 | E14: =IFERROR(F14/C14,0%) -> 0.061498036 | F14: =IFERROR(D14-C14,0) -> 1.4634823 | G14: =('Siniestros Diciembre 2024'!AC14)/1000 -> 5.0645178 | H14: =('Siniestros Diciembre 2025'!Z14)/1000 -> 4.177759 | I14: =IFERROR(J14/G14,0%) -> -0.17509246 | J14: =IFERROR(H14-G14,0) -> -0.88675886 | K14: =IFERROR((G14/C14),0%) -> 0.21281973 | L14: =IFERROR(H14/D14,0%) -> 0.1653857 | M14: =IFERROR(N14/K14,0%) -> -0.22288359 | N14: =IFERROR(L14-K14,0) -> -0.047434025 | O14: =C14/$C$22 -> 0.057599631 | P14: =D14/$D$22 -> 0.0494443 | Q14: =IFERROR(R14/O14,0%) -> -0.14158651 | R14: =IFERROR(P14-O14,0) -> -0.008155331
A15: 6 | B15: ='Primas Diciembre 2024'!G11 -> SEGUROS DAVIVIENDA | C15: =('Primas Diciembre 2024'!G14)/1000 -> 23.628647 | D15: =('Primas Diciembre 2025'!C14)/1000 -> 24.514413 | E15: =IFERROR(F15/C15,0%) -> 0.037486939 | F15: =IFERROR(D15-C15,0) -> 0.88576565 | G15: =('Siniestros Diciembre 2024'!G14)/1000 -> 6.8220844 | H15: =('Siniestros Diciembre 2025'!D14)/1000 -> 7.6841388 | I15: =IFERROR(J15/G15,0%) -> 0.12636233 | J15: =IFERROR(H15-G15,0) -> 0.86205445 | K15: =IFERROR((G15/C15),0%) -> 0.28872091 | L15: =IFERROR(H15/D15,0%) -> 0.31345392 | M15: =IFERROR(N15/K15,0%) -> 0.085664102 | N15: =IFERROR(L15-K15,0) -> 0.024733017 | O15: =C15/$C$22 -> 0.057191612 | P15: =D15/$D$22 -> 0.047983543 | Q15: =IFERROR(R15/O15,0%) -> -0.16100384 | R15: =IFERROR(P15-O15,0) -> -0.0092080689
A16: 7 | B16: ='Primas Diciembre 2024'!K11 -> SEGUROS CONTINENTAL | C16: =('Primas Diciembre 2024'!K14)/1000 -> 18.166174 | D16: =('Primas Diciembre 2025'!G14)/1000 -> 19.370831 | E16: =IFERROR(F16/C16,0%) -> 0.066313175 | F16: =IFERROR(D16-C16,0) -> 1.2046567 | G16: =('Siniestros Diciembre 2024'!O14)/1000 -> 4.2545839 | H16: =('Siniestros Diciembre 2025'!L14)/1000 -> 4.6797342 | I16: =IFERROR(J16/G16,0%) -> 0.099927572 | J16: =IFERROR(H16-G16,0) -> 0.42515024 | K16: =IFERROR((G16/C16),0%) -> 0.23420363 | L16: =IFERROR(H16/D16,0%) -> 0.24158665 | M16: =IFERROR(N16/K16,0%) -> 0.031523944 | N16: =IFERROR(L16-K16,0) -> 0.007383022 | O16: =C16/$C$22 -> 0.04397005 | P16: =D16/$D$22 -> 0.037915699 | Q16: =IFERROR(R16/O16,0%) -> -0.1376926 | R16: =IFERROR(P16-O16,0) -> -0.0060543506
A17: 8 | B17: ='Primas Diciembre 2024'!L11 -> SEGUROS ATLÁNTIDA | C17: =('Primas Diciembre 2024'!L14)/1000 -> 15.369216 | D17: =('Primas Diciembre 2025'!H14)/1000 -> 16.82632 | E17: =IFERROR(F17/C17,0%) -> 0.094806652 | F17: =IFERROR(D17-C17,0) -> 1.4571039 | G17: =('Siniestros Diciembre 2024'!Q14)/1000 -> 4.4484694 | H17: =('Siniestros Diciembre 2025'!N14)/1000 -> 5.233725 | I17: =IFERROR(J17/G17,0%) -> 0.17652267 | J17: =IFERROR(H17-G17,0) -> 0.78525568 | K17: =IFERROR((G17/C17),0%) -> 0.28944023 | L17: =IFERROR(H17/D17,0%) -> 0.31104396 | M17: =IFERROR(N17/K17,0%) -> 0.074639678 | N17: =IFERROR(L17-K17,0) -> 0.021603726 | O17: =C17/$C$22 -> 0.037200193 | P17: =D17/$D$22 -> 0.032935173 | Q17: =IFERROR(R17/O17,0%) -> -0.11465046 | R17: =IFERROR(P17-O17,0) -> -0.0042650193
A18: 9 | B18: ='Primas Diciembre 2024'!P11 -> SEGUROS LAFISE | C18: =('Primas Diciembre 2024'!P14)/1000 -> 4.8785932 | D18: =('Primas Diciembre 2025'!L14)/1000 -> 6.7589499 | E18: =IFERROR(F18/C18,0%) -> 0.38543012 | F18: =IFERROR(D18-C18,0) -> 1.8803567 | G18: =('Siniestros Diciembre 2024'!Y14)/1000 -> 2.3145313 | H18: =('Siniestros Diciembre 2025'!V14)/1000 -> 4.8600086 | I18: =IFERROR(J18/G18,0%) -> 1.0997809 | J18: =IFERROR(H18-G18,0) -> 2.5454773 | K18: =IFERROR((G18/C18),0%) -> 0.47442597 | L18: =IFERROR(H18/D18,0%) -> 0.71904788 | M18: =IFERROR(N18/K18,0%) -> 0.5156166 | N18: =IFERROR(L18-K18,0) -> 0.24462191 | O18: =C18/$C$22 -> 0.011808319 | P18: =D18/$D$22 -> 0.013229702 | Q18: =IFERROR(R18/O18,0%) -> 0.12037126 | R18: =IFERROR(P18-O18,0) -> 0.0014213823
A19: 10 | B19: ='Primas Diciembre 2024'!H11 -> PALIC | C19: =('Primas Diciembre 2024'!H14)/1000 -> 5.6972507 | D19: =('Primas Diciembre 2025'!D14)/1000 -> 6.048948 | E19: =IFERROR(F19/C19,0%) -> 0.061731063 | F19: =IFERROR(D19-C19,0) -> 0.35169734 | G19: =('Siniestros Diciembre 2024'!I14)/1000 -> 0 | H19: =('Siniestros Diciembre 2025'!F14)/1000 -> 0 | I19: =IFERROR(J19/G19,0%) -> 0 | J19: =IFERROR(H19-G19,0) -> 0 | K19: =IFERROR((G19/C19),0%) -> 0 | L19: =IFERROR(H19/D19,0%) -> 0 | M19: =IFERROR(N19/K19,0%) -> 0 | N19: =IFERROR(L19-K19,0) -> 0 | O19: =C19/$C$22 -> 0.013789827 | P19: =D19/$D$22 -> 0.011839972 | Q19: =IFERROR(R19/O19,0%) -> -0.14139807 | R19: =IFERROR(P19-O19,0) -> -0.0019498549
A20: 11 | B20: ='Primas Diciembre 2024'!N11 -> SEGUROS EQUIDAD | C20: =('Primas Diciembre 2024'!N14)/1000 -> 3.4412902 | D20: =('Primas Diciembre 2025'!J14)/1000 -> 3.6603954 | E20: =IFERROR(F20/C20,0%) -> 0.063669493 | F20: =IFERROR(D20-C20,0) -> 0.2191052 | G20: =('Siniestros Diciembre 2024'!U14)/1000 -> 1.1487585 | H20: =('Siniestros Diciembre 2025'!R14)/1000 -> 1.4457465 | I20: =IFERROR(J20/G20,0%) -> 0.25852951 | J20: =IFERROR(H20-G20,0) -> 0.29698798 | K20: =IFERROR((G20/C20),0%) -> 0.33381623 | L20: =IFERROR(H20/D20,0%) -> 0.39497004 | M20: =IFERROR(N20/K20,0%) -> 0.18319602 | N20: =IFERROR(L20-K20,0) -> 0.061153806 | O20: =C20/$C$22 -> 0.0083294203 | P20: =D20/$D$22 -> 0.0071647133 | Q20: =IFERROR(R20/O20,0%) -> -0.1398305 | R20: =IFERROR(P20-O20,0) -> -0.001164707
A21: 12 | B21: ='Primas Diciembre 2024'!Q11 -> ASEGURADORA RURAL | C21: =('Primas Diciembre 2024'!Q14)/1000 -> 0 | D21: =('Primas Diciembre 2025'!M14)/1000 -> 0 | E21: =IFERROR(F21/C21,0%) -> 0 | F21: =IFERROR(D21-C21,0) -> 0 | G21: =('Siniestros Diciembre 2024'!AA14)/1000 -> 0 | H21: =('Siniestros Diciembre 2025'!X14)/1000 -> 0 | I21: =IFERROR(J21/G21,0%) -> 0 | J21: =IFERROR(H21-G21,0) -> 0 | K21: =IFERROR((G21/C21),0%) -> 0 | L21: =IFERROR(H21/D21,0%) -> 0 | M21: =IFERROR(N21/K21,0%) -> 0 | N21: =IFERROR(L21-K21,0) -> 0 | O21: =C21/$C$22 -> 0 | P21: =D21/$D$22 -> 0 | Q21: =IFERROR(R21/O21,0%) -> 0 | R21: =IFERROR(P21-O21,0) -> 0
A22: Total general | C22: =SUM(C10:C21) -> 413.14882 | D22: =SUM(D10:D21) -> 510.89209 | E22: =D22/C22-1 -> 0.23658127 | F22: =D22-C22 -> 97.743271 | G22: =SUM(G10:G21) -> 76.625171 | H22: =SUM(H10:H21) -> 92.908461 | I22: =H22/G22-1 -> 0.21250576 | J22: =H22-G22 -> 16.28329 | K22: =IFERROR((G22/C22),0%) -> 0.18546627 | L22: =IFERROR(H22/D22,0%) -> 0.18185535 | M22: =IFERROR(N22/K22,0%) -> -0.019469413 | N22: =L22-K22 -> -0.0036109195
A24: ='1. Ramos Totales'!A$24 -> Inflación Interanual Diciembre 2025 | E24: ='1. Ramos Totales'!$D$24 -> 0.0498 | G24: ='1. Ramos Totales'!$F$24 -> Inflación Acumulada Diciembre 2025 | J24: ='1. Ramos Totales'!$J$24 -> 0.0498
A25: Crecimiento Real | E25: =E22-E24 -> 0.18678127

Sheet 4. Incendio y Líneas Aliadas
A1: Sector Asegurador Hondureño
A2: Situación de Primas y Siniestros por Ramo
A3: ='1. Ramos Totales'!A3 -> Al 31 de diciembre de 2025
A4: (Valores en millones de Lempiras y Porcentajes)
A6: 4. Incendio y Líneas Aliadas
A8: No. | B8: Compañía | C8: Primas | G8: Siniestros | K8: Siniestros/Primas | O8: Participación de mercado
C9: ='1. Ramos Totales'!$B$9 -> 45657 | D9: ='1. Ramos Totales'!$C$9 -> 46022 | E9: Relativa | F9: Absoluta | G9: ='1. Ramos Totales'!$B$9 -> 45657 | H9: ='1. Ramos Totales'!$C$9 -> 46022 | I9: Relativa | J9: Absoluta | K9: ='1. Ramos Totales'!$B$9 -> 45657 | L9: ='1. Ramos Totales'!$C$9 -> 46022 | M9: Relativa | N9: Absoluta | O9: ='1. Ramos Totales'!$B$9 -> 45657 | P9: ='1. Ramos Totales'!$C$9 -> 46022 | Q9: Relativa | R9: Absoluta
A10: 1 | B10: ='Primas Diciembre 2024'!J11 -> FICOHSA SEGUROS | C10: =('Primas Diciembre 2024'!J58)/1000 -> 1164.2643 | D10: =('Primas Diciembre 2025'!F58)/1000 -> 1159.6979 | E10: =IFERROR(F10/C10,0%) -> -0.0039221191 | F10: =IFERROR(D10-C10,0) -> -4.5663831 | G10: =('Siniestros Diciembre 2024'!M58)/1000 -> 68.421988 | H10: =('Siniestros Diciembre 2025'!J58)/1000 -> 146.97505 | I10: =IFERROR(J10/G10,0%) -> 1.1480676 | J10: =IFERROR(H10-G10,0) -> 78.553064 | K10: =IFERROR((G10/C10),0%) -> 0.058768435 | L10: =IFERROR(H10/D10,0%) -> 0.12673564 | M10: =IFERROR(N10/K10,0%) -> 1.1565257 | N10: =L10-K10 -> 0.067967205 | O10: =C10/$C$22 -> 0.32364926 | P10: =D10/$D$22 -> 0.29031274 | Q10: =IFERROR(R10/O10,0%) -> -0.10300198 | R10: =IFERROR(P10-O10,0) -> -0.033336516
A11: 2 | B11: ='Primas Diciembre 2024'!L11 -> SEGUROS ATLÁNTIDA | C11: =('Primas Diciembre 2024'!L58)/1000 -> 404.34219 | D11: =('Primas Diciembre 2025'!H58)/1000 -> 507.9287 | E11: =IFERROR(F11/C11,0%) -> 0.25618528 | F11: =IFERROR(D11-C11,0) -> 103.58652 | G11: =('Siniestros Diciembre 2024'!Q58)/1000 -> 347.22973 | H11: =('Siniestros Diciembre 2025'!N58)/1000 -> 56.292693 | I11: =IFERROR(J11/G11,0%) -> -0.83788055 | J11: =IFERROR(H11-G11,0) -> -290.93704 | K11: =IFERROR((G11/C11),0%) -> 0.85875217 | L11: =IFERROR(H11/D11,0%) -> 0.11082794 | M11: =IFERROR(N11/K11,0%) -> -0.87094304 | N11: =L11-K11 -> -0.74792423 | O11: =C11/$C$22 -> 0.1124015 | P11: =D11/$D$22 -> 0.12715223 | Q11: =IFERROR(R11/O11,0%) -> 0.13123253 | R11: =IFERROR(P11-O11,0) -> 0.014750733
A12: 3 | B12: ='Primas Diciembre 2024'!R11 -> ASSA CIA. DE SEGUROS | C12: =('Primas Diciembre 2024'!R58)/1000 -> 482.8612 | D12: =('Primas Diciembre 2025'!N58)/1000 -> 467.57174 | E12: =IFERROR(F12/C12,0%) -> -0.031664309 | F12: =IFERROR(D12-C12,0) -> -15.289467 | G12: =('Siniestros Diciembre 2024'!AC58)/1000 -> 55.235579 | H12: =('Siniestros Diciembre 2025'!Z58)/1000 -> 1241.9449 | I12: =IFERROR(J12/G12,0%) -> 21.484509 | J12: =IFERROR(H12-G12,0) -> 1186.7093 | K12: =IFERROR((G12/C12),0%) -> 0.11439225 | L12: =IFERROR(H12/D12,0%) -> 2.656159 | M12: =IFERROR(N12/K12,0%) -> 22.219746 | N12: =L12-K12 -> 2.5417667 | O12: =C12/$C$22 -> 0.13422869 | P12: =D12/$D$22 -> 0.11704948 | Q12: =IFERROR(R12/O12,0%) -> -0.12798466 | R12: =IFERROR(P12-O12,0) -> -0.017179213
A13: 4 | B13: ='Primas Diciembre 2024'!I11 -> MAPFRE SEGUROS | C13: =('Primas Diciembre 2024'!I58)/1000 -> 418.04862 | D13: =('Primas Diciembre 2025'!E58)/1000 -> 404.74271 | E13: =IFERROR(F13/C13,0%) -> -0.031828621 | F13: =IFERROR(D13-C13,0) -> -13.305911 | G13: =('Siniestros Diciembre 2024'!K58)/1000 -> 145.48332 | H13: =('Siniestros Diciembre 2025'!H58)/1000 -> 36.105767 | I13: =IFERROR(J13/G13,0%) -> -0.75182196 | J13: =IFERROR(H13-G13,0) -> -109.37756 | K13: =IFERROR((G13/C13),0%) -> 0.34800575 | L13: =IFERROR(H13/D13,0%) -> 0.089206713 | M13: =IFERROR(N13/K13,0%) -> -0.74366311 | N13: =L13-K13 -> -0.25879904 | O13: =C13/$C$22 -> 0.1162117 | P13: =D13/$D$22 -> 0.10132119 | Q13: =IFERROR(R13/O13,0%) -> -0.12813263 | R13: =IFERROR(P13-O13,0) -> -0.01489051
A14: 5 | B14: ='Primas Diciembre 2024'!O11 -> SEGUROS DEL PAÍS | C14: =('Primas Diciembre 2024'!O58)/1000 -> 389.23292 | D14: =('Primas Diciembre 2025'!K58)/1000 -> 388.80806 | E14: =IFERROR(F14/C14,0%) -> -0.001091513 | F14: =IFERROR(D14-C14,0) -> -0.42485279 | G14: =('Siniestros Diciembre 2024'!W58)/1000 -> 42.446308 | H14: =('Siniestros Diciembre 2025'!T58)/1000 -> 176.41223 | I14: =IFERROR(J14/G14,0%) -> 3.1561267 | J14: =IFERROR(H14-G14,0) -> 133.96593 | K14: =IFERROR((G14/C14),0%) -> 0.10905118 | L14: =IFERROR(H14/D14,0%) -> 0.45372576 | M14: =IFERROR(N14/K14,0%) -> 3.1606681 | N14: =L14-K14 -> 0.34467458 | O14: =C14/$C$22 -> 0.10820133 | P14: =D14/$D$22 -> 0.09733219 | Q14: =IFERROR(R14/O14,0%) -> -0.10045294 | R14: =IFERROR(P14-O14,0) -> -0.010869142
A15: 6 | B15: ='Primas Diciembre 2024'!M11 -> CREFISA | C15: =('Primas Diciembre 2024'!M58)/1000 -> 157.57078 | D15: =('Primas Diciembre 2025'!I58)/1000 -> 337.29489 | E15: =IFERROR(F15/C15,0%) -> 1.1405929 | F15: =IFERROR(D15-C15,0) -> 179.72411 | G15: =('Siniestros Diciembre 2024'!S58)/1000 -> 14.664876 | H15: =('Siniestros Diciembre 2025'!P58)/1000 -> 9.0670237 | I15: =IFERROR(J15/G15,0%) -> -0.38171836 | J15: =IFERROR(H15-G15,0) -> -5.5978526 | K15: =IFERROR((G15/C15),0%) -> 0.093068503 | L15: =IFERROR(H15/D15,0%) -> 0.026881593 | M15: =IFERROR(N15/K15,0%) -> -0.71116337 | N15: =L15-K15 -> -0.06618691 | O15: =C15/$C$22 -> 0.043802482 | P15: =D15/$D$22 -> 0.084436649 | Q15: =IFERROR(R15/O15,0%) -> 0.92766812 | R15: =IFERROR(P15-O15,0) -> 0.040634167
A16: 7 | B16: ='Primas Diciembre 2024'!G11 -> SEGUROS DAVIVIENDA | C16: =('Primas Diciembre 2024'!G58)/1000 -> 250.2576 | D16: =('Primas Diciembre 2025'!C58)/1000 -> 289.02377 | E16: =IFERROR(F16/C16,0%) -> 0.15490508 | F16: =IFERROR(D16-C16,0) -> 38.766174 | G16: =('Siniestros Diciembre 2024'!G58)/1000 -> 249.1987 | H16: =('Siniestros Diciembre 2025'!D58)/1000 -> 6.7657205 | I16: =IFERROR(J16/G16,0%) -> -0.9728501 | J16: =IFERROR(H16-G16,0) -> -242.43298 | K16: =IFERROR((G16/C16),0%) -> 0.99576878 | L16: =IFERROR(H16/D16,0%) -> 0.023408872 | M16: =IFERROR(N16/K16,0%) -> -0.97649166 | N16: =L16-K16 -> -0.97235991 | O16: =C16/$C$22 -> 0.069568129 | P16: =D16/$D$22 -> 0.07235271 | Q16: =IFERROR(R16/O16,0%) -> 0.040026676 | R16: =IFERROR(P16-O16,0) -> 0.002784581
A17: 8 | B17: ='Primas Diciembre 2024'!K11 -> SEGUROS CONTINENTAL | C17: =('Primas Diciembre 2024'!K58)/1000 -> 182.8888 | D17: =('Primas Diciembre 2025'!G58)/1000 -> 212.24821 | E17: =IFERROR(F17/C17,0%) -> 0.16053146 | F17: =IFERROR(D17-C17,0) -> 29.359405 | G17: =('Siniestros Diciembre 2024'!O58)/1000 -> 26.92279 | H17: =('Siniestros Diciembre 2025'!L58)/1000 -> 12.979744 | I17: =IFERROR(J17/G17,0%) -> -0.51789009 | J17: =IFERROR(H17-G17,0) -> -13.943046 | K17: =IFERROR((G17/C17),0%) -> 0.14720852 | L17: =IFERROR(H17/D17,0%) -> 0.061153609 | M17: =IFERROR(N17/K17,0%) -> -0.58457834 | N17: =L17-K17 -> -0.086054914 | O17: =C17/$C$22 -> 0.05084054 | P17: =D17/$D$22 -> 0.053133113 | Q17: =IFERROR(R17/O17,0%) -> 0.045093394 | R17: =IFERROR(P17-O17,0) -> 0.0022925725
A18: 9 | B18: ='Primas Diciembre 2024'!P11 -> SEGUROS LAFISE | C18: =('Primas Diciembre 2024'!P58)/1000 -> 47.272342 | D18: =('Primas Diciembre 2025'!L58)/1000 -> 134.69261 | E18: =IFERROR(F18/C18,0%) -> 1.8492899 | F18: =IFERROR(D18-C18,0) -> 87.420265 | G18: =('Siniestros Diciembre 2024'!Y58)/1000 -> 8.8217414 | H18: =('Siniestros Diciembre 2025'!V58)/1000 -> 1.9142493 | I18: =IFERROR(J18/G18,0%) -> -0.78300778 | J18: =IFERROR(H18-G18,0) -> -6.9074921 | K18: =IFERROR((G18/C18),0%) -> 0.18661528 | L18: =IFERROR(H18/D18,0%) -> 0.014211985 | M18: =IFERROR(N18/K18,0%) -> -0.9238434 | N18: =L18-K18 -> -0.1724033 | O18: =C18/$C$22 -> 0.013141053 | P18: =D18/$D$22 -> 0.033718247 | Q18: =IFERROR(R18/O18,0%) -> 1.565871 | R18: =IFERROR(P18-O18,0) -> 0.020577194
A19: 10 | B19: ='Primas Diciembre 2024'!N11 -> SEGUROS EQUIDAD | C19: =('Primas Diciembre 2024'!N58)/1000 -> 68.173871 | D19: =('Primas Diciembre 2025'!J58)/1000 -> 58.953565 | E19: =IFERROR(F19/C19,0%) -> -0.13524693 | F19: =IFERROR(D19-C19,0) -> -9.2203067 | G19: =('Siniestros Diciembre 2024'!U58)/1000 -> 64.22413 | H19: =('Siniestros Diciembre 2025'!R58)/1000 -> 7.1290362 | I19: =IFERROR(J19/G19,0%) -> -0.88899754 | J19: =IFERROR(H19-G19,0) -> -57.095094 | K19: =IFERROR((G19/C19),0%) -> 0.94206371 | L19: =IFERROR(H19/D19,0%) -> 0.1209263 | M19: =IFERROR(N19/K19,0%) -> -0.87163682 | N19: =L19-K19 -> -0.82113741 | O19: =C19/$C$22 -> 0.018951387 | P19: =D19/$D$22 -> 0.014758129 | Q19: =IFERROR(R19/O19,0%) -> -0.22126391 | R19: =IFERROR(P19-O19,0) -> -0.0041932581
A20: 11 | B20: ='Primas Diciembre 2024'!Q11 -> ASEGURADORA RURAL | C20: =('Primas Diciembre 2024'!Q58)/1000 -> 32.389875 | D20: =('Primas Diciembre 2025'!M58)/1000 -> 33.688188 | E20: =IFERROR(F20/C20,0%) -> 0.04008389 | F20: =IFERROR(D20-C20,0) -> 1.2983122 | G20: =('Siniestros Diciembre 2024'!AA58)/1000 -> 6.139019 | H20: =('Siniestros Diciembre 2025'!X58)/1000 -> 2.1985052 | I20: =IFERROR(J20/G20,0%) -> -0.64188005 | J20: =IFERROR(H20-G20,0) -> -3.9405138 | K20: =IFERROR((G20/C20),0%) -> 0.18953512 | L20: =IFERROR(H20/D20,0%) -> 0.065260417 | M20: =IFERROR(N20/K20,0%) -> -0.65568167 | N20: =L20-K20 -> -0.1242747 | O20: =C20/$C$22 -> 0.0090039344 | P20: =D20/$D$22 -> 0.0084333258 | Q20: =IFERROR(R20/O20,0%) -> -0.063373253 | R20: =IFERROR(P20-O20,0) -> -0.00057060861
A21: 12 | B21: ='Primas Diciembre 2024'!H11 -> PALIC | C21: =('Primas Diciembre 2024'!H58)/1000 -> 0 | D21: =('Primas Diciembre 2025'!D58)/1000 -> 0 | E21: =IFERROR(F21/C21,0%) -> 0 | F21: =IFERROR(D21-C21,0) -> 0 | G21: =('Siniestros Diciembre 2024'!I58)/1000 -> 0 | H21: =('Siniestros Diciembre 2025'!F58)/1000 -> 0 | J21: =IFERROR(H21-G21,0) -> 0 | O21: =C21/$C$22 -> 0 | P21: =D21/$D$22 -> 0 | Q21: =IFERROR(R21/O21,0%) -> 0 | R21: =IFERROR(P21-O21,0) -> 0
A22: Total general | C22: =SUM(C10:C21) -> 3597.3025 | D22: =SUM(D10:D21) -> 3994.6503 | E22: =IFERROR(F22/C22,0%) -> 0.11045717 | F22: =IFERROR(D22-C22,0) -> 397.34786 | G22: =SUM(G10:G21) -> 1028.7882 | H22: =SUM(H10:H21) -> 1697.7849 | I22: =IFERROR(J22/G22,0%) -> 0.65027641 | J22: =IFERROR(H22-G22,0) -> 668.99669 | K22: =IFERROR((G22/C22),0%) -> 0.28598879 | L22: =IFERROR(H22/D22,0%) -> 0.42501464 | M22: =IFERROR(N22/K22,0%) -> 0.48612342 | N22: =L22-K22 -> 0.13902585
A24: ='1. Ramos Totales'!A$24 -> Inflación Interanual Diciembre 2025 | E24: ='1. Ramos Totales'!$D$24 -> 0.0498 | G24: ='1. Ramos Totales'!$F$24 -> Inflación Acumulada Diciembre 2025 | J24: ='1. Ramos Totales'!$J$24 -> 0.0498
A25: Crecimiento Real | E25: =E22-E24 -> 0.060657173

Sheet 5. Vehículos Automotores
A1: Sector Asegurador Hondureño
A2: Situación de Primas y Siniestros por Ramo
A3: ='1. Ramos Totales'!A3 -> Al 31 de diciembre de 2025
A4: (Valores en millones de Lempiras y Porcentajes)
A6: 5. Vehículos Automotores
A8: No. | B8: Compañía | C8: Primas | G8: Siniestros | K8: Siniestros/Primas | O8: Participación de mercado
C9: ='1. Ramos Totales'!$B$9 -> 45657 | D9: ='1. Ramos Totales'!$C$9 -> 46022 | E9: Relativa | F9: Absoluta | G9: ='1. Ramos Totales'!$B$9 -> 45657 | H9: ='1. Ramos Totales'!$C$9 -> 46022 | I9: Relativa | J9: Absoluta | K9: ='1. Ramos Totales'!$B$9 -> 45657 | L9: ='1. Ramos Totales'!$C$9 -> 46022 | M9: Relativa | N9: Absoluta | O9: ='1. Ramos Totales'!$B$9 -> 45657 | P9: ='1. Ramos Totales'!$C$9 -> 46022 | Q9: Relativa | R9: Absoluta
A10: 1 | B10: ='Primas Diciembre 2024'!J11 -> FICOHSA SEGUROS | C10: =('Primas Diciembre 2024'!J59)/1000 -> 594.39363 | D10: =('Primas Diciembre 2025'!F59)/1000 -> 677.14787 | E10: =IFERROR(F10/C10,0%) -> 0.13922464 | F10: =IFERROR(D10-C10,0) -> 82.754238 | G10: =('Siniestros Diciembre 2024'!M59)/1000 -> 280.72304 | H10: =('Siniestros Diciembre 2025'!J59)/1000 -> 329.99564 | I10: =IFERROR(J10/G10,0%) -> 0.17552033 | J10: =IFERROR(H10-G10,0) -> 49.2726 | K10: =IFERROR((G10/C10),0%) -> 0.47228474 | L10: =IFERROR(H10/D10,0%) -> 0.48733173 | M10: =IFERROR(N10/K10,0%) -> 0.031859993 | N10: =L10-K10 -> 0.015046989 | O10: =C10/$C$22 -> 0.21106252 | P10: =D10/$D$22 -> 0.21630429 | Q10: =IFERROR(R10/O10,0%) -> 0.024835174 | R10: =IFERROR(P10-O10,0) -> 0.0052417742
A11: 2 | B11: ='Primas Diciembre 2024'!L11 -> SEGUROS ATLÁNTIDA | C11: =('Primas Diciembre 2024'!L59)/1000 -> 614.34834 | D11: =('Primas Diciembre 2025'!H59)/1000 -> 651.21752 | E11: =IFERROR(F11/C11,0%) -> 0.060013479 | F11: =IFERROR(D11-C11,0) -> 36.869181 | G11: =('Siniestros Diciembre 2024'!Q59)/1000 -> 311.0606 | H11: =('Siniestros Diciembre 2025'!N59)/1000 -> 338.76123 | I11: =IFERROR(J11/G11,0%) -> 0.089052206 | J11: =IFERROR(H11-G11,0) -> 27.700633 | K11: =IFERROR((G11/C11),0%) -> 0.5063261 | L11: =IFERROR(H11/D11,0%) -> 0.52019674 | M11: =IFERROR(N11/K11,0%) -> 0.027394677 | N11: =L11-K11 -> 0.01387064 | O11: =C11/$C$22 -> 0.21814821 | P11: =D11/$D$22 -> 0.20802125 | Q11: =IFERROR(R11/O11,0%) -> -0.046422399 | R11: =IFERROR(P11-O11,0) -> -0.010126963
A12: 3 | B12: ='Primas Diciembre 2024'!I11 -> MAPFRE SEGUROS | C12: =('Primas Diciembre 2024'!I59)/1000 -> 417.05204 | D12: =('Primas Diciembre 2025'!E59)/1000 -> 437.0125 | E12: =IFERROR(F12/C12,0%) -> 0.047860845 | F12: =IFERROR(D12-C12,0) -> 19.960463 | G12: =('Siniestros Diciembre 2024'!K59)/1000 -> 245.03281 | H12: =('Siniestros Diciembre 2025'!H59)/1000 -> 261.70377 | I12: =IFERROR(J12/G12,0%) -> 0.068035628 | J12: =IFERROR(H12-G12,0) -> 16.670961 | K12: =IFERROR((G12/C12),0%) -> 0.58753534 | L12: =IFERROR(H12/D12,0%) -> 0.59884734 | M12: =IFERROR(N12/K12,0%) -> 0.019253304 | N12: =L12-K12 -> 0.011311996 | O12: =C12/$C$22 -> 0.1480905 | P12: =D12/$D$22 -> 0.1395968 | Q12: =IFERROR(R12/O12,0%) -> -0.057354788 | R12: =IFERROR(P12-O12,0) -> -0.0084936995
A13: 4 | B13: ='Primas Diciembre 2024'!G11 -> SEGUROS DAVIVIENDA | C13: =('Primas Diciembre 2024'!G59)/1000 -> 358.39109 | D13: =('Primas Diciembre 2025'!C59)/1000 -> 388.50748 | E13: =IFERROR(F13/C13,0%) -> 0.084032185 | F13: =IFERROR(D13-C13,0) -> 30.116387 | G13: =('Siniestros Diciembre 2024'!G59)/1000 -> 276.95293 | H13: =('Siniestros Diciembre 2025'!D59)/1000 -> 290.43406 | I13: =IFERROR(J13/G13,0%) -> 0.048676619 | J13: =IFERROR(H13-G13,0) -> 13.481132 | K13: =IFERROR((G13/C13),0%) -> 0.77276732 | L13: =IFERROR(H13/D13,0%) -> 0.74756362 | M13: =IFERROR(N13/K13,0%) -> -0.032614868 | N13: =L13-K13 -> -0.025203704 | O13: =C13/$C$22 -> 0.12726066 | P13: =D13/$D$22 -> 0.12410263 | Q13: =IFERROR(R13/O13,0%) -> -0.02481541 | R13: =IFERROR(P13-O13,0) -> -0.0031580254
A14: 5 | B14: ='Primas Diciembre 2024'!O11 -> SEGUROS DEL PAÍS | C14: =('Primas Diciembre 2024'!O59)/1000 -> 231.413 | D14: =('Primas Diciembre 2025'!K59)/1000 -> 290.12756 | E14: =IFERROR(F14/C14,0%) -> 0.25372194 | F14: =IFERROR(D14-C14,0) -> 58.714557 | G14: =('Siniestros Diciembre 2024'!W59)/1000 -> 198.1131 | H14: =('Siniestros Diciembre 2025'!T59)/1000 -> 237.42301 | I14: =IFERROR(J14/G14,0%) -> 0.19842155 | J14: =IFERROR(H14-G14,0) -> 39.309909 | K14: =IFERROR((G14/C14),0%) -> 0.85610187 | L14: =IFERROR(H14/D14,0%) -> 0.81834009 | M14: =IFERROR(N14/K14,0%) -> -0.04410898 | N14: =L14-K14 -> -0.03776178 | O14: =C14/$C$22 -> 0.082172164 | P14: =D14/$D$22 -> 0.092676709 | Q14: =IFERROR(R14/O14,0%) -> 0.12783581 | R14: =IFERROR(P14-O14,0) -> 0.010504545
A15: 6 | B15: ='Primas Diciembre 2024'!M11 -> CREFISA | C15: =('Primas Diciembre 2024'!M59)/1000 -> 174.47333 | D15: =('Primas Diciembre 2025'!I59)/1000 -> 208.86037 | E15: =IFERROR(F15/C15,0%) -> 0.19709049 | F15: =IFERROR(D15-C15,0) -> 34.387035 | G15: =('Siniestros Diciembre 2024'!S59)/1000 -> 94.273134 | H15: =('Siniestros Diciembre 2025'!P59)/1000 -> 134.01072 | I15: =IFERROR(J15/G15,0%) -> 0.42151552 | J15: =IFERROR(H15-G15,0) -> 39.737589 | K15: =IFERROR((G15/C15),0%) -> 0.54032976 | L15: =IFERROR(H15/D15,0%) -> 0.64162831 | M15: =IFERROR(N15/K15,0%) -> 0.18747541 | N15: =L15-K15 -> 0.10129854 | O15: =C15/$C$22 -> 0.061953524 | P15: =D15/$D$22 -> 0.066717175 | Q15: =IFERROR(R15/O15,0%) -> 0.076890723 | R15: =IFERROR(P15-O15,0) -> 0.0047636512
A16: 7 | B16: ='Primas Diciembre 2024'!K11 -> SEGUROS CONTINENTAL | C16: =('Primas Diciembre 2024'!K59)/1000 -> 157.57675 | D16: =('Primas Diciembre 2025'!G59)/1000 -> 185.08496 | E16: =IFERROR(F16/C16,0%) -> 0.17457025 | F16: =IFERROR(D16-C16,0) -> 27.508212 | G16: =('Siniestros Diciembre 2024'!O59)/1000 -> 86.705347 | H16: =('Siniestros Diciembre 2025'!L59)/1000 -> 96.00645 | I16: =IFERROR(J16/G16,0%) -> 0.10727254 | J16: =IFERROR(H16-G16,0) -> 9.3011029 | K16: =IFERROR((G16/C16),0%) -> 0.55024201 | L16: =IFERROR(H16/D16,0%) -> 0.51871556 | M16: =IFERROR(N16/K16,0%) -> -0.057295601 | N16: =L16-K16 -> -0.031526446 | O16: =C16/$C$22 -> 0.055953738 | P16: =D16/$D$22 -> 0.059122495 | Q16: =IFERROR(R16/O16,0%) -> 0.056631733 | R16: =IFERROR(P16-O16,0) -> 0.0031687571
A17: 8 | B17: ='Primas Diciembre 2024'!P11 -> SEGUROS LAFISE | C17: =('Primas Diciembre 2024'!P59)/1000 -> 96.61146 | D17: =('Primas Diciembre 2025'!L59)/1000 -> 113.41348 | E17: =IFERROR(F17/C17,0%) -> 0.17391334 | F17: =IFERROR(D17-C17,0) -> 16.802021 | G17: =('Siniestros Diciembre 2024'!Y59)/1000 -> 68.898812 | H17: =('Siniestros Diciembre 2025'!V59)/1000 -> 67.252604 | I17: =IFERROR(J17/G17,0%) -> -0.023893127 | J17: =IFERROR(H17-G17,0) -> -1.6462081 | K17: =IFERROR((G17/C17),0%) -> 0.71315362 | L17: =IFERROR(H17/D17,0%) -> 0.59298598 | M17: =IFERROR(N17/K17,0%) -> -0.16850176 | N17: =L17-K17 -> -0.12016764 | O17: =C17/$C$22 -> 0.034305647 | P17: =D17/$D$22 -> 0.036228162 | Q17: =IFERROR(R17/O17,0%) -> 0.05604078 | R17: =IFERROR(P17-O17,0) -> 0.0019225152
A18: 9 | B18: ='Primas Diciembre 2024'!Q11 -> ASEGURADORA RURAL | C18: =('Primas Diciembre 2024'!Q59)/1000 -> 85.881219 | D18: =('Primas Diciembre 2025'!M59)/1000 -> 86.20129 | E18: =IFERROR(F18/C18,0%) -> 0.0037269036 | F18: =IFERROR(D18-C18,0) -> 0.32007102 | G18: =('Siniestros Diciembre 2024'!AA59)/1000 -> 35.925658 | H18: =('Siniestros Diciembre 2025'!X59)/1000 -> 53.04833 | I18: =IFERROR(J18/G18,0%) -> 0.47661399 | J18: =IFERROR(H18-G18,0) -> 17.122671 | K18: =IFERROR((G18/C18),0%) -> 0.41831798 | L18: =IFERROR(H18/D18,0%) -> 0.61540065 | M18: =IFERROR(N18/K18,0%) -> 0.47113123 | N18: =L18-K18 -> 0.19708267 | O18: =C18/$C$22 -> 0.030495458 | P18: =D18/$D$22 -> 0.027535653 | Q18: =IFERROR(R18/O18,0%) -> -0.097057244 | R18: =IFERROR(P18-O18,0) -> -0.0029598051
A19: 10 | B19: ='Primas Diciembre 2024'!R11 -> ASSA CIA. DE SEGUROS | C19: =('Primas Diciembre 2024'!R59)/1000 -> 42.756849 | D19: =('Primas Diciembre 2025'!N59)/1000 -> 50.777558 | E19: =IFERROR(F19/C19,0%) -> 0.18758886 | F19: =IFERROR(D19-C19,0) -> 8.0207087 | G19: =('Siniestros Diciembre 2024'!AC59)/1000 -> 37.895641 | H19: =('Siniestros Diciembre 2025'!Z59)/1000 -> 30.938422 | I19: =IFERROR(J19/G19,0%) -> -0.18358892 | J19: =IFERROR(H19-G19,0) -> -6.9572198 | K19: =IFERROR((G19/C19),0%) -> 0.88630576 | L19: =IFERROR(H19/D19,0%) -> 0.60929322 | M19: =IFERROR(N19/K19,0%) -> -0.31254737 | N19: =L19-K19 -> -0.27701254 | O19: =C19/$C$22 -> 0.015182478 | P19: =D19/$D$22 -> 0.016220096 | Q19: =IFERROR(R19/O19,0%) -> 0.068343149 | R19: =IFERROR(P19-O19,0) -> 0.0010376184
A20: 11 | B20: ='Primas Diciembre 2024'!N11 -> SEGUROS EQUIDAD | C20: =('Primas Diciembre 2024'!N59)/1000 -> 43.299319 | D20: =('Primas Diciembre 2025'!J59)/1000 -> 42.183112 | E20: =IFERROR(F20/C20,0%) -> -0.025778873 | F20: =IFERROR(D20-C20,0) -> -1.1162076 | G20: =('Siniestros Diciembre 2024'!U59)/1000 -> 24.160053 | H20: =('Siniestros Diciembre 2025'!R59)/1000 -> 31.286386 | I20: =IFERROR(J20/G20,0%) -> 0.29496346 | J20: =IFERROR(H20-G20,0) -> 7.1263329 | K20: =IFERROR((G20/C20),0%) -> 0.55797767 | L20: =IFERROR(H20/D20,0%) -> 0.74168038 | M20: =IFERROR(N20/K20,0%) -> 0.3292295 | N20: =L20-K20 -> 0.18370271 | O20: =C20/$C$22 -> 0.015375103 | P20: =D20/$D$22 -> 0.013474735 | Q20: =IFERROR(R20/O20,0%) -> -0.12360035 | R20: =IFERROR(P20-O20,0) -> -0.0019003681
A21: 12 | B21: ='Primas Diciembre 2024'!H11 -> PALIC | C21: =('Primas Diciembre 2024'!H59)/1000 -> 0 | D21: =('Primas Diciembre 2025'!D59)/1000 -> 0 | F21: =IFERROR(D21-C21,0) -> 0 | G21: =('Siniestros Diciembre 2024'!I59)/1000 -> 0 | H21: =('Siniestros Diciembre 2025'!F59)/1000 -> 0 | J21: =IFERROR(H21-G21,0) -> 0 | O21: =C21/$C$22 -> 0 | P21: =D21/$D$22 -> 0 | Q21: =IFERROR(R21/O21,0%) -> 0 | R21: =IFERROR(P21-O21,0) -> 0
A22: Total general | C22: =SUM(C10:C21) -> 2816.197 | D22: =SUM(D10:D21) -> 3130.5337 | E22: =IFERROR(F22/C22,0%) -> 0.11161743 | F22: =IFERROR(D22-C22,0) -> 314.33667 | G22: =SUM(G10:G21) -> 1659.7411 | H22: =SUM(H10:H21) -> 1870.8606 | I22: =IFERROR(J22/G22,0%) -> 0.12720026 | J22: =IFERROR(H22-G22,0) -> 211.1195 | K22: =IFERROR((G22/C22),0%) -> 0.58935547 | L22: =IFERROR(H22/D22,0%) -> 0.59761715 | M22: =IFERROR(N22/K22,0%) -> 0.014018162 | N22: =L22-K22 -> 0.0082616802
A24: ='1. Ramos Totales'!A$24 -> Inflación Interanual Diciembre 2025 | E24: ='1. Ramos Totales'!$D$24 -> 0.0498 | G24: ='1. Ramos Totales'!$F$24 -> Inflación Acumulada Diciembre 2025 | J24: ='1. Ramos Totales'!$J$24 -> 0.0498
A25: Crecimiento Real | E25: =E22-E24 -> 0.061817427

Sheet 6. Otros Seguros Generales
A1: Sector Asegurador Hondureño
A2: Situación de Primas y Siniestros por Ramo
A3: ='1. Ramos Totales'!A3 -> Al 31 de diciembre de 2025
A4: (Valores en millones de Lempiras y Porcentajes)
A6: 6. Otros Seguros Generales
A8: No. | B8: Compañía | C8: Primas | G8: Siniestros | K8: Siniestros/Primas | O8: Participación de mercado
C9: ='1. Ramos Totales'!$B$9 -> 45657 | D9: ='1. Ramos Totales'!$C$9 -> 46022 | E9: Relativa | F9: Absoluta | G9: ='1. Ramos Totales'!$B$9 -> 45657 | H9: ='1. Ramos Totales'!$C$9 -> 46022 | I9: Relativa | J9: Absoluta | K9: ='1. Ramos Totales'!$B$9 -> 45657 | L9: ='1. Ramos Totales'!$C$9 -> 46022 | M9: Relativa | N9: Absoluta | O9: ='1. Ramos Totales'!$B$9 -> 45657 | P9: ='1. Ramos Totales'!$C$9 -> 46022 | Q9: Relativa | R9: Absoluta
A10: 1 | B10: ='Primas Diciembre 2024'!J11 -> FICOHSA SEGUROS | C10: =('Primas Diciembre 2024'!J22)/1000 -> 586.25879 | D10: =('Primas Diciembre 2025'!F22)/1000 -> 643.89228 | E10: =IFERROR(F10/C10,0%) -> 0.098307247 | F10: =IFERROR(D10-C10,0) -> 57.633488 | G10: =('Siniestros Diciembre 2024'!M22)/1000 -> 245.87885 | H10: =('Siniestros Diciembre 2025'!J22)/1000 -> 169.60136 | I10: =IFERROR(J10/G10,0%) -> -0.31022386 | J10: =IFERROR(H10-G10,0) -> -76.277484 | K10: =IFERROR((G10/C10),0%) -> 0.41940326 | L10: =IFERROR(H10/D10,0%) -> 0.26340021 | M10: =IFERROR(N10/K10,0%) -> -0.37196431 | N10: =L10-K10 -> -0.15600304 | O10: =C10/$C$22 -> 0.36191858 | P10: =D10/$D$22 -> 0.3553924 | Q10: =IFERROR(R10/O10,0%) -> -0.018032174 | R10: =IFERROR(P10-O10,0) -> -0.0065261789
A11: 2 | B11: ='Primas Diciembre 2024'!L11 -> SEGUROS ATLÁNTIDA | C11: =('Primas Diciembre 2024'!L22)/1000 -> 278.48827 | D11: =('Primas Diciembre 2025'!H22)/1000 -> 328.07185 | E11: =IFERROR(F11/C11,0%) -> 0.1780455 | F11: =IFERROR(D11-C11,0) -> 49.583582 | G11: =('Siniestros Diciembre 2024'!Q22)/1000 -> 34.761446 | H11: =('Siniestros Diciembre 2025'!N22)/1000 -> 40.514562 | I11: =IFERROR(J11/G11,0%) -> 0.16550277 | J11: =IFERROR(H11-G11,0) -> 5.7531157 | K11: =IFERROR((G11/C11),0%) -> 0.12482194 | L11: =IFERROR(H11/D11,0%) -> 0.12349295 | M11: =IFERROR(N11/K11,0%) -> -0.010647063 | N11: =L11-K11 -> -0.0013289871 | O11: =C11/$C$22 -> 0.17192079 | P11: =D11/$D$22 -> 0.18107725 | Q11: =IFERROR(R11/O11,0%) -> 0.053259713 | R11: =IFERROR(P11-O11,0) -> 0.0091564522
A12: 3 | B12: ='Primas Diciembre 2024'!R11 -> ASSA CIA. DE SEGUROS | C12: =('Primas Diciembre 2024'!R22)/1000 -> 212.07929 | D12: =('Primas Diciembre 2025'!N22)/1000 -> 244.16559 | E12: =IFERROR(F12/C12,0%) -> 0.15129392 | F12: =IFERROR(D12-C12,0) -> 32.086306 | G12: =('Siniestros Diciembre 2024'!AC22)/1000 -> 64.156666 | H12: =('Siniestros Diciembre 2025'!Z22)/1000 -> 53.928011 | I12: =IFERROR(J12/G12,0%) -> -0.15943245 | J12: =IFERROR(H12-G12,0) -> -10.228655 | K12: =IFERROR((G12/C12),0%) -> 0.30251264 | L12: =IFERROR(H12/D12,0%) -> 0.22086655 | M12: =IFERROR(N12/K12,0%) -> -0.26989317 | N12: =L12-K12 -> -0.081646098 | O12: =C12/$C$22 -> 0.13092415 | P12: =D12/$D$22 -> 0.1347657 | Q12: =IFERROR(R12/O12,0%) -> 0.029341825 | R12: =IFERROR(P12-O12,0) -> 0.0038415535
A13: 4 | B13: ='Primas Diciembre 2024'!O11 -> SEGUROS DEL PAÍS | C13: =('Primas Diciembre 2024'!O22)/1000 -> 153.94541 | D13: =('Primas Diciembre 2025'!K22)/1000 -> 182.91337 | E13: =IFERROR(F13/C13,0%) -> 0.18817031 | F13: =IFERROR(D13-C13,0) -> 28.967956 | G13: =('Siniestros Diciembre 2024'!W22)/1000 -> 34.097312 | H13: =('Siniestros Diciembre 2025'!T22)/1000 -> 43.53113 | I13: =IFERROR(J13/G13,0%) -> 0.27667336 | J13: =IFERROR(H13-G13,0) -> 9.4338177 | K13: =IFERROR((G13/C13),0%) -> 0.22148963 | L13: =IFERROR(H13/D13,0%) -> 0.23798769 | M13: =IFERROR(N13/K13,0%) -> 0.074486834 | N13: =L13-K13 -> 0.016498061 | O13: =C13/$C$22 -> 0.095036024 | P13: =D13/$D$22 -> 0.10095791 | Q13: =IFERROR(R13/O13,0%) -> 0.062312045 | R13: =IFERROR(P13-O13,0) -> 0.005921889
A14: 5 | B14: ='Primas Diciembre 2024'!I11 -> MAPFRE SEGUROS | C14: =('Primas Diciembre 2024'!I22)/1000 -> 132.76372 | D14: =('Primas Diciembre 2025'!E22)/1000 -> 141.48191 | E14: =IFERROR(F14/C14,0%) -> 0.06566692 | F14: =IFERROR(D14-C14,0) -> 8.7181846 | G14: =('Siniestros Diciembre 2024'!K22)/1000 -> 13.156939 | H14: =('Siniestros Diciembre 2025'!H22)/1000 -> 65.702008 | I14: =IFERROR(J14/G14,0%) -> 3.9937153 | J14: =IFERROR(H14-G14,0) -> 52.545069 | K14: =IFERROR((G14/C14),0%) -> 0.099100409 | L14: =IFERROR(H14/D14,0%) -> 0.46438453 | M14: =IFERROR(N14/K14,0%) -> 3.6860001 | N14: =L14-K14 -> 0.36528412 | O14: =C14/$C$22 -> 0.081959806 | P14: =D14/$D$22 -> 0.078090071 | Q14: =IFERROR(R14/O14,0%) -> -0.047215038 | R14: =IFERROR(P14-O14,0) -> -0.0038697354
A15: 6 | B15: ='Primas Diciembre 2024'!G11 -> SEGUROS DAVIVIENDA | C15: =('Primas Diciembre 2024'!G22)/1000 -> 87.322546 | D15: =('Primas Diciembre 2025'!C22)/1000 -> 95.124859 | E15: =IFERROR(F15/C15,0%) -> 0.089350495 | F15: =IFERROR(D15-C15,0) -> 7.8023127 | G15: =('Siniestros Diciembre 2024'!G22)/1000 -> 35.113728 | H15: =('Siniestros Diciembre 2025'!D22)/1000 -> 37.174556 | I15: =IFERROR(J15/G15,0%) -> 0.058690111 | J15: =IFERROR(H15-G15,0) -> 2.0608286 | K15: =IFERROR((G15/C15),0%) -> 0.40211525 | L15: =IFERROR(H15/D15,0%) -> 0.39079749 | M15: =IFERROR(N15/K15,0%) -> -0.028145563 | N15: =L15-K15 -> -0.01131776 | O15: =C15/$C$22 -> 0.053907339 | P15: =D15/$D$22 -> 0.052503583 | Q15: =IFERROR(R15/O15,0%) -> -0.026040172 | R15: =IFERROR(P15-O15,0) -> -0.0014037564
A16: 7 | B16: ='Primas Diciembre 2024'!M11 -> CREFISA | C16: =('Primas Diciembre 2024'!M22)/1000 -> 43.823224 | D16: =('Primas Diciembre 2025'!I22)/1000 -> 52.551284 | E16: =IFERROR(F16/C16,0%) -> 0.19916517 | F16: =IFERROR(D16-C16,0) -> 8.7280598 | G16: =('Siniestros Diciembre 2024'!S22)/1000 -> 11.480555 | H16: =('Siniestros Diciembre 2025'!P22)/1000 -> 4.1190251 | I16: =IFERROR(J16/G16,0%) -> -0.64121726 | J16: =IFERROR(H16-G16,0) -> -7.3615303 | K16: =IFERROR((G16/C16),0%) -> 0.26197423 | L16: =IFERROR(H16/D16,0%) -> 0.078381055 | M16: =IFERROR(N16/K16,0%) -> -0.70080624 | N16: =L16-K16 -> -0.18359317 | O16: =C16/$C$22 -> 0.027053648 | P16: =D16/$D$22 -> 0.029005359 | Q16: =IFERROR(R16/O16,0%) -> 0.072142258 | R16: =IFERROR(P16-O16,0) -> 0.0019517112
A17: 8 | B17: ='Primas Diciembre 2024'!P11 -> SEGUROS LAFISE | C17: =('Primas Diciembre 2024'!P22)/1000 -> 30.680129 | D17: =('Primas Diciembre 2025'!L22)/1000 -> 42.451206 | E17: =IFERROR(F17/C17,0%) -> 0.38367105 | F17: =IFERROR(D17-C17,0) -> 11.771077 | G17: =('Siniestros Diciembre 2024'!Y22)/1000 -> 1.1745536 | H17: =('Siniestros Diciembre 2025'!V22)/1000 -> 1.5437389 | I17: =IFERROR(J17/G17,0%) -> 0.31431968 | J17: =IFERROR(H17-G17,0) -> 0.36918531 | K17: =IFERROR((G17/C17),0%) -> 0.038283855 | L17: =IFERROR(H17/D17,0%) -> 0.036365019 | M17: =IFERROR(N17/K17,0%) -> -0.050121285 | N17: =L17-K17 -> -0.001918836 | O17: =C17/$C$22 -> 0.018939944 | P17: =D17/$D$22 -> 0.023430683 | Q17: =IFERROR(R17/O17,0%) -> 0.23710415 | R17: =IFERROR(P17-O17,0) -> 0.0044907392
A18: 9 | B18: ='Primas Diciembre 2024'!K11 -> SEGUROS CONTINENTAL | C18: =('Primas Diciembre 2024'!K22)/1000 -> 33.888322 | D18: =('Primas Diciembre 2025'!G22)/1000 -> 37.386609 | E18: =IFERROR(F18/C18,0%) -> 0.10322984 | F18: =IFERROR(D18-C18,0) -> 3.4982862 | G18: =('Siniestros Diciembre 2024'!O22)/1000 -> 3.9084832 | H18: =('Siniestros Diciembre 2025'!L22)/1000 -> 1.4212785 | I18: =IFERROR(J18/G18,0%) -> -0.6363606 | J18: =IFERROR(H18-G18,0) -> -2.4872047 | K18: =IFERROR((G18/C18),0%) -> 0.11533422 | L18: =IFERROR(H18/D18,0%) -> 0.038015711 | M18: =IFERROR(N18/K18,0%) -> -0.67038654 | N18: =L18-K18 -> -0.077318508 | O18: =C18/$C$22 -> 0.020920477 | P18: =D18/$D$22 -> 0.020635309 | Q18: =IFERROR(R18/O18,0%) -> -0.01363101 | R18: =IFERROR(P18-O18,0) -> -0.00028516722
A19: 10 | B19: ='Primas Diciembre 2024'!N11 -> SEGUROS EQUIDAD | C19: =('Primas Diciembre 2024'!N22)/1000 -> 44.987869 | D19: =('Primas Diciembre 2025'!J22)/1000 -> 24.701509 | E19: =IFERROR(F19/C19,0%) -> -0.45092955 | F19: =IFERROR(D19-C19,0) -> -20.28636 | G19: =('Siniestros Diciembre 2024'!U22)/1000 -> 5.5960207 | H19: =('Siniestros Diciembre 2025'!R22)/1000 -> 1.974359 | I19: =IFERROR(J19/G19,0%) -> -0.64718518 | J19: =IFERROR(H19-G19,0) -> -3.6216616 | K19: =IFERROR((G19/C19),0%) -> 0.12438955 | L19: =IFERROR(H19/D19,0%) -> 0.079928679 | M19: =IFERROR(N19/K19,0%) -> -0.35743251 | N19: =L19-K19 -> -0.044460868 | O19: =C19/$C$22 -> 0.027772625 | P19: =D19/$D$22 -> 0.013633847 | Q19: =IFERROR(R19/O19,0%) -> -0.50909045 | R19: =IFERROR(P19-O19,0) -> -0.014138778
A20: 11 | B20: ='Primas Diciembre 2024'!Q11 -> ASEGURADORA RURAL | C20: =('Primas Diciembre 2024'!Q22)/1000 -> 15.626207 | D20: =('Primas Diciembre 2025'!M22)/1000 -> 19.037966 | E20: =IFERROR(F20/C20,0%) -> 0.21833573 | F20: =IFERROR(D20-C20,0) -> 3.4117593 | G20: =('Siniestros Diciembre 2024'!AA22)/1000 -> 107.83744 | H20: =('Siniestros Diciembre 2025'!X22)/1000 -> 2.6671208 | I20: =IFERROR(J20/G20,0%) -> -0.97526721 | J20: =IFERROR(H20-G20,0) -> -105.17032 | K20: =IFERROR((G20/C20),0%) -> 6.9010635 | L20: =IFERROR(H20/D20,0%) -> 0.14009484 | M20: =IFERROR(N20/K20,0%) -> -0.97969953 | N20: =L20-K20 -> -6.7609687 | O20: =C20/$C$22 -> 0.0096466177 | P20: =D20/$D$22 -> 0.010507889 | Q20: =IFERROR(R20/O20,0%) -> 0.089282161 | R20: =IFERROR(P20-O20,0) -> 0.00086127087
A21: 12 | B21: ='Primas Diciembre 2024'!H11 -> PALIC | C21: =('Primas Diciembre 2024'!H22)/1000 -> 0 | D21: =('Primas Diciembre 2025'!D22)/1000 -> 0 | E21: =IFERROR(F21/C21,0%) -> 0 | F21: =IFERROR(D21-C21,0) -> 0 | G21: =('Siniestros Diciembre 2024'!I22)/1000 -> 0 | H21: =('Siniestros Diciembre 2025'!F22)/1000 -> 0 | I21: =IFERROR(J21/G21,0%) -> 0 | J21: =IFERROR(H21-G21,0) -> 0 | K21: =IFERROR((G21/C21),0%) -> 0 | L21: =IFERROR(H21/D21,0%) -> 0 | M21: =IFERROR(N21/K21,0%) -> 0 | N21: =L21-K21 -> 0 | O21: =C21/$C$22 -> 0 | P21: =D21/$D$22 -> 0 | Q21: =IFERROR(R21/O21,0%) -> 0 | R21: =IFERROR(P21-O21,0) -> 0
A22: Total general | C22: =SUM(C10:C21) -> 1619.8638 | D22: =SUM(D10:D21) -> 1811.7784 | E22: =IFERROR(F22/C22,0%) -> 0.1184758 | F22: =IFERROR(D22-C22,0) -> 191.91465 | G22: =SUM(G10:G21) -> 557.16199 | H22: =SUM(H10:H21) -> 422.17715 | I22: =IFERROR(J22/G22,0%) -> -0.24227216 | J22: =IFERROR(H22-G22,0) -> -134.98484 | K22: =IFERROR((G22/C22),0%) -> 0.34395608 | L22: =IFERROR(H22/D22,0%) -> 0.23301809 | M22: =IFERROR(N22/K22,0%) -> -0.32253533 | N22: =L22-K22 -> -0.11093799
A24: ='1. Ramos Totales'!A$24 -> Inflación Interanual Diciembre 2025 | E24: ='1. Ramos Totales'!$D$24 -> 0.0498 | G24: ='1. Ramos Totales'!$F$24 -> Inflación Acumulada Diciembre 2025 | J24: ='1. Ramos Totales'!$J$24 -> 0.0498
A25: Crecimiento Real | E25: =E22-E24 -> 0.068675797

Sheet 6.1 Transporte
A1: Sector Asegurador Hondureño
A2: Situación de Primas y Siniestros por Ramo
A3: ='1. Ramos Totales'!A3 -> Al 31 de diciembre de 2025
A4: (Valores en millones de Lempiras y Porcentajes)
A6: 6.1 Transporte (Terrestre, Marítimo y Aéreo)
A8: No. | B8: Compañía | C8: Primas | G8: Siniestros | K8: Siniestros/Primas | O8: Participación de mercado
C9: ='1. Ramos Totales'!$B$9 -> 45657 | D9: ='1. Ramos Totales'!$C$9 -> 46022 | E9: Relativa | F9: Absoluta | G9: ='1. Ramos Totales'!$B$9 -> 45657 | H9: ='1. Ramos Totales'!$C$9 -> 46022 | I9: Relativa | J9: Absoluta | K9: ='1. Ramos Totales'!$B$9 -> 45657 | L9: ='1. Ramos Totales'!$C$9 -> 46022 | M9: Relativa | N9: Absoluta | O9: ='1. Ramos Totales'!$B$9 -> 45657 | P9: ='1. Ramos Totales'!$C$9 -> 46022 | Q9: Relativa | R9: Absoluta
A10: 1 | B10: ='Primas Diciembre 2024'!J11 -> FICOHSA SEGUROS | C10: =('Primas Diciembre 2024'!J42+'Primas Diciembre 2024'!J43+'Primas Diciembre 2024'!J44)/1000 -> 80.728903 | D10: =('Primas Diciembre 2025'!F42+'Primas Diciembre 2025'!F43+'Primas Diciembre 2025'!F44)/1000 -> 78.403282 | E10: =IFERROR(F10/C10,0%) -> -0.028807783 | F10: =IFERROR(D10-C10,0) -> -2.3256207 | G10: =('Siniestros Diciembre 2024'!M42+'Siniestros Diciembre 2024'!M43+'Siniestros Diciembre 2024'!M44)/1000 -> 9.3793241 | H10: =('Siniestros Diciembre 2025'!J42+'Siniestros Diciembre 2025'!J43+'Siniestros Diciembre 2025'!J44)/1000 -> 17.621395 | I10: =IFERROR(J10/G10,0%) -> 0.87874888 | J10: =IFERROR(H10-G10,0) -> 8.2420706 | K10: =IFERROR((G10/C10),0%) -> 0.11618297 | L10: =IFERROR(H10/D10,0%) -> 0.22475328 | M10: =IFERROR(N10/K10,0%) -> 0.93447687 | N10: =L10-K10 -> 0.1085703 | O10: =C10/$C$22 -> 0.29145734 | P10: =D10/$D$22 -> 0.25590729 | Q10: =IFERROR(R10/O10,0%) -> -0.12197343 | R10: =IFERROR(P10-O10,0) -> -0.035550051
A11: 2 | B11: ='Primas Diciembre 2024'!O11 -> SEGUROS DEL PAÍS | C11: =('Primas Diciembre 2024'!O42+'Primas Diciembre 2024'!O43+'Primas Diciembre 2024'!O44)/1000 -> 34.235008 | D11: =('Primas Diciembre 2025'!K42+'Primas Diciembre 2025'!K43+'Primas Diciembre 2025'!K44)/1000 -> 51.425013 | E11: =IFERROR(F11/C11,0%) -> 0.50211776 | F11: =IFERROR(D11-C11,0) -> 17.190005 | G11: =('Siniestros Diciembre 2024'!W42+'Siniestros Diciembre 2024'!W43+'Siniestros Diciembre 2024'!W44)/1000 -> 16.02507 | H11: =('Siniestros Diciembre 2025'!T42+'Siniestros Diciembre 2025'!T43+'Siniestros Diciembre 2025'!T44)/1000 -> 5.5645131 | I11: =IFERROR(J11/G11,0%) -> -0.65276201 | J11: =IFERROR(H11-G11,0) -> -10.460557 | K11: =IFERROR((G11/C11),0%) -> 0.46809015 | L11: =IFERROR(H11/D11,0%) -> 0.10820635 | M11: =IFERROR(N11/K11,0%) -> -0.76883437 | N11: =L11-K11 -> -0.3598838 | O11: =C11/$C$22 -> 0.1235994 | P11: =D11/$D$22 -> 0.16785057 | Q11: =IFERROR(R11/O11,0%) -> 0.35802088 | R11: =IFERROR(P11-O11,0) -> 0.044251167
A12: 3 | B12: ='Primas Diciembre 2024'!R11 -> ASSA CIA. DE SEGUROS | C12: =('Primas Diciembre 2024'!R42+'Primas Diciembre 2024'!R43+'Primas Diciembre 2024'!R44)/1000 -> 45.093812 | D12: =('Primas Diciembre 2025'!N42+'Primas Diciembre 2025'!N43+'Primas Diciembre 2025'!N44)/1000 -> 49.404024 | E12: =IFERROR(F12/C12,0%) -> 0.095583228 | F12: =IFERROR(D12-C12,0) -> 4.3102121 | G12: =('Siniestros Diciembre 2024'!AC42+'Siniestros Diciembre 2024'!AC43+'Siniestros Diciembre 2024'!AC44)/1000 -> 11.877589 | H12: =('Siniestros Diciembre 2025'!Z42+'Siniestros Diciembre 2025'!Z43+'Siniestros Diciembre 2025'!Z44)/1000 -> 19.575881 | I12: =IFERROR(J12/G12,0%) -> 0.64813588 | J12: =IFERROR(H12-G12,0) -> 7.6982916 | K12: =IFERROR((G12/C12),0%) -> 0.26339732 | L12: =IFERROR(H12/D12,0%) -> 0.39624061 | M12: =IFERROR(N12/K12,0%) -> 0.50434567 | N12: =L12-K12 -> 0.1328433 | O12: =C12/$C$22 -> 0.16280318 | P12: =D12/$D$22 -> 0.16125409 | Q12: =IFERROR(R12/O12,0%) -> -0.0095151412 | R12: =IFERROR(P12-O12,0) -> -0.0015490953
A13: 4 | B13: ='Primas Diciembre 2024'!I11 -> MAPFRE SEGUROS | C13: =('Primas Diciembre 2024'!I42+'Primas Diciembre 2024'!I43+'Primas Diciembre 2024'!I44)/1000 -> 44.939804 | D13: =('Primas Diciembre 2025'!E42+'Primas Diciembre 2025'!E43+'Primas Diciembre 2025'!E44)/1000 -> 45.083455 | E13: =IFERROR(F13/C13,0%) -> 0.0031965233 | F13: =IFERROR(D13-C13,0) -> 0.14365113 | G13: =('Siniestros Diciembre 2024'!K42+'Siniestros Diciembre 2024'!K43+'Siniestros Diciembre 2024'!K44)/1000 -> 2.3139396 | H13: =('Siniestros Diciembre 2025'!H42+'Siniestros Diciembre 2025'!H43+'Siniestros Diciembre 2025'!H44)/1000 -> 7.5212773 | I13: =IFERROR(J13/G13,0%) -> 2.2504208 | J13: =IFERROR(H13-G13,0) -> 5.2073377 | K13: =IFERROR((G13/C13),0%) -> 0.051489757 | L13: =IFERROR(H13/D13,0%) -> 0.1668301 | M13: =IFERROR(N13/K13,0%) -> 2.2400638 | N13: =L13-K13 -> 0.11534034 | O13: =C13/$C$22 -> 0.16224717 | P13: =D13/$D$22 -> 0.14715181 | Q13: =IFERROR(R13/O13,0%) -> -0.093039268 | R13: =IFERROR(P13-O13,0) -> -0.015095358
A14: 5 | B14: ='Primas Diciembre 2024'!L11 -> SEGUROS ATLÁNTIDA | C14: =('Primas Diciembre 2024'!L42+'Primas Diciembre 2024'!L43+'Primas Diciembre 2024'!L44)/1000 -> 29.429325 | D14: =('Primas Diciembre 2025'!H42+'Primas Diciembre 2025'!H43+'Primas Diciembre 2025'!H44)/1000 -> 36.468677 | E14: =IFERROR(F14/C14,0%) -> 0.23919514 | F14: =IFERROR(D14-C14,0) -> 7.0393517 | G14: =('Siniestros Diciembre 2024'!Q42+'Siniestros Diciembre 2024'!Q43+'Siniestros Diciembre 2024'!Q44)/1000 -> 17.429366 | H14: =('Siniestros Diciembre 2025'!N42+'Siniestros Diciembre 2025'!N43+'Siniestros Diciembre 2025'!N44)/1000 -> 4.4643942 | I14: =IFERROR(J14/G14,0%) -> -0.74385792 | J14: =IFERROR(H14-G14,0) -> -12.964972 | K14: =IFERROR((G14/C14),0%) -> 0.59224484 | L14: =IFERROR(H14/D14,0%) -> 0.12241722 | M14: =IFERROR(N14/K14,0%) -> -0.79329964 | N14: =L14-K14 -> -0.46982762 | O14: =C14/$C$22 -> 0.10624934 | P14: =D14/$D$22 -> 0.11903329 | Q14: =IFERROR(R14/O14,0%) -> 0.12032021 | R14: =IFERROR(P14-O14,0) -> 0.012783943
A15: 6 | B15: ='Primas Diciembre 2024'!G11 -> SEGUROS DAVIVIENDA | C15: =('Primas Diciembre 2024'!G42+'Primas Diciembre 2024'!G43+'Primas Diciembre 2024'!G44)/1000 -> 26.901442 | D15: =('Primas Diciembre 2025'!C42+'Primas Diciembre 2025'!C43+'Primas Diciembre 2025'!C44)/1000 -> 27.801913 | E15: =IFERROR(F15/C15,0%) -> 0.033472982 | F15: =IFERROR(D15-C15,0) -> 0.90047147 | G15: =('Siniestros Diciembre 2024'!G42+'Siniestros Diciembre 2024'!G43+'Siniestros Diciembre 2024'!G44)/1000 -> 11.478019 | H15: =('Siniestros Diciembre 2025'!D42+'Siniestros Diciembre 2025'!D43+'Siniestros Diciembre 2025'!D44)/1000 -> 8.8756258 | I15: =IFERROR(J15/G15,0%) -> -0.22672841 | J15: =IFERROR(H15-G15,0) -> -2.6023929 | K15: =IFERROR((G15/C15),0%) -> 0.42666928 | L15: =IFERROR(H15/D15,0%) -> 0.31924515 | M15: =IFERROR(N15/K15,0%) -> -0.25177377 | N15: =L15-K15 -> -0.10742413 | O15: =C15/$C$22 -> 0.097122868 | P15: =D15/$D$22 -> 0.090745081 | Q15: =IFERROR(R15/O15,0%) -> -0.065667204 | R15: =IFERROR(P15-O15,0) -> -0.0063777872
A16: 7 | B16: ='Primas Diciembre 2024'!M11 -> CREFISA | C16: =('Primas Diciembre 2024'!M42+'Primas Diciembre 2024'!M43+'Primas Diciembre 2024'!M44)/1000 -> 9.2033323 | D16: =('Primas Diciembre 2025'!I42+'Primas Diciembre 2025'!I43+'Primas Diciembre 2025'!I44)/1000 -> 9.3925085 | E16: =IFERROR(F16/C16,0%) -> 0.020555185 | F16: =IFERROR(D16-C16,0) -> 0.1891762 | G16: =('Siniestros Diciembre 2024'!S42+'Siniestros Diciembre 2024'!S43+'Siniestros Diciembre 2024'!S44)/1000 -> 3.0246373 | H16: =('Siniestros Diciembre 2025'!P42+'Siniestros Diciembre 2025'!P43+'Siniestros Diciembre 2025'!P44)/1000 -> 1.6392181 | I16: =IFERROR(J16/G16,0%) -> -0.45804473 | J16: =IFERROR(H16-G16,0) -> -1.3854192 | K16: =IFERROR((G16/C16),0%) -> 0.32864589 | L16: =IFERROR(H16/D16,0%) -> 0.174524 | M16: =IFERROR(N16/K16,0%) -> -0.46896035 | N16: =L16-K16 -> -0.15412189 | O16: =C16/$C$22 -> 0.033226994 | P16: =D16/$D$22 -> 0.030657025 | Q16: =IFERROR(R16/O16,0%) -> -0.077345808 | R16: =IFERROR(P16-O16,0) -> -0.0025699687
A17: 8 | B17: ='Primas Diciembre 2024'!K11 -> SEGUROS CONTINENTAL | C17: =('Primas Diciembre 2024'!K42+'Primas Diciembre 2024'!K43+'Primas Diciembre 2024'!K44)/1000 -> 3.0523291 | D17: =('Primas Diciembre 2025'!G42+'Primas Diciembre 2025'!G43+'Primas Diciembre 2025'!G44)/1000 -> 5.7575581 | E17: =IFERROR(F17/C17,0%) -> 0.88628352 | F17: =IFERROR(D17-C17,0) -> 2.705229 | G17: =('Siniestros Diciembre 2024'!O42+'Siniestros Diciembre 2024'!O43+'Siniestros Diciembre 2024'!O44)/1000 -> 0.36385366 | H17: =('Siniestros Diciembre 2025'!L42+'Siniestros Diciembre 2025'!L43+'Siniestros Diciembre 2025'!L44)/1000 -> 0.01946131 | I17: =IFERROR(J17/G17,0%) -> -0.94651336 | J17: =IFERROR(H17-G17,0) -> -0.34439235 | K17: =IFERROR((G17/C17),0%) -> 0.11920525 | L17: =IFERROR(H17/D17,0%) -> 0.0033801326 | M17: =IFERROR(N17/K17,0%) -> -0.97164443 | N17: =L17-K17 -> -0.11582512 | O17: =C17/$C$22 -> 0.011019891 | P17: =D17/$D$22 -> 0.018792595 | Q17: =IFERROR(R17/O17,0%) -> 0.70533394 | R17: =IFERROR(P17-O17,0) -> 0.0077727033
A18: 9 | B18: ='Primas Diciembre 2024'!P11 -> SEGUROS LAFISE | C18: =('Primas Diciembre 2024'!P42+'Primas Diciembre 2024'!P43+'Primas Diciembre 2024'!P44)/1000 -> 2.4124616 | D18: =('Primas Diciembre 2025'!L42+'Primas Diciembre 2025'!L43+'Primas Diciembre 2025'!L44)/1000 -> 2.1660948 | E18: =IFERROR(F18/C18,0%) -> -0.10212257 | F18: =IFERROR(D18-C18,0) -> -0.24636678 | G18: =('Siniestros Diciembre 2024'!Y42+'Siniestros Diciembre 2024'!Y43+'Siniestros Diciembre 2024'!Y44)/1000 -> 0 | H18: =('Siniestros Diciembre 2025'!V42+'Siniestros Diciembre 2025'!V43+'Siniestros Diciembre 2025'!V44)/1000 -> 0.1048728 | I18: =IFERROR(J18/G18,0%) -> 0 | J18: =IFERROR(H18-G18,0) -> 0.1048728 | K18: =IFERROR((G18/C18),0%) -> 0 | L18: =IFERROR(H18/D18,0%) -> 0.048415609 | M18: =IFERROR(N18/K18,0%) -> 0 | N18: =L18-K18 -> 0.048415609 | O18: =C18/$C$22 -> 0.0087097633 | P18: =D18/$D$22 -> 0.0070701051 | Q18: =IFERROR(R18/O18,0%) -> -0.18825519 | R18: =IFERROR(P18-O18,0) -> -0.0016396582
A19: 10 | B19: ='Primas Diciembre 2024'!N11 -> SEGUROS EQUIDAD | C19: =('Primas Diciembre 2024'!N42+'Primas Diciembre 2024'!N43+'Primas Diciembre 2024'!N44)/1000 -> 0.98718284 | D19: =('Primas Diciembre 2025'!J42+'Primas Diciembre 2025'!J43+'Primas Diciembre 2025'!J44)/1000 -> 0.47124964 | E19: =IFERROR(F19/C19,0%) -> -0.52263186 | F19: =IFERROR(D19-C19,0) -> -0.5159332 | G19: =('Siniestros Diciembre 2024'!U42+'Siniestros Diciembre 2024'!U43+'Siniestros Diciembre 2024'!U44)/1000 -> 0.01492086 | H19: =('Siniestros Diciembre 2025'!R42+'Siniestros Diciembre 2025'!R43+'Siniestros Diciembre 2025'!R44)/1000 -> 0 | I19: =IFERROR(J19/G19,0%) -> -1 | J19: =IFERROR(H19-G19,0) -> -0.01492086 | K19: =IFERROR((G19/C19),0%) -> 0.015114586 | L19: =IFERROR(H19/D19,0%) -> 0 | M19: =IFERROR(N19/K19,0%) -> -1 | N19: =L19-K19 -> -0.015114586 | O19: =C19/$C$22 -> 0.003564048 | P19: =D19/$D$22 -> 0.0015381527 | Q19: =IFERROR(R19/O19,0%) -> -0.56842538 | R19: =IFERROR(P19-O19,0) -> -0.0020258953
A20: 11 | B20: ='Primas Diciembre 2024'!Q11 -> ASEGURADORA RURAL | C20: =('Primas Diciembre 2024'!Q42+'Primas Diciembre 2024'!Q43+'Primas Diciembre 2024'!Q44)/1000 -> 0 | D20: =('Primas Diciembre 2025'!M42+'Primas Diciembre 2025'!M43+'Primas Diciembre 2025'!M44)/1000 -> 0 | E20: =IFERROR(F20/C20,0%) -> 0 | F20: =IFERROR(D20-C20,0) -> 0 | G20: =('Siniestros Diciembre 2024'!AA42+'Siniestros Diciembre 2024'!AA43+'Siniestros Diciembre 2024'!AA44)/1000 -> 0 | H20: =('Siniestros Diciembre 2025'!X42+'Siniestros Diciembre 2025'!X43+'Siniestros Diciembre 2025'!X44)/1000 -> 0 | I20: =IFERROR(J20/G20,0%) -> 0 | J20: =IFERROR(H20-G20,0) -> 0 | K20: =IFERROR((G20/C20),0%) -> 0 | L20: =IFERROR(H20/D20,0%) -> 0 | M20: =IFERROR(N20/K20,0%) -> 0 | N20: =L20-K20 -> 0 | O20: =C20/$C$22 -> 0 | P20: =D20/$D$22 -> 0 | Q20: =IFERROR(R20/O20,0%) -> 0 | R20: =IFERROR(P20-O20,0) -> 0
A21: 12 | B21: ='Primas Diciembre 2024'!H11 -> PALIC | C21: =('Primas Diciembre 2024'!H42+'Primas Diciembre 2024'!H43+'Primas Diciembre 2024'!H44)/1000 -> 0 | D21: =('Primas Diciembre 2025'!D42+'Primas Diciembre 2025'!D43+'Primas Diciembre 2025'!D44)/1000 -> 0 | E21: =IFERROR(F21/C21,0%) -> 0 | F21: =IFERROR(D21-C21,0) -> 0 | G21: =('Siniestros Diciembre 2024'!I42+'Siniestros Diciembre 2024'!I43+'Siniestros Diciembre 2024'!I44)/1000 -> 0 | H21: =('Siniestros Diciembre 2025'!F42+'Siniestros Diciembre 2025'!F43+'Siniestros Diciembre 2025'!F44)/1000 -> 0 | I21: =IFERROR(J21/G21,0%) -> 0 | J21: =IFERROR(H21-G21,0) -> 0 | K21: =IFERROR((G21/C21),0%) -> 0 | L21: =IFERROR(H21/D21,0%) -> 0 | M21: =IFERROR(N21/K21,0%) -> 0 | N21: =L21-K21 -> 0 | O21: =C21/$C$22 -> 0 | P21: =D21/$D$22 -> 0 | Q21: =IFERROR(R21/O21,0%) -> 0 | R21: =IFERROR(P21-O21,0) -> 0
A22: Total general | C22: =SUM(C10:C21) -> 276.9836 | D22: =SUM(D10:D21) -> 306.37378 | E22: =IFERROR(F22/C22,0%) -> 0.106108 | F22: =IFERROR(D22-C22,0) -> 29.390176 | G22: =SUM(G10:G21) -> 71.906719 | H22: =SUM(H10:H21) -> 65.386638 | I22: =IFERROR(J22/G22,0%) -> -0.09067416 | J22: =IFERROR(H22-G22,0) -> -6.5200814 | K22: =IFERROR((G22/C22),0%) -> 0.25960642 | L22: =IFERROR(H22/D22,0%) -> 0.21342113 | M22: =IFERROR(N22/K22,0%) -> -0.17790502 | N22: =L22-K22 -> -0.046185284
A24: ='1. Ramos Totales'!A$24 -> Inflación Interanual Diciembre 2025 | E24: ='1. Ramos Totales'!$D$24 -> 0.0498 | G24: ='1. Ramos Totales'!$F$24 -> Inflación Acumulada Diciembre 2025 | J24: ='1. Ramos Totales'!$J$24 -> 0.0498
A25: Crecimiento Real | E25: =E22-E24 -> 0.056308002

Sheet 6.2 Responsabilidad Civil
A1: Sector Asegurador Hondureño
A2: Situación de Primas y Siniestros por Ramo
A3: ='1. Ramos Totales'!A3 -> Al 31 de diciembre de 2025
A4: (Valores en millones de Lempiras y Porcentajes)
A6: 6.2 Responsabilidad Civil
A8: No. | B8: Compañía | C8: Primas | G8: Siniestros | K8: Siniestros/Primas | O8: Participación de mercado
C9: ='1. Ramos Totales'!$B$9 -> 45657 | D9: ='1. Ramos Totales'!$C$9 -> 46022 | E9: Relativa | F9: Absoluta | G9: ='1. Ramos Totales'!$B$9 -> 45657 | H9: ='1. Ramos Totales'!$C$9 -> 46022 | I9: Relativa | J9: Absoluta | K9: ='1. Ramos Totales'!$B$9 -> 45657 | L9: ='1. Ramos Totales'!$C$9 -> 46022 | M9: Relativa | N9: Absoluta | O9: ='1. Ramos Totales'!$B$9 -> 45657 | P9: ='1. Ramos Totales'!$C$9 -> 46022 | Q9: Relativa | R9: Absoluta
A10: 1 | B10: ='Primas Diciembre 2024'!R11 -> ASSA CIA. DE SEGUROS | C10: =('Primas Diciembre 2024'!R37)/1000 -> 125.36071 | D10: =('Primas Diciembre 2025'!N37)/1000 -> 133.07006 | E10: =IFERROR(F10/C10,0%) -> 0.061497404 | F10: =IFERROR(D10-C10,0) -> 7.709358 | G10: =('Siniestros Diciembre 2024'!AC37)/1000 -> 0.79127728 | H10: =('Siniestros Diciembre 2025'!Z37)/1000 -> 4.3837811 | I10: =IFERROR(J10/G10,0%) -> 4.5401327 | J10: =IFERROR(H10-G10,0) -> 3.5925038 | K10: =IFERROR((G10/C10),0%) -> 0.006312004 | L10: =IFERROR(H10/D10,0%) -> 0.032943406 | M10: =IFERROR(N10/K10,0%) -> 4.2191674 | N10: =L10-K10 -> 0.026631402 | O10: =C10/$C$22 -> 0.46282694 | P10: =D10/$D$22 -> 0.48919239 | Q10: =IFERROR(R10/O10,0%) -> 0.056966109 | R10: =IFERROR(P10-O10,0) -> 0.02636545
A11: 2 | B11: ='Primas Diciembre 2024'!J11 -> FICOHSA SEGUROS | C11: =('Primas Diciembre 2024'!J37)/1000 -> 65.681433 | D11: =('Primas Diciembre 2025'!F37)/1000 -> 58.531037 | E11: =IFERROR(F11/C11,0%) -> -0.1088648 | F11: =IFERROR(D11-C11,0) -> -7.1503959 | G11: =('Siniestros Diciembre 2024'!M37)/1000 -> 0.02407626 | H11: =('Siniestros Diciembre 2025'!J37)/1000 -> 2.3784827 | I11: =IFERROR(J11/G11,0%) -> 97.789542 | J11: =IFERROR(H11-G11,0) -> 2.3544064 | K11: =IFERROR((G11/C11),0%) -> 0.00036656113 | L11: =IFERROR(H11/D11,0%) -> 0.040636265 | M11: =IFERROR(N11/K11,0%) -> 109.85809 | N11: =L11-K11 -> 0.040269704 | O11: =C11/$C$22 -> 0.24249334 | P11: =D11/$D$22 -> 0.21517189 | Q11: =IFERROR(R11/O11,0%) -> -0.11266886 | R11: =IFERROR(P11-O11,0) -> -0.027321447
A12: 3 | B12: ='Primas Diciembre 2024'!L11 -> SEGUROS ATLÁNTIDA | C12: =('Primas Diciembre 2024'!L37)/1000 -> 21.999368 | D12: =('Primas Diciembre 2025'!H37)/1000 -> 22.310965 | E12: =IFERROR(F12/C12,0%) -> 0.014163911 | F12: =IFERROR(D12-C12,0) -> 0.3115971 | G12: =('Siniestros Diciembre 2024'!Q37)/1000 -> 2.8531051 | H12: =('Siniestros Diciembre 2025'!N37)/1000 -> 0.81291528 | I12: =IFERROR(J12/G12,0%) -> -0.71507699 | J12: =IFERROR(H12-G12,0) -> -2.0401898 | K12: =IFERROR((G12/C12),0%) -> 0.12969032 | L12: =IFERROR(H12/D12,0%) -> 0.036435684 | M12: =IFERROR(N12/K12,0%) -> -0.71905626 | N12: =L12-K12 -> -0.093254635 | O12: =C12/$C$22 -> 0.081220827 | P12: =D12/$D$22 -> 0.082019608 | Q12: =IFERROR(R12/O12,0%) -> 0.0098346724 | R12: =IFERROR(P12-O12,0) -> 0.00079878023
A13: 4 | B13: ='Primas Diciembre 2024'!O11 -> SEGUROS DEL PAÍS | C13: =('Primas Diciembre 2024'!O37)/1000 -> 13.85989 | D13: =('Primas Diciembre 2025'!K37)/1000 -> 15.556107 | E13: =IFERROR(F13/C13,0%) -> 0.12238314 | F13: =IFERROR(D13-C13,0) -> 1.696217 | G13: =('Siniestros Diciembre 2024'!W37)/1000 -> 1.555207 | H13: =('Siniestros Diciembre 2025'!T37)/1000 -> 3.2049384 | I13: =IFERROR(J13/G13,0%) -> 1.0607793 | J13: =IFERROR(H13-G13,0) -> 1.6497314 | K13: =IFERROR((G13/C13),0%) -> 0.11220919 | L13: =IFERROR(H13/D13,0%) -> 0.20602445 | M13: =IFERROR(N13/K13,0%) -> 0.83607466 | N13: =L13-K13 -> 0.093815259 | O13: =C13/$C$22 -> 0.051170185 | P13: =D13/$D$22 -> 0.057187387 | Q13: =IFERROR(R13/O13,0%) -> 0.11759194 | R13: =IFERROR(P13-O13,0) -> 0.0060172015
A14: 5 | B14: ='Primas Diciembre 2024'!I11 -> MAPFRE SEGUROS | C14: =('Primas Diciembre 2024'!I37)/1000 -> 17.38289 | D14: =('Primas Diciembre 2025'!E37)/1000 -> 14.047735 | E14: =IFERROR(F14/C14,0%) -> -0.19186425 | F14: =IFERROR(D14-C14,0) -> -3.3351552 | G14: =('Siniestros Diciembre 2024'!K37)/1000 -> 0 | H14: =('Siniestros Diciembre 2025'!H37)/1000 -> 0.90539029 | I14: =IFERROR(J14/G14,0%) -> 0 | J14: =IFERROR(H14-G14,0) -> 0.90539029 | K14: =IFERROR((G14/C14),0%) -> 0 | L14: =IFERROR(H14/D14,0%) -> 0.064450982 | M14: =IFERROR(N14/K14,0%) -> 0 | N14: =L14-K14 -> 0.064450982 | O14: =C14/$C$22 -> 0.064176965 | P14: =D14/$D$22 -> 0.051642305 | Q14: =IFERROR(R14/O14,0%) -> -0.195314 | R14: =IFERROR(P14-O14,0) -> -0.01253466
A15: 6 | B15: ='Primas Diciembre 2024'!P11 -> SEGUROS LAFISE | C15: =('Primas Diciembre 2024'!P37)/1000 -> 4.5379411 | D15: =('Primas Diciembre 2025'!L37)/1000 -> 8.7919309 | E15: =IFERROR(F15/C15,0%) -> 0.9374273 | F15: =IFERROR(D15-C15,0) -> 4.2539898 | G15: =('Siniestros Diciembre 2024'!Y37)/1000 -> 0.2165752 | H15: =('Siniestros Diciembre 2025'!P37)/1000 -> 0.05638941 | I15: =IFERROR(J15/G15,0%) -> -0.73963127 | J15: =IFERROR(H15-G15,0) -> -0.16018579 | K15: =IFERROR((G15/C15),0%) -> 0.047725433 | L15: =IFERROR(H15/D15,0%) -> 0.0064137686 | M15: =IFERROR(N15/K15,0%) -> -0.8656111 | N15: =L15-K15 -> -0.041311664 | O15: =C15/$C$22 -> 0.016753905 | P15: =D15/$D$22 -> 0.032320911 | Q15: =IFERROR(R15/O15,0%) -> 0.92915686 | R15: =IFERROR(P15-O15,0) -> 0.015567006
A16: 7 | B16: ='Primas Diciembre 2024'!M11 -> CREFISA | C16: =('Primas Diciembre 2024'!M37)/1000 -> 9.514283 | D16: =('Primas Diciembre 2025'!I37)/1000 -> 8.3647038 | E16: =IFERROR(F16/C16,0%) -> -0.12082667 | F16: =IFERROR(D16-C16,0) -> -1.1495792 | G16: =('Siniestros Diciembre 2024'!S37)/1000 -> 7.1552687 | H16: =('Siniestros Diciembre 2025'!V37)/1000 -> 0.02259877 | I16: =IFERROR(J16/G16,0%) -> -0.99684166 | J16: =IFERROR(H16-G16,0) -> -7.13267 | K16: =IFERROR((G16/C16),0%) -> 0.75205549 | L16: =IFERROR(H16/D16,0%) -> 0.002701682 | M16: =IFERROR(N16/K16,0%) -> -0.9964076 | N16: =L16-K16 -> -0.7493538 | O16: =C16/$C$22 -> 0.03512637 | P16: =D16/$D$22 -> 0.030750338 | Q16: =IFERROR(R16/O16,0%) -> -0.12457967 | R16: =IFERROR(P16-O16,0) -> -0.0043760315
A17: 8 | B17: ='Primas Diciembre 2024'!K11 -> SEGUROS CONTINENTAL | C17: =('Primas Diciembre 2024'!K37)/1000 -> 9.1465438 | D17: =('Primas Diciembre 2025'!G37)/1000 -> 7.0188283 | E17: =IFERROR(F17/C17,0%) -> -0.23262508 | F17: =IFERROR(D17-C17,0) -> -2.1277155 | G17: =('Siniestros Diciembre 2024'!O37)/1000 -> 0.70825118 | H17: =('Siniestros Diciembre 2025'!L37)/1000 -> 0.48680594 | I17: =IFERROR(J17/G17,0%) -> -0.31266484 | J17: =IFERROR(H17-G17,0) -> -0.22144524 | K17: =IFERROR((G17/C17),0%) -> 0.077433749 | L17: =IFERROR(H17/D17,0%) -> 0.069357152 | M17: =IFERROR(N17/K17,0%) -> -0.10430332 | N17: =L17-K17 -> -0.0080765975 | O17: =C17/$C$22 -> 0.03376869 | P17: =D17/$D$22 -> 0.025802628 | Q17: =IFERROR(R17/O17,0%) -> -0.23590083 | R17: =IFERROR(P17-O17,0) -> -0.0079660622
A18: 9 | B18: ='Primas Diciembre 2024'!G11 -> SEGUROS DAVIVIENDA | C18: =('Primas Diciembre 2024'!G37)/1000 -> 3.3756521 | D18: =('Primas Diciembre 2025'!C37)/1000 -> 4.328528 | E18: =IFERROR(F18/-C18,0%) -> -0.28227907 | F18: =IFERROR(D18-C18,0) -> 0.95287594 | G18: =('Siniestros Diciembre 2024'!G37)/1000 -> 0.07566581 | H18: =('Siniestros Diciembre 2025'!D37)/1000 -> 2.5485281 | I18: =IFERROR(J18/G18,0%) -> 32.681369 | J18: =IFERROR(H18-G18,0) -> 2.4728623 | K18: =IFERROR((G18/C18),0%) -> 0.022415169 | L18: =IFERROR(H18/D18,0%) -> 0.58877477 | M18: =IFERROR(N18/K18,0%) -> 25.266801 | N18: =L18-K18 -> 0.5663596 | O18: =C18/$C$22 -> 0.012462779 | P18: =D18/$D$22 -> 0.015912542 | Q18: =IFERROR(R18/O18,0%) -> 0.27680531 | R18: =IFERROR(P18-O18,0) -> 0.0034497633
A19: 10 | B19: ='Primas Diciembre 2024'!N11 -> SEGUROS EQUIDAD | C19: =('Primas Diciembre 2024'!N37)/1000 -> 0 | D19: =('Primas Diciembre 2025'!J37)/1000 -> 0 | E19: =IFERROR(F19/C19,0%) -> 0 | F19: =IFERROR(D19-C19,0) -> 0 | G19: =('Siniestros Diciembre 2024'!U37)/1000 -> 0 | H19: =('Siniestros Diciembre 2025'!R37)/1000 -> 0 | I19: =IFERROR(J19/G19,0%) -> 0 | J19: =IFERROR(H19-G19,0) -> 0 | K19: =IFERROR((G19/C19),0%) -> 0 | L19: =IFERROR(H19/D19,0%) -> 0 | M19: =IFERROR(N19/K19,0%) -> 0 | N19: =L19-K19 -> 0 | O19: =C19/$C$22 -> 0 | P19: =D19/$D$22 -> 0 | Q19: =IFERROR(R19/O19,0%) -> 0 | R19: =IFERROR(P19-O19,0) -> 0
A20: 11 | B20: ='Primas Diciembre 2024'!Q11 -> ASEGURADORA RURAL | C20: =('Primas Diciembre 2024'!Q37)/1000 -> 0 | D20: =('Primas Diciembre 2025'!M37)/1000 -> 0 | E20: =IFERROR(F20/C20,0%) -> 0 | F20: =IFERROR(D20-C20,0) -> 0 | G20: =('Siniestros Diciembre 2024'!AA37)/1000 -> 0 | H20: =('Siniestros Diciembre 2025'!X37)/1000 -> 0 | I20: =IFERROR(J20/G20,0%) -> 0 | J20: =IFERROR(H20-G20,0) -> 0 | K20: =IFERROR((G20/C20),0%) -> 0 | L20: =IFERROR(H20/D20,0%) -> 0 | M20: =IFERROR(N20/K20,0%) -> 0 | N20: =L20-K20 -> 0 | O20: =C20/$C$22 -> 0 | P20: =D20/$D$22 -> 0 | Q20: =IFERROR(R20/O20,0%) -> 0 | R20: =IFERROR(P20-O20,0) -> 0
A21: 12 | B21: ='Primas Diciembre 2024'!H11 -> PALIC | C21: =('Primas Diciembre 2024'!H37)/1000 -> 0 | D21: =('Primas Diciembre 2025'!D22)/1000 -> 0 | E21: =IFERROR(F21/C21,0%) -> 0 | F21: =IFERROR(D21-C21,0) -> 0 | G21: =('Siniestros Diciembre 2024'!I37)/1000 -> 0 | H21: =('Siniestros Diciembre 2025'!F22)/1000 -> 0 | I21: =IFERROR(J21/G21,0%) -> 0 | J21: =IFERROR(H21-G21,0) -> 0 | K21: =IFERROR((G21/C21),0%) -> 0 | L21: =IFERROR(H21/D21,0%) -> 0 | M21: =IFERROR(N21/K21,0%) -> 0 | N21: =L21-K21 -> 0 | O21: =C21/$C$22 -> 0 | P21: =D21/$D$22 -> 0 | Q21: =IFERROR(R21/O21,0%) -> 0 | R21: =IFERROR(P21-O21,0) -> 0
A22: Total general | C22: =SUM(C10:C21) -> 270.85871 | D22: =SUM(D10:D21) -> 272.0199 | E22: =IFERROR(F22/C22,0%) -> 0.0042870769 | F22: =IFERROR(D22-C22,0) -> 1.1611921 | G22: =SUM(G10:G21) -> 13.379427 | H22: =SUM(H10:H21) -> 14.79983 | I22: =IFERROR(J22/G22,0%) -> 0.10616325 | J22: =IFERROR(H22-G22,0) -> 1.4204034 | K22: =IFERROR((G22/C22),0%) -> 0.049396332 | L22: =IFERROR(H22/D22,0%) -> 0.054407159 | M22: =IFERROR(N22/K22,0%) -> 0.10144129 | N22: =L22-K22 -> 0.0050108274
A24: ='1. Ramos Totales'!A$24 -> Inflación Interanual Diciembre 2025 | E24: ='1. Ramos Totales'!$D$24 -> 0.0498 | G24: ='1. Ramos Totales'!$F$24 -> Inflación Acumulada Diciembre 2025 | J24: ='1. Ramos Totales'!$J$24 -> 0.0498
A25: Crecimiento Real | E25: =E22-E24 -> -0.045512923

Sheet 6.3 Equipo Electrónico
A1: Sector Asegurador Hondureño
A2: Situación de Primas y Siniestros por Ramo
A3: ='1. Ramos Totales'!A3 -> Al 31 de diciembre de 2025
A4: (Valores en millones de Lempiras y Porcentajes)
A6: 6.3 Equipo Electrónico
A8: No. | B8: Compañía | C8: Primas | G8: Siniestros | K8: Siniestros/Primas | O8: Participación de mercado
C9: ='1. Ramos Totales'!$B$9 -> 45657 | D9: ='1. Ramos Totales'!$C$9 -> 46022 | E9: Relativa | F9: Absoluta | G9: ='1. Ramos Totales'!$B$9 -> 45657 | H9: ='1. Ramos Totales'!$C$9 -> 46022 | I9: Relativa | J9: Absoluta | K9: ='1. Ramos Totales'!$B$9 -> 45657 | L9: ='1. Ramos Totales'!$C$9 -> 46022 | M9: Relativa | N9: Absoluta | O9: ='1. Ramos Totales'!$B$9 -> 45657 | P9: ='1. Ramos Totales'!$C$9 -> 46022 | Q9: Relativa | R9: Absoluta
A10: 1 | B10: ='Primas Diciembre 2024'!J11 -> FICOHSA SEGUROS | C10: =('Primas Diciembre 2024'!J31)/1000 -> 108.7576 | D10: =('Primas Diciembre 2025'!F31)/1000 -> 112.23202 | E10: =IFERROR(F10/C10,0%) -> 0.031946471 | F10: =IFERROR(D10-C10,0) -> 3.4744215 | G10: =('Siniestros Diciembre 2024'!M31)/1000 -> 40.506043 | H10: =('Siniestros Diciembre 2025'!J31)/1000 -> 16.73973 | I10: =IFERROR(J10/G10,0%) -> -0.586735 | J10: =IFERROR(H10-G10,0) -> -23.766313 | K10: =IFERROR((G10/C10),0%) -> 0.37244333 | L10: =IFERROR(H10/D10,0%) -> 0.14915289 | M10: =IFERROR(N10/K10,0%) -> -0.59952865 | N10: =L10-K10 -> -0.22329045 | O10: =C10/$C$22 -> 0.59170142 | P10: =D10/$D$22 -> 0.56569373 | Q10: =IFERROR(R10/O10,0%) -> -0.043954072 | R10: =IFERROR(P10-O10,0) -> -0.026007687
A11: 2 | B11: ='Primas Diciembre 2024'!L11 -> SEGUROS ATLÁNTIDA | C11: =('Primas Diciembre 2024'!L31)/1000 -> 45.850509 | D11: =('Primas Diciembre 2025'!H31)/1000 -> 44.810524 | E11: =IFERROR(F11/C11,0%) -> -0.022682085 | F11: =IFERROR(D11-C11,0) -> -1.0399852 | G11: =('Siniestros Diciembre 2024'!Q31)/1000 -> 1.8654657 | H11: =('Siniestros Diciembre 2025'!N31)/1000 -> 6.759295 | I11: =IFERROR(J11/G11,0%) -> 2.6233821 | J11: =IFERROR(H11-G11,0) -> 4.8938293 | K11: =IFERROR((G11/C11),0%) -> 0.040685823 | L11: =IFERROR(H11/D11,0%) -> 0.15084169 | M11: =IFERROR(N11/K11,0%) -> 2.7074753 | N11: =L11-K11 -> 0.11015586 | O11: =C11/$C$22 -> 0.2494521 | P11: =D11/$D$22 -> 0.22586275 | Q11: =IFERROR(R11/O11,0%) -> -0.094564652 | R11: =IFERROR(P11-O11,0) -> -0.023589351
A12: 3 | B12: ='Primas Diciembre 2024'!G11 -> SEGUROS DAVIVIENDA | C12: =('Primas Diciembre 2024'!G31)/1000 -> 7.8364082 | D12: =('Primas Diciembre 2025'!C31)/1000 -> 9.1946025 | E12: =IFERROR(F12/C12,0%) -> 0.17331848 | F12: =IFERROR(D12-C12,0) -> 1.3581943 | G12: =('Siniestros Diciembre 2024'!G31)/1000 -> 6.7864189 | H12: =('Siniestros Diciembre 2025'!D31)/1000 -> 13.371197 | I12: =IFERROR(J12/G12,0%) -> 0.97028761 | J12: =IFERROR(H12-G12,0) -> 6.5847782 | K12: =IFERROR((G12/C12),0%) -> 0.86601142 | L12: =IFERROR(H12/D12,0%) -> 1.4542442 | M12: =IFERROR(N12/K12,0%) -> 0.67924366 | N12: =L12-K12 -> 0.58823276 | O12: =C12/$C$22 -> 0.04263439 | P12: =D12/$D$22 -> 0.04634443 | Q12: =IFERROR(R12/O12,0%) -> 0.087019901 | R12: =IFERROR(P12-O12,0) -> 0.0037100403
A13: 4 | B13: ='Primas Diciembre 2024'!I11 -> MAPFRE SEGUROS | C13: =('Primas Diciembre 2024'!I31)/1000 -> 7.5000266 | D13: =('Primas Diciembre 2025'!E31)/1000 -> 8.0589422 | E13: =IFERROR(F13/C13,0%) -> 0.074521817 | F13: =IFERROR(D13-C13,0) -> 0.55891561 | G13: =('Siniestros Diciembre 2024'!Q31)/1000 -> 1.8654657 | H13: =('Siniestros Diciembre 2025'!N31)/1000 -> 6.759295 | I13: =IFERROR(J13/G13,0%) -> 2.6233821 | J13: =IFERROR(H13-G13,0) -> 4.8938293 | K13: =IFERROR((G13/C13),0%) -> 0.24872788 | L13: =IFERROR(H13/D13,0%) -> 0.83873228 | M13: =IFERROR(N13/K13,0%) -> 2.3720879 | N13: =L13-K13 -> 0.5900044 | O13: =C13/$C$22 -> 0.040804288 | P13: =D13/$D$22 -> 0.040620253 | Q13: =IFERROR(R13/O13,0%) -> -0.0045101799 | R13: =IFERROR(P13-O13,0) -> -0.00018403468
A14: 5 | B14: ='Primas Diciembre 2024'!P11 -> SEGUROS LAFISE | C14: =('Primas Diciembre 2024'!P31)/1000 -> 1.2273129 | D14: =('Primas Diciembre 2025'!L31)/1000 -> 6.9447852 | E14: =IFERROR(F14/C14,0%) -> 4.6585284 | F14: =IFERROR(D14-C14,0) -> 5.7174723 | G14: =('Siniestros Diciembre 2024'!Y31)/1000 -> 0.02642594 | H14: =('Siniestros Diciembre 2025'!V31)/1000 -> 0 | I14: =IFERROR(J14/G14,0%) -> -1 | J14: =IFERROR(H14-G14,0) -> -0.02642594 | K14: =IFERROR((G14/C14),0%) -> 0.021531542 | L14: =IFERROR(H14/D14,0%) -> 0 | M14: =IFERROR(N14/K14,0%) -> -1 | N14: =L14-K14 -> -0.021531542 | O14: =C14/$C$22 -> 0.0066772605 | P14: =D14/$D$22 -> 0.035004462 | Q14: =IFERROR(R14/O14,0%) -> 4.2423388 | R14: =IFERROR(P14-O14,0) -> 0.028327201
A15: 6 | B15: ='Primas Diciembre 2024'!O11 -> SEGUROS DEL PAÍS | C15: =('Primas Diciembre 2024'!O31)/1000 -> 4.927603 | D15: =('Primas Diciembre 2025'!K31)/1000 -> 6.3735864 | E15: =IFERROR(F15/C15,0%) -> 0.29344558 | F15: =IFERROR(D15-C15,0) -> 1.4459833 | G15: =('Siniestros Diciembre 2024'!W31)/1000 -> 0.33906642 | H15: =('Siniestros Diciembre 2025'!T31)/1000 -> 0.27045918 | I15: =IFERROR(J15/G15,0%) -> -0.20234159 | J15: =IFERROR(H15-G15,0) -> -0.06860724 | K15: =IFERROR((G15/C15),0%) -> 0.068809605 | L15: =IFERROR(H15/D15,0%) -> 0.042434379 | M15: =IFERROR(N15/K15,0%) -> -0.38330733 | N15: =L15-K15 -> -0.026375226 | O15: =C15/$C$22 -> 0.026808883 | P15: =D15/$D$22 -> 0.032125394 | Q15: =IFERROR(R15/O15,0%) -> 0.19831156 | R15: =IFERROR(P15-O15,0) -> 0.0053165112
A16: 7 | B16: ='Primas Diciembre 2024'!N11 -> SEGUROS EQUIDAD | C16: =('Primas Diciembre 2024'!N31)/1000 -> 3.8594013 | D16: =('Primas Diciembre 2025'!J31)/1000 -> 3.7677073 | E16: =IFERROR(F16/C16,0%) -> -0.023758618 | F16: =IFERROR(D16-C16,0) -> -0.09169404 | G16: =('Siniestros Diciembre 2024'!U31)/1000 -> 0.51881159 | H16: =('Siniestros Diciembre 2025'!R31)/1000 -> 1.1760853 | I16: =IFERROR(J16/G16,0%) -> 1.2668832 | J16: =IFERROR(H16-G16,0) -> 0.6572737 | K16: =IFERROR((G16/C16),0%) -> 0.134428 | L16: =IFERROR(H16/D16,0%) -> 0.3121488 | M16: =IFERROR(N16/K16,0%) -> 1.322052 | N16: =L16-K16 -> 0.1777208 | O16: =C16/$C$22 -> 0.020997275 | P16: =D16/$D$22 -> 0.018990734 | Q16: =IFERROR(R16/O16,0%) -> -0.095562004 | R16: =IFERROR(P16-O16,0) -> -0.0020065417
A17: 8 | B17: ='Primas Diciembre 2024'!M11 -> CREFISA | C17: =('Primas Diciembre 2024'!M31)/1000 -> 2.2873628 | D17: =('Primas Diciembre 2025'!I31)/1000 -> 2.7788034 | E17: =IFERROR(F17/C17,0%) -> 0.21485033 | F17: =IFERROR(D17-C17,0) -> 0.49144064 | G17: =('Siniestros Diciembre 2024'!S31)/1000 -> 0.52262094 | H17: =('Siniestros Diciembre 2025'!P31)/1000 -> 0.43473635 | I17: =IFERROR(J17/G17,0%) -> -0.16816125 | J17: =IFERROR(H17-G17,0) -> -0.08788459 | K17: =IFERROR((G17/C17),0%) -> 0.22848188 | L17: =IFERROR(H17/D17,0%) -> 0.15644732 | M17: =IFERROR(N17/K17,0%) -> -0.3152747 | N17: =L17-K17 -> -0.072034556 | O17: =C17/$C$22 -> 0.012444517 | P17: =D17/$D$22 -> 0.014006267 | Q17: =IFERROR(R17/O17,0%) -> 0.12549705 | R17: =IFERROR(P17-O17,0) -> 0.0015617502
A18: 9 | B18: ='Primas Diciembre 2024'!R11 -> ASSA CIA. DE SEGUROS | C18: =('Primas Diciembre 2024'!R31)/1000 -> 0.44867706 | D18: =('Primas Diciembre 2025'!N31)/1000 -> 2.4579618 | E18: =IFERROR(F18/C18,0%) -> 4.4782426 | F18: =IFERROR(D18-C18,0) -> 2.0092847 | G18: =('Siniestros Diciembre 2024'!AC31)/1000 -> 0.0540113 | H18: =('Siniestros Diciembre 2025'!Z31)/1000 -> 0.74775068 | I18: =IFERROR(J18/G18,0%) -> 12.844338 | J18: =IFERROR(H18-G18,0) -> 0.69373938 | K18: =IFERROR((G18/C18),0%) -> 0.12037901 | L18: =IFERROR(H18/D18,0%) -> 0.30421574 | M18: =IFERROR(N18/K18,0%) -> 1.5271494 | N18: =L18-K18 -> 0.18383674 | O18: =C18/$C$22 -> 0.0024410511 | P18: =D18/$D$22 -> 0.012389099 | Q18: =IFERROR(R18/O18,0%) -> 4.0753132 | R18: =IFERROR(P18-O18,0) -> 0.0099480477
A19: 10 | B19: ='Primas Diciembre 2024'!K11 -> SEGUROS CONTINENTAL | C19: =('Primas Diciembre 2024'!K31)/1000 -> 1.1099639 | D19: =('Primas Diciembre 2025'!G31)/1000 -> 1.7782099 | E19: =IFERROR(F19/C19,0%) -> 0.60204295 | F19: =IFERROR(D19-C19,0) -> 0.66824595 | G19: =('Siniestros Diciembre 2024'!O31)/1000 -> 0.15012257 | H19: =('Siniestros Diciembre 2025'!L31)/1000 -> 0.1782649 | I19: =IFERROR(J19/G19,0%) -> 0.18746235 | J19: =IFERROR(H19-G19,0) -> 0.02814233 | K19: =IFERROR((G19/C19),0%) -> 0.13524995 | L19: =IFERROR(H19/D19,0%) -> 0.10024964 | M19: =IFERROR(N19/K19,0%) -> -0.25878245 | N19: =L19-K19 -> -0.035000314 | O19: =C19/$C$22 -> 0.0060388169 | P19: =D19/$D$22 -> 0.0089628804 | Q19: =IFERROR(R19/O19,0%) -> 0.48421132 | R19: =IFERROR(P19-O19,0) -> 0.0029240635
A20: 11 | B20: ='Primas Diciembre 2024'!Q11 -> ASEGURADORA RURAL | C20: =('Primas Diciembre 2024'!Q31)/1000 -> 0 | D20: =('Primas Diciembre 2025'!M31)/1000 -> 0 | E20: =IFERROR(F20/C20,0%) -> 0 | F20: =IFERROR(D20-C20,0) -> 0 | G20: =('Siniestros Diciembre 2024'!AA31)/1000 -> 0 | H20: =('Siniestros Diciembre 2025'!X31)/1000 -> 0 | I20: =IFERROR(J20/G20,0%) -> 0 | J20: =IFERROR(H20-G20,0) -> 0 | K20: =IFERROR((G20/C20),0%) -> 0 | L20: =IFERROR(H20/D20,0%) -> 0 | M20: =IFERROR(N20/K20,0%) -> 0 | N20: =L20-K20 -> 0 | O20: =C20/$C$22 -> 0 | P20: =D20/$D$22 -> 0 | Q20: =IFERROR(R20/O20,0%) -> 0 | R20: =IFERROR(P20-O20,0) -> 0
A21: 12 | B21: ='Primas Diciembre 2024'!H11 -> PALIC | C21: =('Primas Diciembre 2024'!H31)/1000 -> 0 | D21: =('Primas Diciembre 2025'!D31)/1000 -> 0 | E21: =IFERROR(F21/C21,0%) -> 0 | F21: =IFERROR(D21-C21,0) -> 0 | G21: =('Siniestros Diciembre 2024'!I31)/1000 -> 0 | H21: =('Siniestros Diciembre 2025'!F31)/1000 -> 0 | I21: =IFERROR(J21/G21,0%) -> 0 | J21: =IFERROR(H21-G21,0) -> 0 | K21: =IFERROR((G21/C21),0%) -> 0 | L21: =IFERROR(H21/D21,0%) -> 0 | M21: =IFERROR(N21/K21,0%) -> 0 | N21: =L21-K21 -> 0 | O21: =C21/$C$22 -> 0 | P21: =D21/$D$22 -> 0 | Q21: =IFERROR(R21/O21,0%) -> 0 | R21: =IFERROR(P21-O21,0) -> 0
A22: Total general | C22: =SUM(C10:C21) -> 183.80486 | D22: =SUM(D10:D21) -> 198.39714 | E22: =IFERROR(F22/C22,0%) -> 0.07939006 | F22: =IFERROR(D22-C22,0) -> 14.592279 | G22: =SUM(G10:G21) -> 52.634452 | H22: =SUM(H10:H21) -> 46.436813 | I22: =IFERROR(J22/G22,0%) -> -0.11774871 | J22: =IFERROR(H22-G22,0) -> -6.1976386 | K22: =IFERROR((G22/C22),0%) -> 0.2863605 | L22: =IFERROR(H22/D22,0%) -> 0.23405989 | M22: =IFERROR(N22/K22,0%) -> -0.18263904 | N22: =L22-K22 -> -0.052300606
A24: ='1. Ramos Totales'!A$24 -> Inflación Interanual Diciembre 2025 | E24: ='1. Ramos Totales'!$D$24 -> 0.0498 | G24: ='1. Ramos Totales'!$F$24 -> Inflación Acumulada Diciembre 2025 | J24: ='1. Ramos Totales'!$J$24 -> 0.0498
A25: Crecimiento Real | E25: =E22-E24 -> 0.02959006

Sheet 7. Fianzas
A1: Sector Asegurador Hondureño
A2: Situación de Primas y Siniestros por Ramo
A3: ='1. Ramos Totales'!A3 -> Al 31 de diciembre de 2025
A4: (Valores en millones de Lempiras y Porcentajes)
A6: 7. Fianzas
A8: No. | B8: Compañía | C8: Primas | G8: Siniestros | K8: Siniestros/Primas | O8: Participación de mercado
C9: ='1. Ramos Totales'!$B$9 -> 45657 | D9: ='1. Ramos Totales'!$C$9 -> 46022 | E9: Relativa | F9: Absoluta | G9: ='1. Ramos Totales'!$B$9 -> 45657 | H9: ='1. Ramos Totales'!$C$9 -> 46022 | I9: Relativa | J9: Absoluta | K9: ='1. Ramos Totales'!$B$9 -> 45657 | L9: ='1. Ramos Totales'!$C$9 -> 46022 | M9: Relativa | N9: Absoluta | O9: ='1. Ramos Totales'!$B$9 -> 45657 | P9: ='1. Ramos Totales'!$C$9 -> 46022 | Q9: Relativa | R9: Absoluta
A10: 1 | B10: ='Primas Diciembre 2024'!M11 -> CREFISA | C10: =('Primas Diciembre 2024'!M17)/1000 -> 74.391829 | D10: =('Primas Diciembre 2025'!I17)/1000 -> 87.442929 | E10: =IFERROR(F10/C10,0%) -> 0.17543728 | F10: =IFERROR(D10-C10,0) -> 13.0511 | G10: =('Siniestros Diciembre 2024'!S17)/1000 -> 4.2993294 | H10: =('Siniestros Diciembre 2025'!P17)/1000 -> 7.0602002 | I10: =IFERROR(J10/G10,0%) -> 0.64216312 | J10: =IFERROR(H10-G10,0) -> 2.7608708 | K10: =IFERROR((G10/C10),0%) -> 0.057793033 | L10: =IFERROR(H10/D10,0%) -> 0.080740664 | M10: =IFERROR(N10/K10,0%) -> 0.39706571 | N10: =L10-K10 -> 0.022947632 | O10: =C10/$C$22 -> 0.31975532 | P10: =D10/$D$22 -> 0.29762993 | Q10: =IFERROR(R10/O10,0%) -> -0.069194757 | R10: =IFERROR(P10-O10,0) -> -0.022125391
A11: 2 | B11: ='Primas Diciembre 2024'!I11 -> MAPFRE SEGUROS | C11: =('Primas Diciembre 2024'!I17)/1000 -> 28.516232 | D11: =('Primas Diciembre 2025'!E17)/1000 -> 45.565838 | E11: =IFERROR(F11/C11,0%) -> 0.59789123 | F11: =IFERROR(D11-C11,0) -> 17.049605 | G11: =('Siniestros Diciembre 2024'!K17)/1000 -> 0.455 | H11: =('Siniestros Diciembre 2025'!H17)/1000 -> 0 | I11: =IFERROR(J11/G11,0%) -> -1 | J11: =IFERROR(H11-G11,0) -> -0.455 | K11: =IFERROR((G11/C11),0%) -> 0.015955825 | L11: =IFERROR(H11/D11,0%) -> 0 | M11: =IFERROR(N11/K11,0%) -> -1 | N11: =L11-K11 -> -0.015955825 | O11: =C11/$C$22 -> 0.12257014 | P11: =D11/$D$22 -> 0.15509266 | Q11: =IFERROR(R11/O11,0%) -> 0.26533806 | R11: =IFERROR(P11-O11,0) -> 0.032522523
A12: 3 | B12: ='Primas Diciembre 2024'!O11 -> SEGUROS DEL PAÍS | C12: =('Primas Diciembre 2024'!O17)/1000 -> 35.945378 | D12: =('Primas Diciembre 2025'!K17)/1000 -> 41.798728 | E12: =IFERROR(F12/C12,0%) -> 0.16284012 | F12: =IFERROR(D12-C12,0) -> 5.8533497 | G12: =('Siniestros Diciembre 2024'!W17)/1000 -> 0.10048825 | H12: =('Siniestros Diciembre 2025'!T17)/1000 -> 0.58861452 | I12: =IFERROR(J12/G12,0%) -> 4.8575457 | J12: =IFERROR(H12-G12,0) -> 0.48812627 | K12: =IFERROR((G12/C12),0%) -> 0.0027955819 | L12: =IFERROR(H12/D12,0%) -> 0.014082116 | M12: =IFERROR(N12/K12,0%) -> 4.0372752 | N12: =L12-K12 -> 0.011286534 | O12: =C12/$C$22 -> 0.15450253 | P12: =D12/$D$22 -> 0.14227054 | Q12: =IFERROR(R12/O12,0%) -> -0.079170198 | R12: =IFERROR(P12-O12,0) -> -0.012231996
A13: 4 | B13: ='Primas Diciembre 2024'!R11 -> ASSA CIA. DE SEGUROS | C13: =('Primas Diciembre 2024'!R17)/1000 -> 15.255032 | D13: =('Primas Diciembre 2025'!N17)/1000 -> 34.900661 | E13: =IFERROR(F13/C13,0%) -> 1.2878131 | F13: =IFERROR(D13-C13,0) -> 19.64563 | G13: =('Siniestros Diciembre 2024'!AC17)/1000 -> 0 | H13: =('Siniestros Diciembre 2025'!Z17)/1000 -> 0 | I13: =IFERROR(J13/G13,0%) -> 0 | J13: =IFERROR(H13-G13,0) -> 0 | K13: =IFERROR((G13/C13),0%) -> 0 | L13: =IFERROR(H13/D13,0%) -> 0 | M13: =IFERROR(N13/K13,0%) -> 0 | N13: =L13-K13 -> 0 | O13: =C13/$C$22 -> 0.065570071 | P13: =D13/$D$22 -> 0.11879155 | Q13: =IFERROR(R13/O13,0%) -> 0.81167336 | R13: =IFERROR(P13-O13,0) -> 0.05322148
A14: 5 | B14: ='Primas Diciembre 2024'!J11 -> FICOHSA SEGUROS | C14: =('Primas Diciembre 2024'!J17)/1000 -> 25.527873 | D14: =('Primas Diciembre 2025'!F17)/1000 -> 26.851718 | E14: =IFERROR(F14/C14,0%) -> 0.051858816 | F14: =IFERROR(D14-C14,0) -> 1.3238453 | G14: =('Siniestros Diciembre 2024'!M17)/1000 -> 2.479 | H14: =('Siniestros Diciembre 2025'!J17)/1000 -> 9.2579507 | I14: =IFERROR(J14/G14,0%) -> 2.7345505 | J14: =IFERROR(H14-G14,0) -> 6.7789507 | K14: =IFERROR((G14/C14),0%) -> 0.097109539 | L14: =IFERROR(H14/D14,0%) -> 0.34478057 | M14: =IFERROR(N14/K14,0%) -> 2.5504294 | N14: =L14-K14 -> 0.24767103 | O14: =C14/$C$22 -> 0.1097254 | P14: =D14/$D$22 -> 0.091395326 | Q14: =IFERROR(R14/O14,0%) -> -0.16705407 | R14: =IFERROR(P14-O14,0) -> -0.018330075
A15: 6 | B15: ='Primas Diciembre 2024'!P11 -> SEGUROS LAFISE | C15: =('Primas Diciembre 2024'!P17)/1000 -> 23.730107 | D15: =('Primas Diciembre 2025'!L17)/1000 -> 24.237568 | E15: =IFERROR(F15/C15,0%) -> 0.021384697 | F15: =IFERROR(D15-C15,0) -> 0.50746114 | G15: =('Siniestros Diciembre 2024'!Y17)/1000 -> 0.35470784 | H15: =('Siniestros Diciembre 2025'!V17)/1000 -> 0.5282 | I15: =IFERROR(J15/G15,0%) -> 0.48911284 | J15: =IFERROR(H15-G15,0) -> 0.17349216 | K15: =IFERROR((G15/C15),0%) -> 0.014947587 | L15: =IFERROR(H15/D15,0%) -> 0.021792615 | M15: =IFERROR(N15/K15,0%) -> 0.45793534 | N15: =L15-K15 -> 0.0068450283 | O15: =C15/$C$22 -> 0.10199814 | P15: =D15/$D$22 -> 0.08249753 | Q15: =IFERROR(R15/O15,0%) -> -0.19118592 | R15: =IFERROR(P15-O15,0) -> -0.019500607
A16: 7 | B16: ='Primas Diciembre 2024'!L11 -> SEGUROS ATLÁNTIDA | C16: =('Primas Diciembre 2024'!L17)/1000 -> 15.278565 | D16: =('Primas Diciembre 2025'!H17)/1000 -> 17.160439 | E16: =IFERROR(F16/C16,0%) -> 0.1231709 | F16: =IFERROR(D16-C16,0) -> 1.8818746 | G16: =('Siniestros Diciembre 2024'!Q17)/1000 -> 0 | H16: =('Siniestros Diciembre 2025'!N17)/1000 -> 0 | I16: =IFERROR(J16/G16,0%) -> 0 | J16: =IFERROR(H16-G16,0) -> 0 | K16: =IFERROR((G16/C16),0%) -> 0 | L16: =IFERROR(H16/D16,0%) -> 0 | M16: =IFERROR(N16/K16,0%) -> 0 | N16: =L16-K16 -> 0 | O16: =C16/$C$22 -> 0.065671223 | P16: =D16/$D$22 -> 0.058409072 | Q16: =IFERROR(R16/O16,0%) -> -0.11058346 | R16: =IFERROR(P16-O16,0) -> -0.0072621508
A17: 8 | B17: ='Primas Diciembre 2024'!K11 -> SEGUROS CONTINENTAL | C17: =('Primas Diciembre 2024'!K17)/1000 -> 13.494064 | D17: =('Primas Diciembre 2025'!G17)/1000 -> 15.138109 | E17: =IFERROR(F17/C17,0%) -> 0.12183467 | F17: =IFERROR(D17-C17,0) -> 1.6440448 | G17: =('Siniestros Diciembre 2024'!O17)/1000 -> 0 | H17: =('Siniestros Diciembre 2025'!L17)/1000 -> 24.357111 | I17: =IFERROR(J17/G17,0%) -> 0 | J17: =IFERROR(H17-G17,0) -> 24.357111 | K17: =IFERROR((G17/C17),0%) -> 0 | L17: =IFERROR(H17/D17,0%) -> 1.6089931 | M17: =IFERROR(N17/K17,0%) -> 0 | N17: =L17-K17 -> 1.6089931 | O17: =C17/$C$22 -> 0.058000975 | P17: =D17/$D$22 -> 0.051525654 | Q17: =IFERROR(R17/O17,0%) -> -0.11164159 | R17: =IFERROR(P17-O17,0) -> -0.0064753212
A18: 9 | B18: ='Primas Diciembre 2024'!N11 -> SEGUROS EQUIDAD | C18: =('Primas Diciembre 2024'!N17)/1000 -> 0.51327846 | D18: =('Primas Diciembre 2025'!J17)/1000 -> 0.70151236 | E18: =IFERROR(F18/C18,0%) -> 0.36672862 | F18: =IFERROR(D18-C18,0) -> 0.1882339 | G18: =('Siniestros Diciembre 2024'!U17)/1000 -> 2.8031787 | H18: =('Siniestros Diciembre 2025'!R17)/1000 -> 0 | I18: =IFERROR(J18/G18,0%) -> -1 | J18: =IFERROR(H18-G18,0) -> -2.8031787 | K18: =IFERROR((G18/C18),0%) -> 5.4613216 | L18: =IFERROR(H18/D18,0%) -> 0 | M18: =IFERROR(N18/K18,0%) -> -1 | N18: =L18-K18 -> -5.4613216 | O18: =C18/$C$22 -> 0.0022062036 | P18: =D18/$D$22 -> 0.0023877411 | Q18: =IFERROR(R18/O18,0%) -> 0.082285019 | R18: =IFERROR(P18-O18,0) -> 0.0001815375
A19: 10 | B19: ='Primas Diciembre 2024'!G11 -> SEGUROS DAVIVIENDA | C19: =('Primas Diciembre 2024'!G17)/1000 -> 0 | D19: =('Primas Diciembre 2025'!C17)/1000 -> 0 | E19: =IFERROR(F19/C19,0%) -> 0 | F19: =IFERROR(D19-C19,0) -> 0 | G19: =('Siniestros Diciembre 2024'!G17)/1000 -> 0 | H19: =('Siniestros Diciembre 2025'!D17)/1000 -> 0 | I19: =IFERROR(J19/G19,0%) -> 0 | J19: =IFERROR(H19-G19,0) -> 0 | K19: =IFERROR((G19/C19),0%) -> 0 | L19: =IFERROR(H19/D19,0%) -> 0 | M19: =IFERROR(N19/K19,0%) -> 0 | N19: =L19-K19 -> 0 | O19: =C19/$C$22 -> 0 | P19: =D19/$D$22 -> 0 | Q19: =IFERROR(R19/O19,0%) -> 0 | R19: =IFERROR(P19-O19,0) -> 0
A20: 11 | B20: ='Primas Diciembre 2024'!Q11 -> ASEGURADORA RURAL | C20: =('Primas Diciembre 2024'!Q17)/1000 -> 0 | D20: =('Primas Diciembre 2025'!M17)/1000 -> 0 | E20: =IFERROR(F20/C20,0%) -> 0 | F20: =IFERROR(D20-C20,0) -> 0 | G20: =('Siniestros Diciembre 2024'!AA17)/1000 -> 0 | H20: =('Siniestros Diciembre 2025'!X17)/1000 -> 0 | I20: =IFERROR(J20/G20,0%) -> 0 | J20: =IFERROR(H20-G20,0) -> 0 | K20: =IFERROR((G20/C20),0%) -> 0 | L20: =IFERROR(H20/D20,0%) -> 0 | M20: =IFERROR(N20/K20,0%) -> 0 | N20: =L20-K20 -> 0 | O20: =C20/$C$22 -> 0 | P20: =D20/$D$22 -> 0 | Q20: =IFERROR(R20/O20,0%) -> 0 | R20: =IFERROR(P20-O20,0) -> 0
A21: 12 | B21: ='Primas Diciembre 2024'!H11 -> PALIC | C21: =('Primas Diciembre 2024'!H17)/1000 -> 0 | D21: =('Primas Diciembre 2025'!D17)/1000 -> 0 | E21: =IFERROR(F21/C21,0%) -> 0 | F21: =IFERROR(D21-C21,0) -> 0 | G21: =('Siniestros Diciembre 2024'!I17)/1000 -> 0 | H21: =('Siniestros Diciembre 2025'!F17)/1000 -> 0 | I21: =IFERROR(J21/G21,0%) -> 0 | J21: =IFERROR(H21-G21,0) -> 0 | K21: =IFERROR((G21/C21),0%) -> 0 | L21: =IFERROR(H21/D21,0%) -> 0 | M21: =IFERROR(N21/K21,0%) -> 0 | N21: =L21-K21 -> 0 | O21: =C21/$C$22 -> 0 | P21: =D21/$D$22 -> 0 | Q21: =IFERROR(R21/O21,0%) -> 0 | R21: =IFERROR(P21-O21,0) -> 0
A22: Total general | C22: =SUM(C10:C21) -> 232.65236 | D22: =SUM(D10:D21) -> 293.7975 | E22: =IFERROR(F22/C22,0%) -> 0.26281764 | F22: =IFERROR(D22-C22,0) -> 61.145145 | G22: =SUM(G10:G21) -> 10.491704 | H22: =SUM(H10:H21) -> 41.792077 | I22: =IFERROR(J22/G22,0%) -> 2.9833449 | J22: =IFERROR(H22-G22,0) -> 31.300373 | K22: =IFERROR((G22/C22),0%) -> 0.045096058 | L22: =IFERROR(H22/D22,0%) -> 0.1422479 | M22: =IFERROR(N22/K22,0%) -> 2.1543311 | N22: =L22-K22 -> 0.097151839
A24: ='1. Ramos Totales'!A$24 -> Inflación Interanual Diciembre 2025 | E24: ='1. Ramos Totales'!$D$24 -> 0.0498 | G24: ='1. Ramos Totales'!$F$24 -> Inflación Acumulada Diciembre 2025 | J24: ='1. Ramos Totales'!$J$24 -> 0.0498
A25: Crecimiento Real | E25: =E22-E24 -> 0.21301764

Sheet 8. Primas y Siniestros Totales
A1: Sector Asegurador Hondureño
A2: Situación de Primas y Siniestros por Ramo
A3: ='1. Ramos Totales'!A3 -> Al 31 de diciembre de 2025
A4: (Valores en millones de Lempiras y Porcentajes)
A6: 8. Primas y Siniestros Totales
A8: No. | B8: Compañía | C8: Primas | G8: Siniestros | K8: Siniestros/Primas | O8: PARTICIPACIÓN DE MERCADO
C9: ='1. Ramos Totales'!$B$9 -> 45657 | D9: ='1. Ramos Totales'!$C$9 -> 46022 | E9: Relativa | F9: Absoluta | G9: ='1. Ramos Totales'!$B$9 -> 45657 | H9: ='1. Ramos Totales'!$C$9 -> 46022 | I9: Relativa | J9: Absoluta | K9: ='1. Ramos Totales'!$B$9 -> 45657 | L9: ='1. Ramos Totales'!$C$9 -> 46022 | M9: Relativa | N9: Absoluta | O9: ='1. Ramos Totales'!$B$9 -> 45657 | P9: ='1. Ramos Totales'!$C$9 -> 46022 | Q9: Relativa | R9: Absoluta
A10: =RANK(D10,$D$10:$D$21) -> 1 | B10: ='Primas Diciembre 2025'!F11 -> FICOHSA SEGUROS | C10: =('Primas Diciembre 2024'!J61)/1000 -> 4409.1933 | D10: =('Primas Diciembre 2025'!F61)/1000 -> 4850.8033 | E10: =IFERROR(F10/C10,0%) -> 0.10015664 | F10: =IFERROR(D10-C10,0) -> 441.60998 | G10: =('Siniestros Diciembre 2024'!M61)/1000 -> 1587.6109 | H10: =('Siniestros Diciembre 2025'!J61)/1000 -> 1723.9969 | I10: =IFERROR(J10/G10,0%) -> 0.085906478 | J10: =IFERROR(H10-G10,0) -> 136.38606 | K10: =IFERROR((G10/C10),0%) -> 0.36006833 | L10: =IFERROR(H10/D10,0%) -> 0.35540442 | M10: =IFERROR(N10/K10,0%) -> -0.012952846 | N10: =L10-K10 -> -0.0046639095 | O10: =C10/$C$22 -> 0.23908772 | P10: =D10/$D$22 -> 0.2403561 | Q10: =IFERROR(R10/O10,0%) -> 0.0053051046 | R10: =IFERROR(P10-O10,0) -> 0.0012683854
A11: =RANK(D11,$D$10:$D$21) -> 2 | B11: ='Primas Diciembre 2025'!E11 -> MAPFRE SEGUROS | C11: =('Primas Diciembre 2024'!I61)/1000 -> 3052.3444 | D11: =('Primas Diciembre 2025'!E61)/1000 -> 3127.4865 | E11: =IFERROR(F11/C11,0%) -> 0.024617821 | F11: =IFERROR(D11-C11,0) -> 75.142067 | G11: =('Siniestros Diciembre 2024'!K61)/1000 -> 1113.4385 | H11: =('Siniestros Diciembre 2025'!H61)/1000 -> 1057.1637 | I11: =IFERROR(J11/G11,0%) -> -0.050541472 | J11: =IFERROR(H11-G11,0) -> -56.274823 | K11: =IFERROR((G11/C11),0%) -> 0.36478143 | L11: =IFERROR(H11/D11,0%) -> 0.33802343 | M11: =IFERROR(N11/K11,0%) -> -0.07335349 | N11: =L11-K11 -> -0.026757991 | O11: =C11/$C$22 -> 0.16551283 | P11: =D11/$D$22 -> 0.15496618 | Q11: =IFERROR(R11/O11,0%) -> -0.063721028 | R11: =IFERROR(P11-O11,0) -> -0.010546648
A12: =RANK(D12,$D$10:$D$21) -> 3 | B12: ='Primas Diciembre 2025'!H11 -> SEGUROS ATLÁNTIDA | C12: =('Primas Diciembre 2024'!L61)/1000 -> 2484.1368 | D12: =('Primas Diciembre 2025'!H61)/1000 -> 2738.0758 | E12: =IFERROR(F12/C12,0%) -> 0.10222423 | F12: =IFERROR(D12-C12,0) -> 253.93897 | G12: =('Siniestros Diciembre 2024'!Q61)/1000 -> 1289.5165 | H12: =('Siniestros Diciembre 2025'!N61)/1000 -> 1105.7573 | I12: =IFERROR(J12/G12,0%) -> -0.14250241 | J12: =IFERROR(H12-G12,0) -> -183.75921 | K12: =IFERROR((G12/C12),0%) -> 0.51910043 | L12: =IFERROR(H12/D12,0%) -> 0.40384466 | M12: =IFERROR(N12/K12,0%) -> -0.22202981 | N12: =L12-K12 -> -0.11525577 | O12: =C12/$C$22 -> 0.13470188 | P12: =D12/$D$22 -> 0.13567098 | Q12: =IFERROR(R12/O12,0%) -> 0.0071944358 | R12: =IFERROR(P12-O12,0) -> 0.000969104
A13: =RANK(D13,$D$10:$D$21) -> 4 | B13: ='Primas Diciembre 2025'!I11 -> CREFISA | C13: =('Primas Diciembre 2024'!M61)/1000 -> 1347.9053 | D13: =('Primas Diciembre 2025'!I61)/1000 -> 1663.4791 | E13: =IFERROR(F13/C13,0%) -> 0.23412159 | F13: =IFERROR(D13-C13,0) -> 315.57374 | G13: =('Siniestros Diciembre 2024'!S61)/1000 -> 587.33678 | H13: =('Siniestros Diciembre 2025'!P61)/1000 -> 669.86951 | I13: =IFERROR(J13/G13,0%) -> 0.14052028 | J13: =IFERROR(H13-G13,0) -> 82.53273 | K13: =IFERROR((G13/C13),0%) -> 0.43574038 | L13: =IFERROR(H13/D13,0%) -> 0.40269188 | M13: =IFERROR(N13/K13,0%) -> -0.075844479 | N13: =L13-K13 -> -0.033048502 | O13: =C13/$C$22 -> 0.073089925 | P13: =D13/$D$22 -> 0.082424976 | Q13: =IFERROR(R13/O13,0%) -> 0.12772008 | R13: =IFERROR(P13-O13,0) -> 0.0093350514
A14: =RANK(D14,$D$10:$D$21) -> 5 | B14: ='Primas Diciembre 2025'!C11 -> SEGUROS DAVIVIENDA | C14: =('Primas Diciembre 2024'!G61)/1000 -> 1514.0799 | D14: =('Primas Diciembre 2025'!C61)/1000 -> 1624.8433 | E14: =IFERROR(F14/C14,0%) -> 0.073155563 | F14: =IFERROR(D14-C14,0) -> 110.76337 | G14: =('Siniestros Diciembre 2024'!G61)/1000 -> 775.85184 | H14: =('Siniestros Diciembre 2025'!D61)/1000 -> 663.21888 | I14: =IFERROR(J14/G14,0%) -> -0.14517328 | J14: =IFERROR(H14-G14,0) -> -112.63296 | K14: =IFERROR((G14/C14),0%) -> 0.51242463 | L14: =IFERROR(H14/D14,0%) -> 0.40817406 | M14: =IFERROR(N14/K14,0%) -> -0.20344567 | N14: =L14-K14 -> -0.10425057 | O14: =C14/$C$22 -> 0.082100713 | P14: =D14/$D$22 -> 0.080510583 | Q14: =IFERROR(R14/O14,0%) -> -0.019368034 | R14: =IFERROR(P14-O14,0) -> -0.0015901294
A15: =RANK(D15,$D$10:$D$21) -> 6 | B15: ='Primas Diciembre 2025'!D11 -> PALIC | C15: =('Primas Diciembre 2024'!H61)/1000 -> 1381.8012 | D15: =('Primas Diciembre 2025'!D61)/1000 -> 1450.0815 | E15: =IFERROR(F15/C15,0%) -> 0.049413977 | F15: =IFERROR(D15-C15,0) -> 68.280291 | G15: =('Siniestros Diciembre 2024'!I61)/1000 -> 538.8692 | H15: =('Siniestros Diciembre 2025'!F61)/1000 -> 583.633 | I15: =IFERROR(J15/G15,0%) -> 0.083069863 | J15: =IFERROR(H15-G15,0) -> 44.763791 | K15: =IFERROR((G15/C15),0%) -> 0.38997593 | L15: =IFERROR(H15/D15,0%) -> 0.4024829 | M15: =IFERROR(N15/K15,0%) -> 0.032071125 | N15: =L15-K15 -> 0.012506967 | O15: =C15/$C$22 -> 0.074927922 | P15: =D15/$D$22 -> 0.071851179 | Q15: =IFERROR(R15/O15,0%) -> -0.041062707 | R15: =IFERROR(P15-O15,0) -> -0.0030767433
A16: =RANK(D16,$D$10:$D$21) -> 7 | B16: ='Primas Diciembre 2025'!K11 -> SEGUROS DEL PAÍS | C16: =('Primas Diciembre 2024'!O61)/1000 -> 1250.5437 | D16: =('Primas Diciembre 2025'!K61)/1000 -> 1376.0558 | E16: =IFERROR(F16/C16,0%) -> 0.10036608 | F16: =IFERROR(D16-C16,0) -> 125.51217 | G16: =('Siniestros Diciembre 2024'!W61)/1000 -> 413.7391 | H16: =('Siniestros Diciembre 2025'!T61)/1000 -> 617.9251 | I16: =IFERROR(J16/G16,0%) -> 0.49351392 | J16: =IFERROR(H16-G16,0) -> 204.186 | K16: =IFERROR((G16/C16),0%) -> 0.33084738 | L16: =IFERROR(H16/D16,0%) -> 0.44905526 | M16: =IFERROR(N16/K16,0%) -> 0.35728822 | N16: =L16-K16 -> 0.11820787 | O16: =C16/$C$22 -> 0.067810506 | P16: =D16/$D$22 -> 0.068183226 | Q16: =IFERROR(R16/O16,0%) -> 0.0054964903 | R16: =IFERROR(P16-O16,0) -> 0.00037271979
A17: =RANK(D17,$D$10:$D$21) -> 8 | B17: ='Primas Diciembre 2025'!N11 -> ASSA CIA. DE SEGUROS | C17: =('Primas Diciembre 2024'!R61)/1000 -> 861.41587 | D17: =('Primas Diciembre 2025'!N61)/1000 -> 1080.2733 | E17: =IFERROR(F17/C17,0%) -> 0.25406708 | F17: =IFERROR(D17-C17,0) -> 218.85741 | G17: =('Siniestros Diciembre 2024'!AC61)/1000 -> 216.84121 | H17: =('Siniestros Diciembre 2025'!Z61)/1000 -> 1431.3444 | I17: =IFERROR(J17/G17,0%) -> 5.6008875 | J17: =IFERROR(H17-G17,0) -> 1214.5032 | K17: =IFERROR((G17/C17),0%) -> 0.25172651 | L17: =IFERROR(H17/D17,0%) -> 1.3249836 | M17: =IFERROR(N17/K17,0%) -> 4.2635841 | N17: =L17-K17 -> 1.0732571 | O17: =C17/$C$22 -> 0.046710121 | P17: =D17/$D$22 -> 0.053527274 | Q17: =IFERROR(R17/O17,0%) -> 0.14594594 | R17: =IFERROR(P17-O17,0) -> 0.0068171527
A18: =RANK(D18,$D$10:$D$21) -> 9 | B18: ='Primas Diciembre 2025'!G11 -> SEGUROS CONTINENTAL | C18: =('Primas Diciembre 2024'!K61)/1000 -> 542.79406 | D18: =('Primas Diciembre 2025'!G61)/1000 -> 614.12831 | E18: =IFERROR(F18/C18,0%) -> 0.13142048 | F18: =IFERROR(D18-C18,0) -> 71.334256 | G18: =('Siniestros Diciembre 2024'!O61)/1000 -> 181.63144 | H18: =('Siniestros Diciembre 2025'!L61)/1000 -> 237.85134 | I18: =IFERROR(J18/G18,0%) -> 0.3095274 | J18: =IFERROR(H18-G18,0) -> 56.219906 | K18: =IFERROR((G18/C18),0%) -> 0.33462311 | L18: =IFERROR(H18/D18,0%) -> 0.3872991 | M18: =IFERROR(N18/K18,0%) -> 0.15741885 | N18: =L18-K18 -> 0.052675987 | O18: =C18/$C$22 -> 0.029432911 | P18: =D18/$D$22 -> 0.030429906 | Q18: =IFERROR(R18/O18,0%) -> 0.033873493 | R18: =IFERROR(P18-O18,0) -> 0.00099699549
A19: =RANK(D19,$D$10:$D$21) -> 10 | B19: ='Primas Diciembre 2025'!J11 -> SEGUROS EQUIDAD | C19: =('Primas Diciembre 2024'!N61)/1000 -> 724.9267 | D19: =('Primas Diciembre 2025'!J61)/1000 -> 597.42208 | E19: =IFERROR(F19/C19,0%) -> -0.17588622 | F19: =IFERROR(D19-C19,0) -> -127.50462 | G19: =('Siniestros Diciembre 2024'!U61)/1000 -> 396.97868 | H19: =('Siniestros Diciembre 2025'!R61)/1000 -> 317.64589 | I19: =IFERROR(J19/G19,0%) -> -0.19984142 | J19: =IFERROR(H19-G19,0) -> -79.332783 | K19: =IFERROR((G19/C19),0%) -> 0.54761216 | L19: =IFERROR(H19/D19,0%) -> 0.53169426 | M19: =IFERROR(N19/K19,0%) -> -0.029067829 | N19: =L19-K19 -> -0.015917897 | O19: =C19/$C$22 -> 0.039309021 | P19: =D19/$D$22 -> 0.029602117 | Q19: =IFERROR(R19/O19,0%) -> -0.24693834 | R19: =IFERROR(P19-O19,0) -> -0.0097069043
A20: =RANK(D20,$D$10:$D$21) -> 11 | B20: ='Primas Diciembre 2025'!M11 -> ASEGURADORA RURAL | C20: =('Primas Diciembre 2024'!Q61)/1000 -> 468.87359 | D20: =('Primas Diciembre 2025'!M61)/1000 -> 544.688 | E20: =IFERROR(F20/C20,0%) -> 0.16169477 | F20: =IFERROR(D20-C20,0) -> 75.814406 | G20: =('Siniestros Diciembre 2024'!AA61)/1000 -> 340.81675 | H20: =('Siniestros Diciembre 2025'!X61)/1000 -> 254.81372 | I20: =IFERROR(J20/G20,0%) -> -0.25234391 | J20: =IFERROR(H20-G20,0) -> -86.003033 | K20: =IFERROR((G20/C20),0%) -> 0.72688408 | L20: =IFERROR(H20/D20,0%) -> 0.46781592 | M20: =IFERROR(N20/K20,0%) -> -0.35640918 | N20: =L20-K20 -> -0.25906816 | O20: =C20/$C$22 -> 0.025424587 | P20: =D20/$D$22 -> 0.026989156 | Q20: =IFERROR(R20/O20,0%) -> 0.061537639 | R20: =IFERROR(P20-O20,0) -> 0.001564569
A21: =RANK(D21,$D$10:$D$21) -> 12 | B21: ='Primas Diciembre 2025'!L11 -> SEGUROS LAFISE | C21: =('Primas Diciembre 2024'!P61)/1000 -> 403.72414 | D21: =('Primas Diciembre 2025'!L61)/1000 -> 514.39845 | E21: =IFERROR(F21/C21,0%) -> 0.2741335 | F21: =IFERROR(D21-C21,0) -> 110.67431 | G21: =('Siniestros Diciembre 2024'!Y61)/1000 -> 134.7788 | H21: =('Siniestros Diciembre 2025'!V61)/1000 -> 144.68329 | I21: =IFERROR(J21/G21,0%) -> 0.073486958 | J21: =IFERROR(H21-G21,0) -> 9.9044841 | K21: =IFERROR((G21/C21),0%) -> 0.33383885 | L21: =IFERROR(H21/D21,0%) -> 0.28126695 | M21: =IFERROR(N21/K21,0%) -> -0.15747686 | N21: =L21-K21 -> -0.052571893 | O21: =C21/$C$22 -> 0.021891869 | P21: =D21/$D$22 -> 0.025488316 | Q21: =IFERROR(R21/O21,0%) -> 0.16428231 | R21: =IFERROR(P21-O21,0) -> 0.0035964469
A22: Total general | C22: =SUM(C10:C21) -> 18441.739 | D22: =SUM(D10:D21) -> 20181.735 | E22: =IFERROR(F22/C22,0%) -> 0.094350991 | F22: =IFERROR(D22-C22,0) -> 1739.9963 | G22: =SUM(G10:G21) -> 7577.4097 | H22: =SUM(H10:H21) -> 8807.9031 | I22: =IFERROR(J22/G22,0%) -> 0.16238971 | J22: =IFERROR(H22-G22,0) -> 1230.4934 | K22: =IFERROR((G22/C22),0%) -> 0.41088369 | L22: =IFERROR(H22/D22,0%) -> 0.43642942 | M22: =IFERROR(N22/K22,0%) -> 0.062172668 | N22: =L22-K22 -> 0.025545735 | O22: =SUM(O10:O21) -> 1 | P22: =SUM(P10:P21) -> 1 | Q22: =SUM(Q10:Q21) -> 0.18026539 | R22: =SUM(R10:R21) -> 3.469447e-18
A24: ='1. Ramos Totales'!A$24 -> Inflación Interanual Diciembre 2025 | E24: ='1. Ramos Totales'!$D$24 -> 0.0498 | G24: ='1. Ramos Totales'!$F$24 -> Inflación Acumulada Diciembre 2025 | J24: ='1. Ramos Totales'!$J$24 -> 0.0498
A25: Crecimiento Real | E25: =E22-E24 -> 0.044550991

Sheet 9. Primas y Siniestros NO VIDA
A1: Sector Asegurador Hondureño
A2: Situación de Primas y Siniestros por Ramo
A3: ='1. Ramos Totales'!A3 -> Al 31 de diciembre de 2025
A4: (Valores en millones de Lempiras y Porcentajes)
A6: 10. Primas y Siniestros Segmentado por Seguros No Vida
A8: No. | B8: Compañía | C8: Primas | G8: Siniestros | K8: Siniestros/Primas
C9: ='1. Ramos Totales'!$B$9 -> 45657 | D9: ='1. Ramos Totales'!$C$9 -> 46022 | E9: Relativa | F9: Absoluta | G9: ='1. Ramos Totales'!$B$9 -> 45657 | H9: ='1. Ramos Totales'!$C$9 -> 46022 | I9: Relativa | J9: Absoluta | K9: ='1. Ramos Totales'!$B$9 -> 45657 | L9: ='1. Ramos Totales'!$C$9 -> 46022 | M9: Relativa | N9: Absoluta
A10: 1 | B10: ='Primas Diciembre 2024'!J11 -> FICOHSA SEGUROS | C10: =('Primas Diciembre 2024'!J61-'Primas Diciembre 2024'!J51)/1000 -> 3284.6966 | D10: =('Primas Diciembre 2025'!F61-'Primas Diciembre 2025'!F51)/1000 -> 3550.552 | E10: =IFERROR(F10/C10,0%) -> 0.080937565 | F10: =IFERROR(D10-C10,0) -> 265.85535 | G10: =('Siniestros Diciembre 2024'!M61-'Siniestros Diciembre 2024'!M51)/1000 -> 1254.6684 | H10: =('Siniestros Diciembre 2025'!J61-'Siniestros Diciembre 2025'!J51)/1000 -> 1412.077 | I10: =IFERROR(J10/G10,0%) -> 0.12545836 | J10: =IFERROR(H10-G10,0) -> 157.40864 | K10: =IFERROR((G10/C10),0%) -> 0.3819739 | L10: =IFERROR(H10/D10,0%) -> 0.39770634 | M10: =IFERROR(N10/K10,0%) -> 0.041187203 | N10: =L10-K10 -> 0.015732437
A11: 2 | B11: ='Primas Diciembre 2024'!L11 -> SEGUROS ATLÁNTIDA | C11: =('Primas Diciembre 2024'!L61-'Primas Diciembre 2024'!L51)/1000 -> 1710.0082 | D11: =('Primas Diciembre 2025'!H61-'Primas Diciembre 2025'!H51)/1000 -> 1967.5427 | E11: =IFERROR(F11/C11,0%) -> 0.1506042 | F11: =IFERROR(D11-C11,0) -> 257.53443 | G11: =('Siniestros Diciembre 2024'!Q61-'Siniestros Diciembre 2024'!Q51)/1000 -> 1048.5327 | H11: =('Siniestros Diciembre 2025'!N61-'Siniestros Diciembre 2025'!N51)/1000 -> 819.92051 | I11: =IFERROR(J11/G11,0%) -> -0.21803054 | J11: =IFERROR(H11-G11,0) -> -228.61214 | K11: =IFERROR((G11/C11),0%) -> 0.61317404 | L11: =IFERROR(H11/D11,0%) -> 0.41672312 | M11: =IFERROR(N11/K11,0%) -> -0.32038362 | N11: =L11-K11 -> -0.19645092
A12: 3 | B12: ='Primas Diciembre 2024'!I11 -> MAPFRE SEGUROS | C12: =('Primas Diciembre 2024'!I61-'Primas Diciembre 2024'!I51)/1000 -> 1620.3836 | D12: =('Primas Diciembre 2025'!E61-'Primas Diciembre 2025'!E51)/1000 -> 1661.8984 | E12: =IFERROR(F12/C12,0%) -> 0.025620363 | F12: =IFERROR(D12-C12,0) -> 41.514817 | G12: =('Siniestros Diciembre 2024'!K61-'Siniestros Diciembre 2024'!K51)/1000 -> 789.66015 | H12: =('Siniestros Diciembre 2025'!H61-'Siniestros Diciembre 2025'!H51)/1000 -> 718.74508 | I12: =IFERROR(J12/G12,0%) -> -0.089804545 | J12: =IFERROR(H12-G12,0) -> -70.91507 | K12: =IFERROR((G12/C12),0%) -> 0.48732914 | L12: =IFERROR(H12/D12,0%) -> 0.43248436 | M12: =IFERROR(N12/K12,0%) -> -0.11254155 | N12: =L12-K12 -> -0.054844778
A13: 4 | B13: ='Primas Diciembre 2024'!M11 -> CREFISA | C13: =('Primas Diciembre 2024'!M61-'Primas Diciembre 2024'!M51)/1000 -> 979.84179 | D13: =('Primas Diciembre 2025'!I61-'Primas Diciembre 2025'!I51)/1000 -> 1254.8785 | E13: =IFERROR(F13/C13,0%) -> 0.280695 | F13: =IFERROR(D13-C13,0) -> 275.03669 | G13: =('Siniestros Diciembre 2024'!S61-'Siniestros Diciembre 2024'!S51)/1000 -> 471.81514 | H13: =('Siniestros Diciembre 2025'!P61-'Siniestros Diciembre 2025'!P51)/1000 -> 523.14639 | I13: =IFERROR(J13/G13,0%) -> 0.10879526 | J13: =IFERROR(H13-G13,0) -> 51.331249 | K13: =IFERROR((G13/C13),0%) -> 0.48152176 | L13: =IFERROR(H13/D13,0%) -> 0.41689008 | M13: =IFERROR(N13/K13,0%) -> -0.1342238 | N13: =L13-K13 -> -0.064631678
A14: 5 | B14: ='Primas Diciembre 2024'!O11 -> SEGUROS DEL PAÍS | C14: =('Primas Diciembre 2024'!O61-'Primas Diciembre 2024'!O51)/1000 -> 956.7757 | D14: =('Primas Diciembre 2025'!K61-'Primas Diciembre 2025'!K51)/1000 -> 1054.2564 | E14: =IFERROR(F14/C14,0%) -> 0.10188462 | F14: =IFERROR(D14-C14,0) -> 97.480729 | G14: =('Siniestros Diciembre 2024'!W61-'Siniestros Diciembre 2024'!W51)/1000 -> 355.70743 | H14: =('Siniestros Diciembre 2025'!T61-'Siniestros Diciembre 2025'!T51)/1000 -> 538.87434 | I14: =IFERROR(J14/G14,0%) -> 0.51493697 | J14: =IFERROR(H14-G14,0) -> 183.16691 | K14: =IFERROR((G14/C14),0%) -> 0.37177724 | L14: =IFERROR(H14/D14,0%) -> 0.51114162 | M14: =IFERROR(N14/K14,0%) -> 0.3748599 | N14: =L14-K14 -> 0.13936438
A15: 6 | B15: ='Primas Diciembre 2024'!R11 -> ASSA CIA. DE SEGUROS | C15: =('Primas Diciembre 2024'!R61-'Primas Diciembre 2024'!R51)/1000 -> 842.81576 | D15: =('Primas Diciembre 2025'!N61-'Primas Diciembre 2025'!N51)/1000 -> 923.20027 | E15: =IFERROR(F15/C15,0%) -> 0.095376136 | F15: =IFERROR(D15-C15,0) -> 80.38451 | G15: =('Siniestros Diciembre 2024'!AC61-'Siniestros Diciembre 2024'!AC51)/1000 -> 208.9757 | H15: =('Siniestros Diciembre 2025'!Z61-'Siniestros Diciembre 2025'!Z51)/1000 -> 1406.1752 | I15: =IFERROR(J15/G15,0%) -> 5.7288935 | J15: =IFERROR(H15-G15,0) -> 1197.1995 | K15: =IFERROR((G15/C15),0%) -> 0.24794945 | L15: =IFERROR(H15/D15,0%) -> 1.523153 | M15: =IFERROR(N15/K15,0%) -> 5.1429981 | N15: =L15-K15 -> 1.2752035
A16: 7 | B16: ='Primas Diciembre 2024'!G11 -> SEGUROS DAVIVIENDA | C16: =('Primas Diciembre 2024'!G61-'Primas Diciembre 2024'!G51)/1000 -> 786.33744 | D16: =('Primas Diciembre 2025'!C61-'Primas Diciembre 2025'!C51)/1000 -> 884.9697 | E16: =IFERROR(F16/C16,0%) -> 0.12543249 | F16: =IFERROR(D16-C16,0) -> 98.632262 | G16: =('Siniestros Diciembre 2024'!G61-'Siniestros Diciembre 2024'!G51)/1000 -> 623.62323 | H16: =('Siniestros Diciembre 2025'!D61-'Siniestros Diciembre 2025'!D51)/1000 -> 422.57559 | I16: =IFERROR(J16/G16,0%) -> -0.32238638 | J16: =IFERROR(H16-G16,0) -> -201.04764 | K16: =IFERROR((G16/C16),0%) -> 0.7930733 | L16: =IFERROR(H16/D16,0%) -> 0.47750289 | M16: =IFERROR(N16/K16,0%) -> -0.39790825 | N16: =L16-K16 -> -0.31557041
A17: 8 | B17: ='Primas Diciembre 2024'!H11 -> PALIC | C17: =('Primas Diciembre 2024'!H61-'Primas Diciembre 2024'!H51)/1000 -> 673.59016 | D17: =('Primas Diciembre 2025'!D61-'Primas Diciembre 2025'!D51)/1000 -> 713.44266 | E17: =IFERROR(F17/C17,0%) -> 0.05916431 | F17: =IFERROR(D17-C17,0) -> 39.852497 | G17: =('Siniestros Diciembre 2024'!I61-'Siniestros Diciembre 2024'!I51)/1000 -> 429.7557 | H17: =('Siniestros Diciembre 2025'!F61-'Siniestros Diciembre 2025'!F51)/1000 -> 454.57002 | I17: =IFERROR(J17/G17,0%) -> 0.057740529 | J17: =IFERROR(H17-G17,0) -> 24.814322 | K17: =IFERROR((G17/C17),0%) -> 0.63800769 | L17: =IFERROR(H17/D17,0%) -> 0.63715005 | M17: =IFERROR(N17/K17,0%) -> -0.0013442491 | N17: =L17-K17 -> -0.00085764124
A18: 9 | B18: ='Primas Diciembre 2024'!K11 -> SEGUROS CONTINENTAL | C18: =('Primas Diciembre 2024'!K61-'Primas Diciembre 2024'!K51)/1000 -> 460.77354 | D18: =('Primas Diciembre 2025'!G61-'Primas Diciembre 2025'!G51)/1000 -> 524.47681 | E18: =IFERROR(F18/C18,0%) -> 0.1382529 | F18: =IFERROR(D18-C18,0) -> 63.703276 | G18: =('Siniestros Diciembre 2024'!O61-'Siniestros Diciembre 2024'!O51)/1000 -> 155.88096 | H18: =('Siniestros Diciembre 2025'!L61-'Siniestros Diciembre 2025'!L51)/1000 -> 209.64842 | I18: =IFERROR(J18/G18,0%) -> 0.34492638 | J18: =IFERROR(H18-G18,0) -> 53.767456 | K18: =IFERROR((G18/C18),0%) -> 0.33830276 | L18: =IFERROR(H18/D18,0%) -> 0.39972867 | M18: =IFERROR(N18/K18,0%) -> 0.1815708 | N18: =L18-K18 -> 0.061425903
A19: 10 | B19: ='Primas Diciembre 2024'!P11 -> SEGUROS LAFISE | C19: =('Primas Diciembre 2024'!P61-'Primas Diciembre 2024'!P51)/1000 -> 203.17263 | D19: =('Primas Diciembre 2025'!L61-'Primas Diciembre 2025'!L51)/1000 -> 321.55381 | E19: =IFERROR(F19/C19,0%) -> 0.58266303 | F19: =IFERROR(D19-C19,0) -> 118.38118 | G19: =('Siniestros Diciembre 2024'!Y61-'Siniestros Diciembre 2024'!Y51)/1000 -> 81.564546 | H19: =('Siniestros Diciembre 2025'!V61-'Siniestros Diciembre 2025'!V51)/1000 -> 76.098801 | I19: =IFERROR(J19/G19,0%) -> -0.067011289 | J19: =IFERROR(H19-G19,0) -> -5.4657454 | K19: =IFERROR((G19/C19),0%) -> 0.4014544 | L19: =IFERROR(H19/D19,0%) -> 0.23665961 | M19: =IFERROR(N19/K19,0%) -> -0.4104944 | N19: =L19-K19 -> -0.16479478
A20: 11 | B20: ='Primas Diciembre 2024'!Q11 -> ASEGURADORA RURAL | C20: =('Primas Diciembre 2024'!Q61-'Primas Diciembre 2024'!Q51)/1000 -> 183.24365 | D20: =('Primas Diciembre 2025'!M61-'Primas Diciembre 2025'!M51)/1000 -> 228.22787 | E20: =IFERROR(F20/C20,0%) -> 0.24548853 | F20: =IFERROR(D20-C20,0) -> 44.984215 | G20: =('Siniestros Diciembre 2024'!AA61-'Siniestros Diciembre 2024'!AA51)/1000 -> 206.89514 | H20: =('Siniestros Diciembre 2025'!X61-'Siniestros Diciembre 2025'!X51)/1000 -> 126.2512 | I20: =IFERROR(J20/G20,0%) -> -0.38978169 | J20: =IFERROR(H20-G20,0) -> -80.643938 | K20: =IFERROR((G20/C20),0%) -> 1.1290713 | L20: =IFERROR(H20/D20,0%) -> 0.55318049 | M20: =IFERROR(N20/K20,0%) -> -0.51005706 | N20: =L20-K20 -> -0.57589077
A21: 12 | B21: ='Primas Diciembre 2024'!N11 -> SEGUROS EQUIDAD | C21: =('Primas Diciembre 2024'!N61-'Primas Diciembre 2024'!N51)/1000 -> 232.31392 | D21: =('Primas Diciembre 2025'!J61-'Primas Diciembre 2025'!J51)/1000 -> 195.76742 | E21: =IFERROR(F21/C21,0%) -> -0.15731517 | F21: =IFERROR(D21-C21,0) -> -36.546505 | G21: =('Siniestros Diciembre 2024'!U61-'Siniestros Diciembre 2024'!U51)/1000 -> 152.99866 | H21: =('Siniestros Diciembre 2025'!R61-'Siniestros Diciembre 2025'!R51)/1000 -> 89.396428 | I21: =IFERROR(J21/G21,0%) -> -0.41570449 | J21: =IFERROR(H21-G21,0) -> -63.602228 | K21: =IFERROR((G21/C21),0%) -> 0.65858583 | L21: =IFERROR(H21/D21,0%) -> 0.4566461 | M21: =IFERROR(N21/K21,0%) -> -0.30662628 | N21: =L21-K21 -> -0.20193972
A22: Total general | C22: =SUM(C10:C21) -> 11933.953 | D22: =SUM(D10:D21) -> 13280.767 | E22: =IFERROR(F22/C22,0%) -> 0.1128556 | F22: =IFERROR(D22-C22,0) -> 1346.8134 | G22: =SUM(G10:G21) -> 5780.0777 | H22: =SUM(H10:H21) -> 6797.479 | I22: =IFERROR(J22/G22,0%) -> 0.17601863 | J22: =IFERROR(H22-G22,0) -> 1017.4013 | K22: =IFERROR((G22/C22),0%) -> 0.4843389 | L22: =IFERROR(H22/D22,0%) -> 0.51182882 | M22: =IFERROR(N22/K22,0%) -> 0.056757612 | N22: =L22-K22 -> 0.02748992
A23: Seguros No Vida incluye: Accidentes y Enfermedades, Incendio y Lineas Aliadas, Vehiculos Automotores, Otros seguros Generales y Fianzas.
A25: ='1. Ramos Totales'!A$24 -> Inflación Interanual Diciembre 2025 | E25: ='1. Ramos Totales'!$D$24 -> 0.0498 | G25: ='1. Ramos Totales'!$F$24 -> Inflación Acumulada Diciembre 2025 | J25: ='1. Ramos Totales'!$J$24 -> 0.0498
A26: Crecimiento Real | E26: =E22-E25 -> 0.063055601

Sheet 1. Utilidad
A1: Sector Asegurador Hondureño
A2: Principales Cuentas Contables e Indicadores Financieros
A3: ='1. Ramos Totales'!A3 -> Al 31 de diciembre de 2025
A4: (Valores en millones de Lempiras y Porcentajes)
A6: 1. Utilidad
A8: No. | B8: Compañía | C8: Período | E8: Variación | G8: Utilidad/Primas | I8: Variación | L8: PRIMAS | M8: PRIMAS
C9: ='1. Ramos Totales'!$B$9 -> 45657 | D9: ='1. Ramos Totales'!$C$9 -> 46022 | E9: Relativa | F9: Absoluta | G9: ='1. Ramos Totales'!$B$9 -> 45657 | H9: ='1. Ramos Totales'!$C$9 -> 46022 | I9: Relativa | J9: Absoluta | L9: 2023 | M9: 2024
A10: 1 | B10: ='ER diciembre 2024'!H9 -> FICOHSA SEGUROS | C10: =('ER diciembre 2024'!H37)/1000 -> 323.65135 | D10: =('ER Diciembre 2025'!F37)/1000 -> 353.5184 | E10: =IFERROR(F10/C10,0%) -> 0.092281567 | F10: =IFERROR(D10-C10,0) -> 29.867053 | G10: =C10/L10 -> 0.073403756 | H10: =IFERROR(D10/M10,0) -> 0.072878322 | I10: =IFERROR(J10/G10,0%) -> -0.007158136 | J10: =IFERROR(H10-G10,0) -> -0.00052543407 | K10: 1 | L10: =VLOOKUP(B10,'8. Primas y Siniestros Totales'!$B$10:$D$21,2,FALSE) -> 4409.1933 | M10: =VLOOKUP(B10,'8. Primas y Siniestros Totales'!$B$10:$D$21,3,FALSE) -> 4850.8033
A11: 2 | B11: ='ER diciembre 2024'!J9 -> SEGUROS ATLÁNTIDA | C11: =('ER diciembre 2024'!J37)/1000 -> 252.4232 | D11: =('ER Diciembre 2025'!H37)/1000 -> 348.66247 | E11: =IFERROR(F11/C11,0%) -> 0.38126161 | F11: =IFERROR(D11-C11,0) -> 96.239275 | G11: =C11/L11 -> 0.10161405 | H11: =IFERROR(D11/M11,0) -> 0.1273385 | I11: =IFERROR(J11/G11,0%) -> 0.25315845 | J11: =IFERROR(H11-G11,0) -> 0.025724455 | K11: 2 | L11: =VLOOKUP(B11,'8. Primas y Siniestros Totales'!$B$10:$D$21,2,FALSE) -> 2484.1368 | M11: =VLOOKUP(B11,'8. Primas y Siniestros Totales'!$B$10:$D$21,3,FALSE) -> 2738.0758
A12: 3 | B12: ='ER diciembre 2024'!E9 -> SEGUROS DAVIVIENDA | C12: =('ER diciembre 2024'!E37)/1000 -> 282.04282 | D12: =('ER Diciembre 2025'!C37)/1000 -> 328.36914 | E12: =IFERROR(F12/C12,0%) -> 0.1642528 | F12: =IFERROR(D12-C12,0) -> 46.326323 | G12: =C12/L12 -> 0.18628001 | H12: =IFERROR(D12/M12,0) -> 0.20209281 | I12: =IFERROR(J12/G12,0%) -> 0.084887262 | J12: =IFERROR(H12-G12,0) -> 0.0158128 | K12: 3 | L12: =VLOOKUP(B12,'8. Primas y Siniestros Totales'!$B$10:$D$21,2,FALSE) -> 1514.0799 | M12: =VLOOKUP(B12,'8. Primas y Siniestros Totales'!$B$10:$D$21,3,FALSE) -> 1624.8433
A13: 4 | B13: ='ER diciembre 2024'!F9 -> PALIC | C13: =('ER diciembre 2024'!F37)/1000 -> 92.32441 | D13: =('ER Diciembre 2025'!D37)/1000 -> 188.31341 | E13: =IFERROR(F13/C13,0%) -> 1.0396926 | F13: =IFERROR(D13-C13,0) -> 95.989002 | G13: =C13/L13 -> 0.06681454 | H13: =IFERROR(D13/M13,0) -> 0.12986402 | I13: =IFERROR(J13/G13,0%) -> 0.94364912 | J13: =IFERROR(H13-G13,0) -> 0.063049482 | K13: 4 | L13: =VLOOKUP(B13,'8. Primas y Siniestros Totales'!$B$10:$D$21,2,FALSE) -> 1381.8012 | M13: =VLOOKUP(B13,'8. Primas y Siniestros Totales'!$B$10:$D$21,3,FALSE) -> 1450.0815
A14: 5 | B14: ='ER diciembre 2024'!M9 -> SEGUROS DEL PAÍS | C14: =('ER diciembre 2024'!M37)/1000 -> 158.78215 | D14: =('ER Diciembre 2025'!K37)/1000 -> 182.86543 | E14: =IFERROR(F14/C14,0%) -> 0.15167497 | F14: =IFERROR(D14-C14,0) -> 24.083278 | G14: =C14/L14 -> 0.1269705 | H14: =IFERROR(D14/M14,0) -> 0.132891 | I14: =IFERROR(J14/G14,0%) -> 0.046628929 | J14: =IFERROR(H14-G14,0) -> 0.0059204983 | K14: 5 | L14: =VLOOKUP(B14,'8. Primas y Siniestros Totales'!$B$10:$D$21,2,FALSE) -> 1250.5437 | M14: =VLOOKUP(B14,'8. Primas y Siniestros Totales'!$B$10:$D$21,3,FALSE) -> 1376.0558
A15: 6 | B15: ='ER diciembre 2024'!G9 -> MAPFRE SEGUROS | C15: =('ER diciembre 2024'!G37)/1000 -> 127.71589 | D15: =('ER Diciembre 2025'!E37)/1000 -> 171.34795 | E15: =IFERROR(F15/C15,0%) -> 0.34163376 | F15: =IFERROR(D15-C15,0) -> 43.632059 | G15: =C15/L15 -> 0.0418419 | H15: =IFERROR(D15/M15,0) -> 0.05478775 | I15: =IFERROR(J15/G15,0%) -> 0.30939921 | J15: =IFERROR(H15-G15,0) -> 0.012945851 | K15: 6 | L15: =VLOOKUP(B15,'8. Primas y Siniestros Totales'!$B$10:$D$21,2,FALSE) -> 3052.3444 | M15: =VLOOKUP(B15,'8. Primas y Siniestros Totales'!$B$10:$D$21,3,FALSE) -> 3127.4865
A16: 7 | B16: ='ER diciembre 2024'!L9 -> SEGUROS EQUIDAD | C16: =('ER diciembre 2024'!L37)/1000 -> 144.86068 | D16: =('ER Diciembre 2025'!J37)/1000 -> 155.18359 | E16: =IFERROR(F16/C16,0%) -> 0.071260935 | F16: =IFERROR(D16-C16,0) -> 10.322908 | G16: =C16/L16 -> 0.19982804 | H16: =IFERROR(D16/M16,0) -> 0.25975536 | I16: =IFERROR(J16/G16,0%) -> 0.29989446 | J16: =IFERROR(H16-G16,0) -> 0.059927322 | K16: 7 | L16: =VLOOKUP(B16,'8. Primas y Siniestros Totales'!$B$10:$D$21,2,FALSE) -> 724.9267 | M16: =VLOOKUP(B16,'8. Primas y Siniestros Totales'!$B$10:$D$21,3,FALSE) -> 597.42208
A17: 8 | B17: ='ER diciembre 2024'!K9 -> CREFISA | C17: =('ER diciembre 2024'!K37)/1000 -> 105.71627 | D17: =('ER Diciembre 2025'!I37)/1000 -> 131.87066 | E17: =IFERROR(F17/C17,0%) -> 0.24740171 | F17: =IFERROR(D17-C17,0) -> 26.154387 | G17: =C17/L17 -> 0.078430045 | H17: =IFERROR(D17/M17,0) -> 0.079274014 | I17: =IFERROR(J17/G17,0%) -> 0.010760784 | J17: =IFERROR(H17-G17,0) -> 0.00084396875 | K17: 8 | L17: =VLOOKUP(B17,'8. Primas y Siniestros Totales'!$B$10:$D$21,2,FALSE) -> 1347.9053 | M17: =VLOOKUP(B17,'8. Primas y Siniestros Totales'!$B$10:$D$21,3,FALSE) -> 1663.4791
A18: 9 | B18: ='ER diciembre 2024'!O9 -> ASEGURADORA RURAL | C18: =('ER diciembre 2024'!O37)/1000 -> 66.625186 | D18: =('ER Diciembre 2025'!M37)/1000 -> 84.387647 | E18: =IFERROR(F18/C18,0%) -> 0.2666028 | F18: =IFERROR(D18-C18,0) -> 17.762461 | G18: =C18/L18 -> 0.14209627 | H18: =IFERROR(D18/M18,0) -> 0.15492841 | I18: =IFERROR(J18/G18,0%) -> 0.090306021 | J18: =IFERROR(H18-G18,0) -> 0.012832148 | K18: 9 | L18: =VLOOKUP(B18,'8. Primas y Siniestros Totales'!$B$10:$D$21,2,FALSE) -> 468.87359 | M18: =VLOOKUP(B18,'8. Primas y Siniestros Totales'!$B$10:$D$21,3,FALSE) -> 544.688
A19: 10 | B19: ='ER diciembre 2024'!N9 -> SEGUROS LAFISE | C19: =('ER diciembre 2024'!N37)/1000 -> 43.477012 | D19: =('ER Diciembre 2025'!L37)/1000 -> 78.200318 | E19: =IFERROR(F19/C19,0%) -> 0.798659 | F19: =IFERROR(D19-C19,0) -> 34.723307 | G19: =C19/L19 -> 0.1076899 | H19: =IFERROR(D19/M19,0) -> 0.15202285 | I19: =IFERROR(J19/G19,0%) -> 0.41167232 | J19: =IFERROR(H19-G19,0) -> 0.044332951 | K19: 10 | L19: =VLOOKUP(B19,'8. Primas y Siniestros Totales'!$B$10:$D$21,2,FALSE) -> 403.72414 | M19: =VLOOKUP(B19,'8. Primas y Siniestros Totales'!$B$10:$D$21,3,FALSE) -> 514.39845
A20: 11 | B20: ='ER diciembre 2024'!I9 -> SEGUROS CONTINENTAL | C20: =('ER diciembre 2024'!I37)/1000 -> 32.199303 | D20: =('ER Diciembre 2025'!G37)/1000 -> 40.170946 | E20: =IFERROR(F20/C20,0%) -> 0.2475719 | F20: =IFERROR(D20-C20,0) -> 7.9716428 | G20: =C20/L20 -> 0.0593214 | H20: =IFERROR(D20/M20,0) -> 0.065411324 | I20: =IFERROR(J20/G20,0%) -> 0.10265982 | J20: =IFERROR(H20-G20,0) -> 0.0060899241 | K20: 11 | L20: =VLOOKUP(B20,'8. Primas y Siniestros Totales'!$B$10:$D$21,2,FALSE) -> 542.79406 | M20: =VLOOKUP(B20,'8. Primas y Siniestros Totales'!$B$10:$D$21,3,FALSE) -> 614.12831
A21: 12 | B21: ='ER diciembre 2024'!P9 -> ASSA CIA. DE SEGUROS | C21: =('ER diciembre 2024'!P37)/1000 -> 19.116969 | D21: =('ER Diciembre 2025'!N37)/1000 -> 17.360169 | E21: =IFERROR(F21/C21,0%) -> -0.09189743 | F21: =IFERROR(D21-C21,0) -> -1.7568003 | G21: =C21/L21 -> 0.022192497 | H21: =IFERROR(D21/M21,0) -> 0.016070164 | I21: =IFERROR(J21/G21,0%) -> -0.27587401 | J21: =IFERROR(H21-G21,0) -> -0.006122333 | K21: 12 | L21: =VLOOKUP(B21,'8. Primas y Siniestros Totales'!$B$10:$D$21,2,FALSE) -> 861.41587 | M21: =VLOOKUP(B21,'8. Primas y Siniestros Totales'!$B$10:$D$21,3,FALSE) -> 1080.2733
A22: Total general | C22: =SUM(C10:C21) -> 1648.9352 | D22: =SUM(D10:D21) -> 2080.2501 | E22: =IFERROR(F22/C22,0%) -> 0.26157176 | F22: =IFERROR(D22-C22,0) -> 431.3149 | G22: =C22/L22 -> 0.089413219 | H22: =IFERROR(D22/M22,0) -> 0.10307588 | I22: =IFERROR(J22/G22,0%) -> 0.1528036 | J22: =H22-G22 -> 0.013662662 | L22: =SUM(L10:L21) -> 18441.739 | M22: =SUM(M10:M21) -> 20181.735

Sheet 2. Ingresos Financieros
A1: Sector Asegurador Hondureño
A2: Principales Cuentas Contables e Indicadores Financieros
A3: ='1. Ramos Totales'!A3 -> Al 31 de diciembre de 2025
A4: (Valores en millones de Lempiras y Porcentajes)
A6: 2. Ingresos Financieros
A8: No. | B8: Compañía | C8: Período | E8: Variación | G8: Ingresos Financieros/Primas | I8: Variación | M8: PRIMAS | N8: PRIMAS
C9: ='1. Ramos Totales'!$B$9 -> 45657 | D9: ='1. Ramos Totales'!$C$9 -> 46022 | E9: Relativa | F9: Absoluta | G9: ='1. Ramos Totales'!$B$9 -> 45657 | H9: ='1. Ramos Totales'!$C$9 -> 46022 | I9: Relativa | J9: Absoluta | M9: 2023 | N9: 2024
A10: 1 | B10: ='ER diciembre 2024'!H9 -> FICOHSA SEGUROS | C10: =('ER diciembre 2024'!H18)/1000 -> 172.8427 | D10: =('ER Diciembre 2025'!F18)/1000 -> 276.34684 | E10: =IFERROR(D10/C10-1,0) -> 0.5988343 | F10: =D10-C10 -> 103.50414 | G10: =C10/M10 -> 0.039200527 | H10: =IFERROR(D10/N10,0) -> 0.056969294 | I10: =IFERROR(H10/G10-1,0) -> 0.45327879 | J10: =H10-G10 -> 0.017768767 | M10: =VLOOKUP(B10,'8. Primas y Siniestros Totales'!$B$10:$D$21,2,FALSE) -> 4409.1933 | N10: =VLOOKUP(B10,'8. Primas y Siniestros Totales'!$B$10:$D$21,3,FALSE) -> 4850.8033
A11: 2 | B11: ='ER diciembre 2024'!J9 -> SEGUROS ATLÁNTIDA | C11: =('ER diciembre 2024'!J18)/1000 -> 182.02899 | D11: =('ER Diciembre 2025'!H18)/1000 -> 250.8305 | E11: =IFERROR(D11/C11-1,0) -> 0.37797012 | F11: =D11-C11 -> 68.801517 | G11: =C11/M11 -> 0.073276553 | H11: =IFERROR(D11/N11,0) -> 0.091608312 | I11: =IFERROR(H11/G11-1,0) -> 0.25017223 | J11: =H11-G11 -> 0.018331758 | M11: =VLOOKUP(B11,'8. Primas y Siniestros Totales'!$B$10:$D$21,2,FALSE) -> 2484.1368 | N11: =VLOOKUP(B11,'8. Primas y Siniestros Totales'!$B$10:$D$21,3,FALSE) -> 2738.0758
A12: 3 | B12: ='ER diciembre 2024'!E9 -> SEGUROS DAVIVIENDA | C12: =('ER diciembre 2024'!E18)/1000 -> 171.25786 | D12: =('ER Diciembre 2025'!C18)/1000 -> 230.2556 | E12: =IFERROR(D12/C12-1,0) -> 0.34449659 | F12: =D12-C12 -> 58.997746 | G12: =C12/M12 -> 0.11311018 | H12: =IFERROR(D12/N12,0) -> 0.14170942 | I12: =IFERROR(H12/G12-1,0) -> 0.25284407 | J12: =H12-G12 -> 0.028599239 | M12: =VLOOKUP(B12,'8. Primas y Siniestros Totales'!$B$10:$D$21,2,FALSE) -> 1514.0799 | N12: =VLOOKUP(B12,'8. Primas y Siniestros Totales'!$B$10:$D$21,3,FALSE) -> 1624.8433
A13: 4 | B13: ='ER diciembre 2024'!G9 -> MAPFRE SEGUROS | C13: =('ER diciembre 2024'!G18)/1000 -> 136.76149 | D13: =('ER Diciembre 2025'!E18)/1000 -> 198.09011 | E13: =IFERROR(D13/C13-1,0) -> 0.44843486 | F13: =D13-C13 -> 61.328619 | G13: =C13/M13 -> 0.044805393 | H13: =IFERROR(D13/N13,0) -> 0.063338439 | I13: =IFERROR(H13/G13-1,0) -> 0.41363426 | J13: =H13-G13 -> 0.018533046 | M13: =VLOOKUP(B13,'8. Primas y Siniestros Totales'!$B$10:$D$21,2,FALSE) -> 3052.3444 | N13: =VLOOKUP(B13,'8. Primas y Siniestros Totales'!$B$10:$D$21,3,FALSE) -> 3127.4865
A14: 5 | B14: ='ER diciembre 2024'!F9 -> PALIC | C14: =('ER diciembre 2024'!F18)/1000 -> 113.46662 | D14: =('ER Diciembre 2025'!D18)/1000 -> 183.84355 | E14: =IFERROR(D14/C14-1,0) -> 0.62024351 | F14: =D14-C14 -> 70.376934 | G14: =C14/M14 -> 0.082115012 | H14: =IFERROR(D14/N14,0) -> 0.12678153 | I14: =IFERROR(H14/G14-1,0) -> 0.54395076 | J14: =H14-G14 -> 0.044666523 | M14: =VLOOKUP(B14,'8. Primas y Siniestros Totales'!$B$10:$D$21,2,FALSE) -> 1381.8012 | N14: =VLOOKUP(B14,'8. Primas y Siniestros Totales'!$B$10:$D$21,3,FALSE) -> 1450.0815
A15: 6 | B15: ='ER diciembre 2024'!K9 -> CREFISA | C15: =('ER diciembre 2024'!K18)/1000 -> 78.2379 | D15: =('ER Diciembre 2025'!I18)/1000 -> 128.95438 | E15: =IFERROR(D15/C15-1,0) -> 0.6482342 | F15: =D15-C15 -> 50.716482 | G15: =C15/M15 -> 0.058044062 | H15: =IFERROR(D15/N15,0) -> 0.077520893 | I15: =IFERROR(H15/G15-1,0) -> 0.33555251 | J15: =H15-G15 -> 0.019476831 | M15: =VLOOKUP(B15,'8. Primas y Siniestros Totales'!$B$10:$D$21,2,FALSE) -> 1347.9053 | N15: =VLOOKUP(B15,'8. Primas y Siniestros Totales'!$B$10:$D$21,3,FALSE) -> 1663.4791
A16: 7 | B16: ='ER diciembre 2024'!M9 -> SEGUROS DEL PAÍS | C16: =('ER diciembre 2024'!M18)/1000 -> 83.283013 | D16: =('ER Diciembre 2025'!K18)/1000 -> 119.84077 | E16: =IFERROR(D16/C16-1,0) -> 0.43895816 | F16: =D16-C16 -> 36.557758 | G16: =C16/M16 -> 0.066597445 | H16: =IFERROR(D16/N16,0) -> 0.087090051 | I16: =IFERROR(H16/G16-1,0) -> 0.30770858 | J16: =H16-G16 -> 0.020492605 | M16: =VLOOKUP(B16,'8. Primas y Siniestros Totales'!$B$10:$D$21,2,FALSE) -> 1250.5437 | N16: =VLOOKUP(B16,'8. Primas y Siniestros Totales'!$B$10:$D$21,3,FALSE) -> 1376.0558
A17: 8 | B17: ='ER diciembre 2024'!L9 -> SEGUROS EQUIDAD | C17: =('ER diciembre 2024'!L18)/1000 -> 74.709397 | D17: =('ER Diciembre 2025'!J18)/1000 -> 116.14659 | E17: =IFERROR(D17/C17-1,0) -> 0.55464495 | F17: =D17-C17 -> 41.43719 | G17: =C17/M17 -> 0.10305786 | H17: =IFERROR(D17/N17,0) -> 0.19441295 | I17: =IFERROR(H17/G17-1,0) -> 0.88644456 | J17: =H17-G17 -> 0.091355082 | M17: =VLOOKUP(B17,'8. Primas y Siniestros Totales'!$B$10:$D$21,2,FALSE) -> 724.9267 | N17: =VLOOKUP(B17,'8. Primas y Siniestros Totales'!$B$10:$D$21,3,FALSE) -> 597.42208
A18: 9 | B18: ='ER diciembre 2024'!I9 -> SEGUROS CONTINENTAL | C18: =('ER diciembre 2024'!I18)/1000 -> 52.605861 | D18: =('ER Diciembre 2025'!G18)/1000 -> 114.46578 | E18: =IFERROR(D18/C18-1,0) -> 1.1759131 | F18: =D18-C18 -> 61.859921 | G18: =C18/M18 -> 0.096916796 | H18: =IFERROR(D18/N18,0) -> 0.1863874 | I18: =IFERROR(H18/G18-1,0) -> 0.92316927 | J18: =H18-G18 -> 0.089470607 | M18: =VLOOKUP(B18,'8. Primas y Siniestros Totales'!$B$10:$D$21,2,FALSE) -> 542.79406 | N18: =VLOOKUP(B18,'8. Primas y Siniestros Totales'!$B$10:$D$21,3,FALSE) -> 614.12831
A19: 10 | B19: ='ER diciembre 2024'!O9 -> ASEGURADORA RURAL | C19: =('ER diciembre 2024'!O18)/1000 -> 49.193615 | D19: =('ER Diciembre 2025'!M18)/1000 -> 83.93148 | E19: =IFERROR(D19/C19-1,0) -> 0.7061458 | F19: =D19-C19 -> 34.737865 | G19: =C19/M19 -> 0.10491872 | H19: =IFERROR(D19/N19,0) -> 0.15409093 | I19: =IFERROR(H19/G19-1,0) -> 0.46866961 | J19: =H19-G19 -> 0.049172214 | M19: =VLOOKUP(B19,'8. Primas y Siniestros Totales'!$B$10:$D$21,2,FALSE) -> 468.87359 | N19: =VLOOKUP(B19,'8. Primas y Siniestros Totales'!$B$10:$D$21,3,FALSE) -> 544.688
A20: 11 | B20: ='ER diciembre 2024'!N9 -> SEGUROS LAFISE | C20: =('ER diciembre 2024'!N18)/1000 -> 42.891941 | D20: =('ER Diciembre 2025'!L18)/1000 -> 69.972686 | E20: =IFERROR(D20/C20-1,0) -> 0.6313714 | F20: =D20-C20 -> 27.080745 | G20: =C20/M20 -> 0.10624071 | H20: =IFERROR(D20/N20,0) -> 0.13602818 | I20: =IFERROR(H20/G20-1,0) -> 0.28037714 | J20: =H20-G20 -> 0.029787467 | M20: =VLOOKUP(B20,'8. Primas y Siniestros Totales'!$B$10:$D$21,2,FALSE) -> 403.72414 | N20: =VLOOKUP(B20,'8. Primas y Siniestros Totales'!$B$10:$D$21,3,FALSE) -> 514.39845
A21: 12 | B21: ='ER diciembre 2024'!P9 -> ASSA CIA. DE SEGUROS | C21: =('ER diciembre 2024'!P18)/1000 -> 20.476815 | D21: =('ER Diciembre 2025'!N18)/1000 -> 29.74884 | E21: =IFERROR(D21/C21-1,0) -> 0.45280604 | F21: =D21-C21 -> 9.2720255 | G21: =C21/M21 -> 0.023771114 | H21: =IFERROR(D21/N21,0) -> 0.027538254 | I21: =IFERROR(H21/G21-1,0) -> 0.15847555 | J21: =H21-G21 -> 0.0037671403 | M21: =VLOOKUP(B21,'8. Primas y Siniestros Totales'!$B$10:$D$21,2,FALSE) -> 861.41587 | N21: =VLOOKUP(B21,'8. Primas y Siniestros Totales'!$B$10:$D$21,3,FALSE) -> 1080.2733
A22: Total general | C22: =SUM(C10:C21) -> 1177.7562 | D22: =SUM(D10:D21) -> 1802.4271 | E22: =IFERROR(D22/C22-1,0) -> 0.53039071 | F22: =D22-C22 -> 624.67094 | G22: =IFERROR(C22/M22,0) -> 0.063863619 | H22: =IFERROR(D22/N22,0) -> 0.089309819 | I22: =IFERROR(H22/G22-1,0) -> 0.39844595 | J22: =H22-G22 -> 0.0254462 | M22: =SUM(M10:M21) -> 18441.739 | N22: =SUM(N10:N21) -> 20181.735

Sheet 3. Reserva Técnica y Matemática
A1: Sector Asegurador Hondureño
A2: Principales Cuentas Contables e Indicadores Financieros
A3: ='1. Ramos Totales'!A3 -> Al 31 de diciembre de 2025
A4: (Valores en millones de Lempiras y Porcentajes)
A6: 3. Reserva Técnica y Matemática
A8: No. | B8: Compañía | C8: Período | E8: Variación | G8: Reservas Matemáticas/Primas | I8: Variación | M8: PRIMAS | N8: PRIMAS
C9: ='1. Ramos Totales'!$B$9 -> 45657 | D9: ='1. Ramos Totales'!$C$9 -> 46022 | E9: Relativa | F9: Absoluta | G9: ='1. Ramos Totales'!$B$9 -> 45657 | H9: ='1. Ramos Totales'!$C$9 -> 46022 | I9: Relativa | J9: Absoluta | M9: 2023 | N9: 2024
A10: 1 | B10: ='Balance diciembre 2024'!G9 -> PALIC | C10: =('Balance diciembre 2024'!G35)/1000 -> 2615.3119 | D10: =('Balance Diciembre 2025'!F35)/1000 -> 2816.0463 | E10: =IFERROR(D10/C10-1,0) -> 0.076753532 | F10: =D10-C10 -> 200.73442 | G10: =C10/M10 -> 1.8926832 | H10: =D10/N10 -> 1.9419918 | I10: =IFERROR(H10/G10-1,0) -> 0.026052212 | J10: =H10-G10 -> 0.049308584 | L10: 1 | M10: =VLOOKUP(B10,'8. Primas y Siniestros Totales'!$B$10:$D$21,2,FALSE) -> 1381.8012 | N10: =VLOOKUP(B10,'8. Primas y Siniestros Totales'!$B$10:$D$21,3,FALSE) -> 1450.0815
A11: 2 | B11: ='Balance diciembre 2024'!F9 -> SEGUROS DAVIVIENDA | C11: =('Balance diciembre 2024'!F35)/1000 -> 1045.3239 | D11: =('Balance Diciembre 2025'!E35)/1000 -> 1068.2031 | E11: =IFERROR(D11/C11-1,0) -> 0.021887103 | F11: =D11-C11 -> 22.879112 | G11: =C11/M11 -> 0.6904021 | H11: =D11/N11 -> 0.65741913 | I11: =IFERROR(H11/G11-1,0) -> -0.047773559 | J11: =H11-G11 -> -0.032982965 | L11: 2 | M11: =VLOOKUP(B11,'8. Primas y Siniestros Totales'!$B$10:$D$21,2,FALSE) -> 1514.0799 | N11: =VLOOKUP(B11,'8. Primas y Siniestros Totales'!$B$10:$D$21,3,FALSE) -> 1624.8433
A12: 3 | B12: ='Balance diciembre 2024'!K9 -> SEGUROS ATLÁNTIDA | C12: =('Balance diciembre 2024'!K35)/1000 -> 977.02513 | D12: =('Balance Diciembre 2025'!J35)/1000 -> 956.41612 | E12: =IFERROR(D12/C12-1,0) -> -0.021093638 | F12: =D12-C12 -> -20.609015 | G12: =C12/M12 -> 0.39330568 | H12: =D12/N12 -> 0.34930228 | I12: =IFERROR(H12/G12-1,0) -> -0.11188093 | J12: =H12-G12 -> -0.044003404 | L12: 3 | M12: =VLOOKUP(B12,'8. Primas y Siniestros Totales'!$B$10:$D$21,2,FALSE) -> 2484.1368 | N12: =VLOOKUP(B12,'8. Primas y Siniestros Totales'!$B$10:$D$21,3,FALSE) -> 2738.0758
A13: 4 | B13: ='Balance diciembre 2024'!I9 -> FICOHSA SEGUROS | C13: =('Balance diciembre 2024'!I35)/1000 -> 640.66366 | D13: =('Balance Diciembre 2025'!H35)/1000 -> 751.81917 | E13: =IFERROR(D13/C13-1,0) -> 0.17350057 | F13: =D13-C13 -> 111.15551 | G13: =C13/M13 -> 0.14530179 | H13: =D13/N13 -> 0.15498859 | I13: =IFERROR(H13/G13-1,0) -> 0.066666808 | J13: =H13-G13 -> 0.0096868063 | L13: 4 | M13: =VLOOKUP(B13,'8. Primas y Siniestros Totales'!$B$10:$D$21,2,FALSE) -> 4409.1933 | N13: =VLOOKUP(B13,'8. Primas y Siniestros Totales'!$B$10:$D$21,3,FALSE) -> 4850.8033
A14: 5 | B14: ='Balance diciembre 2024'!H9 -> MAPFRE SEGUROS | C14: =('Balance diciembre 2024'!H35)/1000 -> 604.90227 | D14: =('Balance Diciembre 2025'!G35)/1000 -> 606.83604 | E14: =IFERROR(D14/C14-1,0) -> 0.0031968196 | F14: =D14-C14 -> 1.9337634 | G14: =C14/M14 -> 0.19817629 | H14: =D14/N14 -> 0.19403315 | I14: =IFERROR(H14/G14-1,0) -> -0.020906333 | J14: =H14-G14 -> -0.0041431393 | L14: 5 | M14: =VLOOKUP(B14,'8. Primas y Siniestros Totales'!$B$10:$D$21,2,FALSE) -> 3052.3444 | N14: =VLOOKUP(B14,'8. Primas y Siniestros Totales'!$B$10:$D$21,3,FALSE) -> 3127.4865
A15: 6 | B15: ='Balance diciembre 2024'!L9 -> CREFISA | C15: =('Balance diciembre 2024'!L35)/1000 -> 363.2803 | D15: =('Balance Diciembre 2025'!K35)/1000 -> 408.7522 | E15: =IFERROR(D15/C15-1,0) -> 0.12517027 | F15: =D15-C15 -> 45.471894 | G15: =C15/M15 -> 0.26951471 | H15: =D15/N15 -> 0.24572128 | I15: =IFERROR(H15/G15-1,0) -> -0.088282485 | J15: =H15-G15 -> -0.023793428 | L15: 6 | M15: =VLOOKUP(B15,'8. Primas y Siniestros Totales'!$B$10:$D$21,2,FALSE) -> 1347.9053 | N15: =VLOOKUP(B15,'8. Primas y Siniestros Totales'!$B$10:$D$21,3,FALSE) -> 1663.4791
A16: 7 | B16: ='Balance diciembre 2024'!J9 -> SEGUROS CONTINENTAL | C16: =('Balance diciembre 2024'!J35)/1000 -> 356.85463 | D16: =('Balance Diciembre 2025'!I35)/1000 -> 395.34806 | E16: =IFERROR(D16/C16-1,0) -> 0.10786865 | F16: =D16-C16 -> 38.493425 | G16: =C16/M16 -> 0.65744019 | H16: =D16/N16 -> 0.64375481 | I16: =IFERROR(H16/G16-1,0) -> -0.020816166 | J16: =H16-G16 -> -0.013685384 | L16: 7 | M16: =VLOOKUP(B16,'8. Primas y Siniestros Totales'!$B$10:$D$21,2,FALSE) -> 542.79406 | N16: =VLOOKUP(B16,'8. Primas y Siniestros Totales'!$B$10:$D$21,3,FALSE) -> 614.12831
A17: 8 | B17: ='Balance diciembre 2024'!N9 -> SEGUROS DEL PAÍS | C17: =('Balance diciembre 2024'!N35)/1000 -> 286.31509 | D17: =('Balance Diciembre 2025'!M35)/1000 -> 324.75511 | E17: =IFERROR(D17/C17-1,0) -> 0.13425773 | F17: =D17-C17 -> 38.440014 | G17: =C17/M17 -> 0.2289525 | H17: =D17/N17 -> 0.23600431 | I17: =IFERROR(H17/G17-1,0) -> 0.030800339 | J17: =H17-G17 -> 0.0070518146 | L17: 8 | M17: =VLOOKUP(B17,'8. Primas y Siniestros Totales'!$B$10:$D$21,2,FALSE) -> 1250.5437 | N17: =VLOOKUP(B17,'8. Primas y Siniestros Totales'!$B$10:$D$21,3,FALSE) -> 1376.0558
A18: 9 | B18: ='Balance diciembre 2024'!M9 -> SEGUROS EQUIDAD | C18: =('Balance diciembre 2024'!M35)/1000 -> 316.80089 | D18: =('Balance Diciembre 2025'!L35)/1000 -> 315.0798 | E18: =IFERROR(D18/C18-1,0) -> -0.0054327412 | F18: =D18-C18 -> -1.7210973 | G18: =C18/M18 -> 0.43701093 | H18: =D18/N18 -> 0.52739898 | I18: =IFERROR(H18/G18-1,0) -> 0.20683246 | J18: =H18-G18 -> 0.090388047 | L18: 9 | M18: =VLOOKUP(B18,'8. Primas y Siniestros Totales'!$B$10:$D$21,2,FALSE) -> 724.9267 | N18: =VLOOKUP(B18,'8. Primas y Siniestros Totales'!$B$10:$D$21,3,FALSE) -> 597.42208
A19: 10 | B19: ='Balance diciembre 2024'!O9 -> SEGUROS LAFISE | C19: =('Balance diciembre 2024'!O35)/1000 -> 155.27668 | D19: =('Balance Diciembre 2025'!N35)/1000 -> 198.67952 | E19: =IFERROR(D19/C19-1,0) -> 0.27951934 | F19: =D19-C19 -> 43.402835 | G19: =C19/M19 -> 0.38461084 | H19: =D19/N19 -> 0.38623662 | I19: =IFERROR(H19/G19-1,0) -> 0.0042270581 | J19: =H19-G19 -> 0.0016257724 | L19: 10 | M19: =VLOOKUP(B19,'8. Primas y Siniestros Totales'!$B$10:$D$21,2,FALSE) -> 403.72414 | N19: =VLOOKUP(B19,'8. Primas y Siniestros Totales'!$B$10:$D$21,3,FALSE) -> 514.39845
A20: 11 | B20: ='Balance diciembre 2024'!P9 -> ASEGURADORA RURAL | C20: =('Balance diciembre 2024'!P35)/1000 -> 136.89848 | D20: =('Balance Diciembre 2025'!O35)/1000 -> 163.01565 | E20: =IFERROR(D20/C20-1,0) -> 0.19077766 | F20: =D20-C20 -> 26.117171 | G20: =C20/M20 -> 0.2919731 | H20: =D20/N20 -> 0.29928262 | I20: =IFERROR(H20/G20-1,0) -> 0.025034884 | J20: =H20-G20 -> 0.0073095128 | L20: 11 | M20: =VLOOKUP(B20,'8. Primas y Siniestros Totales'!$B$10:$D$21,2,FALSE) -> 468.87359 | N20: =VLOOKUP(B20,'8. Primas y Siniestros Totales'!$B$10:$D$21,3,FALSE) -> 544.688
A21: 12 | B21: ='Balance diciembre 2024'!Q9 -> ASSA CIA. DE SEGUROS | C21: =('Balance diciembre 2024'!Q35)/1000 -> 36.577194 | D21: =('Balance Diciembre 2025'!P35)/1000 -> 75.942922 | E21: =IFERROR(D21/C21-1,0) -> 1.076237 | F21: =D21-C21 -> 39.365728 | G21: =C21/M21 -> 0.042461714 | H21: =D21/N21 -> 0.070299732 | I21: =IFERROR(H21/G21-1,0) -> 0.65560279 | J21: =H21-G21 -> 0.027838018 | L21: 12 | M21: =VLOOKUP(B21,'8. Primas y Siniestros Totales'!$B$10:$D$21,2,FALSE) -> 861.41587 | N21: =VLOOKUP(B21,'8. Primas y Siniestros Totales'!$B$10:$D$21,3,FALSE) -> 1080.2733
A22: Total general | C22: =SUM(C10:C21) -> 7535.2302 | D22: =SUM(D10:D21) -> 8080.894 | E22: =IFERROR(D22/C22-1,0) -> 0.07241501 | F22: =D22-C22 -> 545.66377 | G22: =C22/M22 -> 0.40859651 | H22: =D22/N22 -> 0.4004063 | I22: =IFERROR(H22/G22-1,0) -> -0.02004474 | J22: =H22-G22 -> -0.0081902109 | M22: =SUM(M10:M21) -> 18441.739 | N22: =SUM(N10:N21) -> 20181.735

Sheet 4. Primas Por Cobrar
A1: Sector Asegurador Hondureño
A2: Principales Cuentas Contables e Indicadores Financieros
A3: ='1. Ramos Totales'!A3 -> Al 31 de diciembre de 2025
A4: (Valores en millones de Lempiras y Porcentajes)
A6: 4. Primas Por Cobrar
A8: No | B8: Compañía | C8: Período | E8: Variación | G8: Primas por Cobrar / Primas | I8: Variación | L8: PRIMAS | M8: PRIMAS
C9: ='1. Ramos Totales'!$B$9 -> 45657 | D9: ='1. Ramos Totales'!$C$9 -> 46022 | E9: Relativa | F9: Absoluta | G9: ='1. Ramos Totales'!$B$9 -> 45657 | H9: ='1. Ramos Totales'!$C$9 -> 46022 | I9: Relativa | J9: Absoluta | L9: 2023 | M9: 2024
A10: 1 | B10: ='Balance diciembre 2024'!I9 -> FICOHSA SEGUROS | C10: =('Balance diciembre 2024'!I16)/1000 -> 1090.2822 | D10: =('Balance Diciembre 2025'!H16)/1000 -> 1162.241 | E10: =IFERROR(D10/C10-1,0) -> 0.066000245 | F10: =D10-C10 -> 71.95889 | G10: =C10/L10 -> 0.24727475 | H10: =D10/M10 -> 0.23959765 | I10: =IFERROR(H10/G10-1,0) -> -0.031046845 | J10: =H10-G10 -> -0.0076771007 | L10: =VLOOKUP(B10,'8. Primas y Siniestros Totales'!$B$10:$D$21,2,FALSE) -> 4409.1933 | M10: =VLOOKUP(B10,'8. Primas y Siniestros Totales'!$B$10:$D$21,3,FALSE) -> 4850.8033
